{
    "DOI": "http://dx.doi.org/doi:10.23728/b2share.d8b3db5e46204709964990d656a4fedc",
    "DiscHierarchy": [],
    "Discipline": "Not stated",
    "MetaDataAccess": "https://b2share.eudat.eu/api/oai2d?verb=GetRecord&metadataPrefix=marcxml&identifier=oai:b2share.eudat.eu:b2rec/d8b3db5e46204709964990d656a4fedc",
    "PID": "http://hdl.handle.net/11304/e2d02cfb-eea1-4475-bd26-4ff9a7727075",
    "PublicationTimestamp": "2018-01-31T11:59:59Z",
    "PublicationYear": [
        "2018"
    ],
    "RelatedIdentifier": [
        "http://hdl.handle.net/11304/e2d02cfb-eea1-4475-bd26-4ff9a7727075",
        "10.23728/b2share.d8b3db5e46204709964990d656a4fedc",
        "https://b2share.eudat.eu/api/records/d8b3db5e46204709964990d656a4fedc",
        "oai:b2share.eudat.eu:b2rec/d8b3db5e46204709964990d656a4fedc"
    ],
    "Rights": [
        "info:eu-repo/semantics/openAccess"
    ],
    "author": [
        "Luca Franci"
    ],
    "fulltext": "oai:b2share.eudat.eu:b2rec/d8b3db5e46204709964990d656a4fedc;2018-01-31T12:05:00Z;e9b9792e-79fb-4b07-b6b4-b9c2bd06d095;Luca Franci;2018-01-31T12:05:00.092734+00:00;This is a small collection of movies from 2D and 3D high-resolution hybrid particle-in-cell  simulations of plasma turbulence performed with the hybrid code CAMELIA. The evolution of the magnetic field is shown in a large 3D grid (3D_B2_Wholegrid.avi), in a large 2D grid (2D_B2_WholeGrid.avi) and in two smaller 2D subgrids (2D_B2_SubGrid1.avi and 2D_B2_SubGrid2.avi)\nThese movie were shown by L. Franci during his talk \"Hybrid simulations of plasma turbulence \u2028in support of space missions:  toward an archive for numerical results  with EUDAT services\" at the \"EUDAT Conference - Putting the EOSC vision into practice\" in Porto (24th January 2018). \nMore details about CAMELIA can be found here: http://terezka.asu.cas.cz/helinger/camelia.html and https://arxiv.org/abs/1712.03930. The analysis and discussion of the 2D and 3D simulations shown in the movies can be found here: http://dx.doi.org/10.3847/2041-8213/aa93fb and http://dx.doi.org/10.3847/1538-4357/aaa3e8.;http://hdl.handle.net/11304/e2d02cfb-eea1-4475-bd26-4ff9a7727075;10.23728/b2share.d8b3db5e46204709964990d656a4fedc;https://b2share.eudat.eu/api/records/d8b3db5e46204709964990d656a4fedc;oai:b2share.eudat.eu:b2rec/d8b3db5e46204709964990d656a4fedc;info:eu-repo/semantics/openAccess;Turbulence;Astrophysical plasmas;Solar wind;Movies from the talk \"Hybrid simulations of plasma turbulence \u2028in support of space missions:  toward an archive for numerical results  with EUDAT services\"",
    "group": "b2share",
    "groups": [
        {
            "name": "b2share"
        }
    ],
    "name": "00cc5cb4-cfb2-5876-9e41-071cf49d04d2",
    "notes": [
        "This is a small collection of movies from 2D and 3D high-resolution hybrid particle-in-cell  simulations of plasma turbulence performed with the hybrid code CAMELIA. The evolution of the magnetic field is shown in a large 3D grid (3D_B2_Wholegrid.avi), in a large 2D grid (2D_B2_WholeGrid.avi) and in two smaller 2D subgrids (2D_B2_SubGrid1.avi and 2D_B2_SubGrid2.avi)\nThese movie were shown by L. Franci during his talk \"Hybrid simulations of plasma turbulence \u2028in support of space missions:  toward an archive for numerical results  with EUDAT services\" at the \"EUDAT Conference - Putting the EOSC vision into practice\" in Porto (24th January 2018). \nMore details about CAMELIA can be found here: http://terezka.asu.cas.cz/helinger/camelia.html and https://arxiv.org/abs/1712.03930. The analysis and discussion of the 2D and 3D simulations shown in the movies can be found here: http://dx.doi.org/10.3847/2041-8213/aa93fb and http://dx.doi.org/10.3847/1538-4357/aaa3e8."
    ],
    "oai_identifier": [
        "oai:b2share.eudat.eu:b2rec/d8b3db5e46204709964990d656a4fedc"
    ],
    "oai_set": [
        "e9b9792e-79fb-4b07-b6b4-b9c2bd06d095"
    ],
    "state": "active",
    "tags": [
        {
            "name": "Turbulence"
        },
        {
            "name": "Astrophysical plasmas"
        },
        {
            "name": "Solar wind"
        }
    ],
    "title": [
        "Movies from the talk \"Hybrid simulations of plasma turbulence \u2028in support of space missions:  toward an archive for numerical results  with EUDAT services\""
    ],
    "url": "https://b2share.eudat.eu/api/records/d8b3db5e46204709964990d656a4fedc"
}