{
    "Contact": [
        "Buddenbaum, Henning"
    ],
    "Contributor": [
        "Federal Ministry of Economic Affairs and Energy"
    ],
    "DOI": "http://dx.doi.org/doi:10.5880/enmap.2015.005",
    "DiscHierarchy": [
        "4.4.6",
        "Geosciences",
        "Earth System Research"
    ],
    "Discipline": "Earth System Research",
    "Language": [
        "English"
    ],
    "MetaDataAccess": "http://doidb.wdc-terra.org/oaip/oai?verb=GetRecord&metadataPrefix=oai_datacite&identifier=oai:doidb.wdc-terra.org:6140",
    "MetadataAccess": [
        "oai:doidb.wdc-terra.org:6140"
    ],
    "PublicationTimestamp": "2015-07-01T11:59:59Z",
    "PublicationYear": [
        "2015"
    ],
    "Publisher": [
        "GFZ Data Services"
    ],
    "ResourceType": [
        "Dataset"
    ],
    "Rights": [
        "CC BY-SA 4.0"
    ],
    "SpatialCoverage": "(50N-50N,7 E-7 E)",
    "TempCoverageBegin": 63566420399,
    "TempCoverageEnd": 63566420399,
    "TemporalCoverage": " period : ( 2015-05-05T11:59:59Z - 2015-05-05T11:59:59Z ) ",
    "TemporalCoverage:BeginDate": "2015-05-05T11:59:59Z",
    "TemporalCoverage:EndDate": "2015-05-05T11:59:59Z",
    "author": [
        "Dotzler, Sandra",
        "Buddenbaum, Henning",
        "Hill, Joachim"
    ],
    "fulltext": "oai:doidb.wdc-terra.org:6140;2016-11-25T13:58:02Z;DOIDB;DOIDB.ENMAP;false;3;DOIDB.ENMAP;10.5880/enmap.2015.005;Buddenbaum, Henning;0000-0002-0956-5628;University of Trier, Environmental Remote Sensing and Geoinformatics, Trier, Germany;Dotzler, Sandra;0000-0002-8171-2944;University of Trier, Environmental Remote Sensing and Geoinformatics, Trier, Germany;Hill, Joachim;University of Trier, Environmental Remote Sensing and Geoinformatics, Trier, Germany;Nationalpark Hunsr\u00fcck-Hochwald, 2014-05-05 - An EnMAP Preparatory Flight Campaign (Datasets);GFZ Data Services;2015;Imaging Spectroscopy;Vegetation Ecology;Forest;Buddenbaum, Henning;0000-0002-0956-5628;University of Trier, Environmental Remote Sensing and Geoinformatics, Trier, Germany;Buddenbaum, Henning;0000-0002-0956-5628;University of Trier, Environmental Remote Sensing and Geoinformatics, Trier, Germany;Dotzler, Sandra;0000-0002-8171-2944;University of Trier, Environmental Remote Sensing and Geoinformatics, Trier, Germany;Dotzler, Sandra;0000-0002-8171-2944;University of Trier, Environmental Remote Sensing and Geoinformatics, Trier, Germany;Hill, Joachim;University of Trier, Environmental Remote Sensing and Geoinformatics, Trier, Germany;Federal Ministry of Economic Affairs and Energy;Federal Ministry of Economic Affairs and Energy;Foerster, Saskia;0000-0001-7752-7394;GFZ German Research Centre for Geosciences;Kuester, Theres;GFZ German Research Centre for Geosciences;Elger, Kirsten;0000-0001-5140-8602;GFZ German Research Centre for Geosciences;2015-05-05;2015-05-05T12:22:00/2015-05-05T14:21:00;eng;Dataset;10.2312/enmap.2015.005;10.1080/01431160500285076;10.1080/01431161.2013.776721;10.3390/rs70708830;http://www.enmap.org/?q=flights;CC BY-SA 4.0;The dataset consists of hyperspectral imagery acquired during airplane overflights on 5th May 2014 that contain 242 spectral bands, ranging from VIS to SWIR (423 - 2438 nm) wavelength regions. It covers an area of about 116 km\u00b2 which is dominated by spruce and beech forests. The flight campaign was part of several campaigns aiming at the creation of a multitemporal hyperspectral data set of the newly founded National Park Hunsr\u00fcck-Hochwald in Rhineland Palatinate, Germany. ;The Environmental Mapping and Analysis Program (EnMAP) is a German hyperspectral satellite mission that aims at monitoring and characterizing the Earth\u2019s environment on a global scale. EnMAP serves to measure and model key dynamic processes of the Earth\u2019s ecosystems by extracting geochemical, biochemical and biophysical parameters, which provide information on the status and evolution of various terrestrial and aquatic ecosystems. In the frame of the EnMAP preparatory phase, pre-flight campaigns including airborne and in-situ measurements in different environments and for several application fields are being conducted. The main purpose of these campaigns is to support the development of scientific applications for EnMAP. In addition, the acquired data are input in the EnMAP end-to-end simulation tool (EeteS) and are employed to test data pre-processing and calibration-validation methods. The campaign data are made freely available to the scientific community under a Creative Commons Attribution-ShareAlike 4.0 International License. An overview of all available data is provided in in the EnMAP Flight Campaigns Metadata Portal http://www.enmap.org/?q=flights.;49.62316641036846 6.93511962890625 49.75997752330658 7.1575927734375;HySpex, 22 Flight Lines",
    "group": "enmap",
    "groups": [
        {
            "name": "enmap"
        }
    ],
    "name": "d71bddc0-2d29-5c77-95fb-1ad37dda327d",
    "notes": [
        "The dataset consists of hyperspectral imagery acquired during airplane overflights on 5th May 2014 that contain 242 spectral bands, ranging from VIS to SWIR (423 - 2438 nm) wavelength regions. It covers an area of about 116 km\u00b2 which is dominated by spruce and beech forests. The flight campaign was part of several campaigns aiming at the creation of a multitemporal hyperspectral data set of the newly founded National Park Hunsr\u00fcck-Hochwald in Rhineland Palatinate, Germany. ",
        "The Environmental Mapping and Analysis Program (EnMAP) is a German hyperspectral satellite mission that aims at monitoring and characterizing the Earth\u2019s environment on a global scale. EnMAP serves to measure and model key dynamic processes of the Earth\u2019s ecosystems by extracting geochemical, biochemical and biophysical parameters, which provide information on the status and evolution of various terrestrial and aquatic ecosystems. In the frame of the EnMAP preparatory phase, pre-flight campaigns including airborne and in-situ measurements in different environments and for several application fields are being conducted. The main purpose of these campaigns is to support the development of scientific applications for EnMAP. In addition, the acquired data are input in the EnMAP end-to-end simulation tool (EeteS) and are employed to test data pre-processing and calibration-validation methods. The campaign data are made freely available to the scientific community under a Creative Commons Attribution-ShareAlike 4.0 International License. An overview of all available data is provided in in the EnMAP Flight Campaigns Metadata Portal http://www.enmap.org/?q=flights."
    ],
    "oai_identifier": [
        "oai:doidb.wdc-terra.org:6140"
    ],
    "oai_set": [
        "DOIDB",
        "DOIDB.ENMAP"
    ],
    "spatial": "{\"type\":\"Polygon\",\"coordinates\":[[[6.93511962890625,49.62316641036846],[6.93511962890625,49.75997752330658],[7.1575927734375,49.75997752330658],[7.1575927734375,49.62316641036846],[6.93511962890625,49.62316641036846]]]}",
    "state": "active",
    "tags": [
        {
            "name": "Imaging Spectroscopy"
        },
        {
            "name": "Vegetation Ecology"
        },
        {
            "name": "Forest"
        }
    ],
    "title": [
        "Nationalpark Hunsr\u00fcck-Hochwald, 2014-05-05 - An EnMAP Preparatory Flight Campaign (Datasets)"
    ],
    "url": ""
}