{
    "Contact": [
        "Michael Lehning"
    ],
    "Contributor": [
        "EnviDat"
    ],
    "DOI": "http://dx.doi.org/doi:10.16904/envidat.47",
    "DiscHierarchy": [
        "4.4.7",
        "Geosciences",
        "Environmental Research"
    ],
    "Discipline": "Environmental Research",
    "Format": [
        "XLSX",
        "ZIP"
    ],
    "Language": [
        "English"
    ],
    "MetaDataAccess": "https://www.envidat.ch/oai?verb=GetRecord&metadataPrefix=datacite&identifier=oai:envidat.ch:90e36ede-4301-43f3-b0cb-b524d8c81f6b",
    "MetadataAccess": [
        "oai:envidat.ch:90e36ede-4301-43f3-b0cb-b524d8c81f6b"
    ],
    "PublicationTimestamp": "2018-07-01T11:59:59Z",
    "PublicationYear": [
        "2018"
    ],
    "Publisher": [
        "EnviDat"
    ],
    "RelatedIdentifier": [
        "https://www.envidat.ch/dataset/pv_snow_mountain"
    ],
    "ResourceType": [
        "Dataset"
    ],
    "Rights": [
        "Open Data Commons Open Database License (ODbL)"
    ],
    "SpatialCoverage": "(46N-48N,6 E-10E)",
    "TempCoverageBegin": 63679694399,
    "TempCoverageEnd": 63679694399,
    "TemporalCoverage": " point in time : 2018-12-06T11:59:59Z",
    "TemporalCoverage:BeginDate": "2018-12-06T11:59:59Z",
    "TemporalCoverage:EndDate": "2018-12-06T11:59:59Z",
    "author": [
        "Annelen Kahl",
        "J\u00e9r\u00f4me Dujardin",
        "Michael Lehning"
    ],
    "fulltext": "oai:envidat.ch:90e36ede-4301-43f3-b0cb-b524d8c81f6b;2018-12-09T00:32:54Z;10.16904/envidat.47;Annelen Kahl;WSL/SLF and EPFL;J\u00e9r\u00f4me Dujardin;EPFL;Michael Lehning;0000-0002-8442-0875;WSL/SLF and EPFL;Dataset on PV Production in Snow Covered Mountains;2018;EnviDat;ALBEDO;ENERGY;IRRADIANCE;MOUNTAIN;PHOTOVOLTAIC;REFLECTION;SNOW;Michael Lehning;0000-0002-8442-0875;WSL/SLF and EPFL;2018-12-06;en;Dataset;https://www.envidat.ch/dataset/pv_snow_mountain;2654822 bytes;XLSX;ZIP;1.0;Open Data Commons Open Database License (ODbL);### Overview\nThe SUNWELL Modelling Environment is a combination of data and code that models electricity production from satellite-derived irradiance data and other spatial data sets for all of Switzerland. This ensemble accompanies the publication \"The bright side of PV production in snow-covered mountains\", published in the Proceedings of the National Academy of Science and reproduces all results and figures of. Code and resources are in their original form (with documentation). A new version with a more generalized application to PV modelling and with more flexibility in terms of input and output formats will be released in the coming months.\n\n### Format\nAll code is written and has to be executed in Matlab. The input and output data sets are also in the Matlab-specific .mat format. Whenever publicly available, the original data is provided as geotif, .xlsx or other common format. \nThis is the case for:\n\n- Digital Elevation Model (InputsFromMatlab/MSG/OriginalData/ASTERDEM), \n- Landsurface cover type (InputsFromMatlab/MSG/OriginalData/CORINE), \n- Population Density (InputsFromMatlab/MSG/OriginalData/popdensRaster, \n- Electricity production from three of our validation sites (/Validation/WSL), \n- Measured irradiance for two validation sites (/Validation/ASRB)\nThe \u2018Metadata\u2019 documents in the respective folders provide further information about the data sources and processing. Figures are produced either in .pdf or .png format. \n\n### Structure\nThe central level of the SUNWELL environment holds the 5 Mains, which run the different modelling aspects of the paper; each code is documented separately. Additional code is located in the __\u2018DataProcessing\u2019__ and the __\u2018functions\u2019__ folder. Functions are called in the different Mains.\n\n__\u2018InputsFromMatlab\u2019__ contains the radiation and albedo input data sets in separate subfolders (SIS/SISDIR/ALB). The original data is not publicly available, but can be requested for research purposes free of charge. We provide a processed subset of the data set that was used to run the SUNWELL simulations. The MSG subfolder contains additional spatial input data sets.\n\n__\u2018Outputs\u2019__ contains the output files from the different mains (matching names, Main_CHallpixels.m \uf0e0 Prod_CHallpixels)\n\n__\u2018Publication_figures\u2019__ contains all individual figures from the PNAS publication, as well as the generating code (/code_plot) and the power point figures (/ppts) that provide the combined final figures.\n\n__\u2018Validation\u2019__ contains the data sets used in the model validation:\n\n- Electricity production from three of our validation sites (/WSL), \n- Measured irradiance for two validation sites (/ASRB)\n\n__Electricity__ production from a validation site at Lac des Toules in Wallis (/LDT), this data set was provided under an NDA and cannot be made publicly available. \n\n__Paper Citation:__\n > _Annelen Kahl; J\u00e9r\u00f4me Dujardin; Michael Lehning (2018). Dataset on PV Production in Snow Covered Mountains. PNAS - Proceedings of the National Academy of Sciences. (in press)_;45.81802 5.95587 47.80838 10.49203;Switzerland",
    "group": "envidat",
    "groups": [
        {
            "name": "envidat"
        }
    ],
    "name": "2a3db70e-fc2b-50fe-a30a-0f7b00bc160b",
    "notes": [
        "### Overview\nThe SUNWELL Modelling Environment is a combination of data and code that models electricity production from satellite-derived irradiance data and other spatial data sets for all of Switzerland. This ensemble accompanies the publication \"The bright side of PV production in snow-covered mountains\", published in the Proceedings of the National Academy of Science and reproduces all results and figures of. Code and resources are in their original form (with documentation). A new version with a more generalized application to PV modelling and with more flexibility in terms of input and output formats will be released in the coming months.\n\n### Format\nAll code is written and has to be executed in Matlab. The input and output data sets are also in the Matlab-specific .mat format. Whenever publicly available, the original data is provided as geotif, .xlsx or other common format. \nThis is the case for:\n\n- Digital Elevation Model (InputsFromMatlab/MSG/OriginalData/ASTERDEM), \n- Landsurface cover type (InputsFromMatlab/MSG/OriginalData/CORINE), \n- Population Density (InputsFromMatlab/MSG/OriginalData/popdensRaster, \n- Electricity production from three of our validation sites (/Validation/WSL), \n- Measured irradiance for two validation sites (/Validation/ASRB)\nThe \u2018Metadata\u2019 documents in the respective folders provide further information about the data sources and processing. Figures are produced either in .pdf or .png format. \n\n### Structure\nThe central level of the SUNWELL environment holds the 5 Mains, which run the different modelling aspects of the paper; each code is documented separately. Additional code is located in the __\u2018DataProcessing\u2019__ and the __\u2018functions\u2019__ folder. Functions are called in the different Mains.\n\n__\u2018InputsFromMatlab\u2019__ contains the radiation and albedo input data sets in separate subfolders (SIS/SISDIR/ALB). The original data is not publicly available, but can be requested for research purposes free of charge. We provide a processed subset of the data set that was used to run the SUNWELL simulations. The MSG subfolder contains additional spatial input data sets.\n\n__\u2018Outputs\u2019__ contains the output files from the different mains (matching names, Main_CHallpixels.m \uf0e0 Prod_CHallpixels)\n\n__\u2018Publication_figures\u2019__ contains all individual figures from the PNAS publication, as well as the generating code (/code_plot) and the power point figures (/ppts) that provide the combined final figures.\n\n__\u2018Validation\u2019__ contains the data sets used in the model validation:\n\n- Electricity production from three of our validation sites (/WSL), \n- Measured irradiance for two validation sites (/ASRB)\n\n__Electricity__ production from a validation site at Lac des Toules in Wallis (/LDT), this data set was provided under an NDA and cannot be made publicly available. \n\n__Paper Citation:__\n > _Annelen Kahl; J\u00e9r\u00f4me Dujardin; Michael Lehning (2018). Dataset on PV Production in Snow Covered Mountains. PNAS - Proceedings of the National Academy of Sciences. (in press)_"
    ],
    "oai_identifier": [
        "oai:envidat.ch:90e36ede-4301-43f3-b0cb-b524d8c81f6b"
    ],
    "oai_set": "",
    "spatial": "{\"type\":\"Polygon\",\"coordinates\":[[[5.95587,45.81802],[5.95587,47.80838],[10.49203,47.80838],[10.49203,45.81802],[5.95587,45.81802]]]}",
    "state": "active",
    "tags": [
        {
            "name": "ALBEDO"
        },
        {
            "name": "ENERGY"
        },
        {
            "name": "IRRADIANCE"
        },
        {
            "name": "MOUNTAIN"
        },
        {
            "name": "PHOTOVOLTAIC"
        },
        {
            "name": "REFLECTION"
        },
        {
            "name": "SNOW"
        }
    ],
    "title": [
        "Dataset on PV Production in Snow Covered Mountains"
    ],
    "url": ""
}