{
    "Contact": [
        "Yves B\u00fchler"
    ],
    "Contributor": [
        "EnviDat"
    ],
    "DOI": "http://dx.doi.org/doi:10.16904/envidat.31",
    "DiscHierarchy": [
        "4.4.7",
        "Geosciences",
        "Environmental Research"
    ],
    "Discipline": "Environmental Research",
    "Format": [
        "TIFF",
        "tfw"
    ],
    "Language": [
        "English"
    ],
    "MetaDataAccess": "https://www.envidat.ch/oai?verb=GetRecord&metadataPrefix=datacite&identifier=oai:envidat.ch:84db9938-9af5-4ae1-8e30-cb45c61fc274",
    "MetadataAccess": [
        "oai:envidat.ch:84db9938-9af5-4ae1-8e30-cb45c61fc274"
    ],
    "PublicationTimestamp": "2016-07-01T11:59:59Z",
    "PublicationYear": [
        "2016"
    ],
    "Publisher": [
        "The Cryosphere"
    ],
    "RelatedIdentifier": [
        "https://www.envidat.ch/dataset/uas-based-snow-depth-maps-bramabuel-davos-ch"
    ],
    "ResourceType": [
        "tif raster"
    ],
    "Rights": [
        "Open Data Commons Open Database License (ODbL)"
    ],
    "SpatialCoverage": "(47N-47N,10E-10E)",
    "TempCoverageBegin": 63564605999,
    "TempCoverageEnd": 63564605999,
    "TemporalCoverage": " point in time : 2015-04-14T11:59:59Z",
    "TemporalCoverage:BeginDate": "2015-04-14T11:59:59Z",
    "TemporalCoverage:EndDate": "2015-04-14T11:59:59Z",
    "author": [
        "Yves B\u00fchler"
    ],
    "fulltext": "oai:envidat.ch:84db9938-9af5-4ae1-8e30-cb45c61fc274;2018-12-06T17:36:41Z;10.16904/envidat.31;Yves B\u00fchler;SLF;UAS based snow depth maps Br\u00e4mab\u00fcel, Davos, CH;high spatial resolution snow depth map;2016;The Cryosphere;REMOTE SENSING;SNOW;SNOW DEPTH;SWE;UAS;Yves B\u00fchler;SLF;2015-04-14;en;tif raster;https://www.envidat.ch/dataset/uas-based-snow-depth-maps-bramabuel-davos-ch;163529181 bytes;89 bytes;TIFF;tfw;1.0;Open Data Commons Open Database License (ODbL);This snow depth map was generated 14 January 2015, close to peak of winter accumulation, applying Unmanned Aerial System digital surface models with a spatial resolution of 10 cm. The covered area is 285'000 m2 at the top of Br\u00e4mab\u00fcel, 2490 m a.s.l. covering all expositions. Coordinate system: CH1903LV03.\n\nA detailed description is given here:\n\nB\u00fchler, Y., Adams, M. S., B\u00f6sch, R., and Stoffel, A.: Mapping snow depth in alpine terrain with unmanned aerial systems (UASs): potential and limitations, The Cryosphere, 10, 1075-1088, 10.5194/tc-10-1075-2016, 2016.\n\nAbstract:\nDetailed information on the spatial and temporal distribution, and variability of snow depth (HS) is a crucial input for numerous applications in hydrology, climatology, ecology and avalanche research. Nowadays, snow depth distribution is usually estimated by combining point measurements from weather stations or observers in the field with spatial interpolation algorithms. However, even a dense measurement network is not able to capture the large spatial variability of snow depth in alpine terrain. \nRemote sensing methods, such as laser scanning or digital photogrammetry, have recently been successfully applied to map snow depth variability at local and regional scales. However, such data acquisition is costly, if manned airplanes are involved. The effectiveness of ground-based measurements on the other hand, is often hindered by occlusions, due to the complex terrain or acute viewing angles. In this paper, we investigate the application of unmanned aerial systems (UAS), in combination with structure-from-motion photogrammetry, to map snow depth distribution. Such systems have the advantage that they are comparatively cost-effective and can be applied very flexibly to cover also otherwise inaccessible terrain. In this study we map snow depth at two different locations: a) a sheltered location at the bottom of the Fl\u00fcela valley (1900 m a.s.l.) and b) an exposed location (2500 m a.s.l.) on a peak in the ski resort Jakobshorn, both in the vicinity of Davos, Switzerland. At the first test site, we monitor the ablation on three different dates. We validate the photogrammetric snow depth maps using simultaneously acquired manual snow depth measurements. The resulting snow depth values have a root mean square error (RMSE) better than 0.07 to 0.15 m on meadows and rocks and a RMSE better than 0.30 m on sections covered by bushes or tall grass. This new measurement technology opens the door for efficient, flexible, repeatable and cost effective snow depth monitoring for various applications, investigating the worlds cryosphere.;46.7827679855 9.84855651855 46.7809459618 9.8459815979;Br\u00e4mab\u00fcl, Jakobshorn, Davos, Switzerland",
    "group": "envidat",
    "groups": [
        {
            "name": "envidat"
        }
    ],
    "name": "2e6fc4dc-1ef2-5533-b25c-0ebb27ab2593",
    "notes": [
        "This snow depth map was generated 14 January 2015, close to peak of winter accumulation, applying Unmanned Aerial System digital surface models with a spatial resolution of 10 cm. The covered area is 285'000 m2 at the top of Br\u00e4mab\u00fcel, 2490 m a.s.l. covering all expositions. Coordinate system: CH1903LV03.\n\nA detailed description is given here:\n\nB\u00fchler, Y., Adams, M. S., B\u00f6sch, R., and Stoffel, A.: Mapping snow depth in alpine terrain with unmanned aerial systems (UASs): potential and limitations, The Cryosphere, 10, 1075-1088, 10.5194/tc-10-1075-2016, 2016.\n\nAbstract:\nDetailed information on the spatial and temporal distribution, and variability of snow depth (HS) is a crucial input for numerous applications in hydrology, climatology, ecology and avalanche research. Nowadays, snow depth distribution is usually estimated by combining point measurements from weather stations or observers in the field with spatial interpolation algorithms. However, even a dense measurement network is not able to capture the large spatial variability of snow depth in alpine terrain. \nRemote sensing methods, such as laser scanning or digital photogrammetry, have recently been successfully applied to map snow depth variability at local and regional scales. However, such data acquisition is costly, if manned airplanes are involved. The effectiveness of ground-based measurements on the other hand, is often hindered by occlusions, due to the complex terrain or acute viewing angles. In this paper, we investigate the application of unmanned aerial systems (UAS), in combination with structure-from-motion photogrammetry, to map snow depth distribution. Such systems have the advantage that they are comparatively cost-effective and can be applied very flexibly to cover also otherwise inaccessible terrain. In this study we map snow depth at two different locations: a) a sheltered location at the bottom of the Fl\u00fcela valley (1900 m a.s.l.) and b) an exposed location (2500 m a.s.l.) on a peak in the ski resort Jakobshorn, both in the vicinity of Davos, Switzerland. At the first test site, we monitor the ablation on three different dates. We validate the photogrammetric snow depth maps using simultaneously acquired manual snow depth measurements. The resulting snow depth values have a root mean square error (RMSE) better than 0.07 to 0.15 m on meadows and rocks and a RMSE better than 0.30 m on sections covered by bushes or tall grass. This new measurement technology opens the door for efficient, flexible, repeatable and cost effective snow depth monitoring for various applications, investigating the worlds cryosphere."
    ],
    "oai_identifier": [
        "oai:envidat.ch:84db9938-9af5-4ae1-8e30-cb45c61fc274"
    ],
    "oai_set": "",
    "spatial": "{\"type\":\"Polygon\",\"coordinates\":[[[9.84855651855,46.7827679855],[9.84855651855,46.7809459618],[9.8459815979,46.7809459618],[9.8459815979,46.7827679855],[9.84855651855,46.7827679855]]]}",
    "state": "active",
    "tags": [
        {
            "name": "REMOTE SENSING"
        },
        {
            "name": "SNOW"
        },
        {
            "name": "SNOW DEPTH"
        },
        {
            "name": "SWE"
        },
        {
            "name": "UAS"
        }
    ],
    "title": [
        "UAS based snow depth maps Br\u00e4mab\u00fcel, Davos, CH",
        "high spatial resolution snow depth map"
    ],
    "url": ""
}