{
    "Contact": [
        "Andrin Caviezel"
    ],
    "Contributor": [
        "EnviDat"
    ],
    "DOI": "http://dx.doi.org/doi:10.16904/envidat.37",
    "DiscHierarchy": [
        "4.4.7",
        "Geosciences",
        "Environmental Research"
    ],
    "Discipline": "Environmental Research",
    "Format": [
        "application/x-7z-compressed",
        "ZIP"
    ],
    "Language": [
        "English"
    ],
    "MetaDataAccess": "https://www.envidat.ch/oai?verb=GetRecord&metadataPrefix=datacite&identifier=oai:envidat.ch:5b7a47bf-cbea-42a0-879f-ea2ccd17e82f",
    "MetadataAccess": [
        "oai:envidat.ch:5b7a47bf-cbea-42a0-879f-ea2ccd17e82f"
    ],
    "PublicationTimestamp": "2018-07-01T11:59:59Z",
    "PublicationYear": [
        "2018"
    ],
    "Publisher": [
        "WSL Institute for Snow and Avalanche Research SLF"
    ],
    "RelatedIdentifier": [
        "https://www.envidat.ch/dataset/experimental-rockfall-dataset-tschamut-grisons-switzerland"
    ],
    "ResourceType": [
        "Dataset"
    ],
    "Rights": [
        "Open Data Commons Open Database License (ODbL)"
    ],
    "SpatialCoverage": "(47N-47N,9 E-9 E)",
    "TempCoverageBegin": 63658609199,
    "TempCoverageEnd": 63658609199,
    "TemporalCoverage": " point in time : 2018-04-06T11:59:59Z",
    "TemporalCoverage:BeginDate": "2018-04-06T11:59:59Z",
    "TemporalCoverage:EndDate": "2018-04-06T11:59:59Z",
    "author": [
        "Andrin Caviezel",
        "Perry Bartelt",
        "Marc Christen",
        "Yves B\u00fchler"
    ],
    "fulltext": "oai:envidat.ch:5b7a47bf-cbea-42a0-879f-ea2ccd17e82f;2018-12-09T00:23:44Z;10.16904/envidat.37;Andrin Caviezel;0000-0001-6249-4913;WSL Institute for Snow and Avalanche Research SLF;Yves B\u00fchler;WSL Institute for Snow and Avalanche Research SLF;Marc Christen;WSL Institute for Snow and Avalanche Research SLF;Perry Bartelt;WSL Institute for Snow and Avalanche Research SLF;Induced Rockfall Dataset (Small Rock Experimental Campaign), Tschamut, Grisons, Switzerland;2018;WSL Institute for Snow and Avalanche Research SLF;DEM;DEPOSITION POINTS;INDUCED ROCKFALL;ROCKFALL;ROCKFALL EXPERIMENTS;ROCKFALL RUNOUT;SENSOR STREAM;STONENODE;STONENODEDATA;Andrin Caviezel;0000-0001-6249-4913;WSL Institute for Snow and Avalanche Research SLF;2018-04-06;en;Dataset;https://www.envidat.ch/dataset/experimental-rockfall-dataset-tschamut-grisons-switzerland;83833546 bytes;6899716 bytes;ZIP;application/x-7z-compressed;1.0;Open Data Commons Open Database License (ODbL);#Dataset of an experimental campaign of induced rockfall in Tschamut, Grisons, Switzerland. \n\nThe data archive contains site specific geographical data such as DEM and orthophoto as well as the deposition points of manually induced rockfall by releasing differently shaped boulders with 30\u201380 kg of mass. Additionally available are all the StoneNode data streams for rocks equipped with a sensor. The data set consists of \n</ul>\n* Deposition points from two series (wet (27/10/2016) and frozen (08/12/2016) ground)  \n* Digital Elevation Model (grid resolution 2 m) obtained via UAV\n* Orthophoto (5 cm resolution) obtained via UAV\n* Digitized rock point clouds (.pts input files for RAMMS::ROCKFALL)\n* StoneNode v1.0 raw data stream for equipped rocks.\n\nFurther information is found in\n</ul>\n* __A. Caviezel__ et al., _Design and Evaluation of a Low-Power Sensor Device for Induced Rockfall Experiments_, IEEE Transactions on Instrumentation and Measurement, 2018, 67, 767-779, http://ieeexplore.ieee.org/document/8122020/\n* __ P. Niklaus__ et al., _StoneNode: A low-power sensor device for induced rockfall experiments_, 2017 IEEE Sensors Applications Symposium (SAS), 2017, 1-6, http://ieeexplore.ieee.org/document/7894081/;46.6518076158 8.70076417923 46.6540464071 8.70375752449;Switzerland",
    "group": "envidat",
    "groups": [
        {
            "name": "envidat"
        }
    ],
    "name": "34de5744-e093-539f-88b3-b8ec716fa68c",
    "notes": [
        "#Dataset of an experimental campaign of induced rockfall in Tschamut, Grisons, Switzerland. \n\nThe data archive contains site specific geographical data such as DEM and orthophoto as well as the deposition points of manually induced rockfall by releasing differently shaped boulders with 30\u201380 kg of mass. Additionally available are all the StoneNode data streams for rocks equipped with a sensor. The data set consists of \n</ul>\n* Deposition points from two series (wet (27/10/2016) and frozen (08/12/2016) ground)  \n* Digital Elevation Model (grid resolution 2 m) obtained via UAV\n* Orthophoto (5 cm resolution) obtained via UAV\n* Digitized rock point clouds (.pts input files for RAMMS::ROCKFALL)\n* StoneNode v1.0 raw data stream for equipped rocks.\n\nFurther information is found in\n</ul>\n* __A. Caviezel__ et al., _Design and Evaluation of a Low-Power Sensor Device for Induced Rockfall Experiments_, IEEE Transactions on Instrumentation and Measurement, 2018, 67, 767-779, http://ieeexplore.ieee.org/document/8122020/\n* __ P. Niklaus__ et al., _StoneNode: A low-power sensor device for induced rockfall experiments_, 2017 IEEE Sensors Applications Symposium (SAS), 2017, 1-6, http://ieeexplore.ieee.org/document/7894081/"
    ],
    "oai_identifier": [
        "oai:envidat.ch:5b7a47bf-cbea-42a0-879f-ea2ccd17e82f"
    ],
    "oai_set": "",
    "spatial": "{\"type\":\"Polygon\",\"coordinates\":[[[8.70076417923,46.6518076158],[8.70076417923,46.6540464071],[8.70375752449,46.6540464071],[8.70375752449,46.6518076158],[8.70076417923,46.6518076158]]]}",
    "state": "active",
    "tags": [
        {
            "name": "DEM"
        },
        {
            "name": "DEPOSITION POINTS"
        },
        {
            "name": "INDUCED ROCKFALL"
        },
        {
            "name": "ROCKFALL"
        },
        {
            "name": "ROCKFALL EXPERIMENTS"
        },
        {
            "name": "ROCKFALL RUNOUT"
        },
        {
            "name": "SENSOR STREAM"
        },
        {
            "name": "STONENODE"
        },
        {
            "name": "STONENODEDATA"
        }
    ],
    "title": [
        "Induced Rockfall Dataset (Small Rock Experimental Campaign), Tschamut, Grisons, Switzerland"
    ],
    "url": ""
}