{
    "Contact": [
        "Lars Waser"
    ],
    "Contributor": [
        "EnviDat"
    ],
    "DOI": "http://dx.doi.org/doi:10.16904/1000001.3",
    "DiscHierarchy": [
        "4.4.7",
        "Geosciences",
        "Environmental Research"
    ],
    "Discipline": "Environmental Research",
    "Format": [
        "PDF",
        "TXT",
        "JPEG"
    ],
    "Language": [
        "English"
    ],
    "MetaDataAccess": "https://www.envidat.ch/oai?verb=GetRecord&metadataPrefix=datacite&identifier=oai:envidat.ch:82d763fa-123a-4648-b827-0dec02a5efbc",
    "MetadataAccess": [
        "oai:envidat.ch:82d763fa-123a-4648-b827-0dec02a5efbc"
    ],
    "PublicationTimestamp": "2018-07-01T11:59:59Z",
    "PublicationYear": [
        "2018"
    ],
    "Publisher": [
        "National Forest Inventory (NFI)"
    ],
    "RelatedIdentifier": [
        "https://www.envidat.ch/dataset/forest-type-nfi"
    ],
    "ResourceType": [
        "Dataset"
    ],
    "Rights": [
        "Other (Not Open)"
    ],
    "SpatialCoverage": "(46N-48N,6 E-10E)",
    "TempCoverageBegin": 63655934399,
    "TempCoverageEnd": 63655934399,
    "TemporalCoverage": " point in time : 2018-03-06T11:59:59Z",
    "TemporalCoverage:BeginDate": "2018-03-06T11:59:59Z",
    "TemporalCoverage:EndDate": "2018-03-06T11:59:59Z",
    "author": [
        "Lars Waser",
        "Christian Ginzler"
    ],
    "fulltext": "oai:envidat.ch:82d763fa-123a-4648-b827-0dec02a5efbc;2018-04-03T13:06:34Z;10.16904/1000001.3;Lars Waser;D-5937-2011;Swiss Federal Institute for Forest, Snow and Landscape Research WSL;Christian Ginzler;E-9544-2012;Swiss Federal Institute for Forest, Snow and Landscape Research WSL;Forest Type NFI;Waldmischungsgrad LFI;2018;National Forest Inventory (NFI);FOREST;FOREST INVENTORY;FOREST TYPE;NFI;Lars Waser;D-5937-2011;Swiss Federal Institute for Forest, Snow and Landscape Research WSL;2018-03-06;en;Dataset;https://www.envidat.ch/dataset/forest-type-nfi;88 bytes;3072776 bytes;TXT;PDF;JPEG;2016 (current);Other (Not Open);This dataset presents an remote sensing based approach for a countrywide mapping of broadleaved and coniferous trees in Switzerland with a spatial resolution of 3 m x 3 m. The data available is a raster of 25 m x 25 m with the fraction of broadleaf trees. The classification approach incorporates a random forest classifier, explanatory variables from multispectral aerial imagery and a Digital Terrain Model (DTM) from Airborne Laser Scanning (ALS) data, digitized training polygons and independent validation data from the National Forest Inventory (NFI). Whereas high model overall accuracies (0.99)\nand kappa (0.98) were achieved, the comparison of the tree type map with independent NFI data revealed significant deviations that are related to underestimations of broadleaved trees (median of 3.17%).;45.81802 5.95587 47.80838 10.49203;Switzerland",
    "group": "envidat",
    "groups": [
        {
            "name": "envidat"
        }
    ],
    "name": "350fb689-e44d-5d31-965f-e3ec6dda96b6",
    "notes": [
        "This dataset presents an remote sensing based approach for a countrywide mapping of broadleaved and coniferous trees in Switzerland with a spatial resolution of 3 m x 3 m. The data available is a raster of 25 m x 25 m with the fraction of broadleaf trees. The classification approach incorporates a random forest classifier, explanatory variables from multispectral aerial imagery and a Digital Terrain Model (DTM) from Airborne Laser Scanning (ALS) data, digitized training polygons and independent validation data from the National Forest Inventory (NFI). Whereas high model overall accuracies (0.99)\nand kappa (0.98) were achieved, the comparison of the tree type map with independent NFI data revealed significant deviations that are related to underestimations of broadleaved trees (median of 3.17%)."
    ],
    "oai_identifier": [
        "oai:envidat.ch:82d763fa-123a-4648-b827-0dec02a5efbc"
    ],
    "oai_set": "",
    "spatial": "{\"type\":\"Polygon\",\"coordinates\":[[[5.95587,45.81802],[5.95587,47.80838],[10.49203,47.80838],[10.49203,45.81802],[5.95587,45.81802]]]}",
    "state": "active",
    "tags": [
        {
            "name": "FOREST"
        },
        {
            "name": "FOREST INVENTORY"
        },
        {
            "name": "FOREST TYPE"
        },
        {
            "name": "NFI"
        }
    ],
    "title": [
        "Forest Type NFI",
        "Waldmischungsgrad LFI"
    ],
    "url": ""
}