{
    "Contact": [
        "F. Alexander Haumann"
    ],
    "Contributor": [
        "EnviDat"
    ],
    "DOI": "http://dx.doi.org/doi:10.16904/8",
    "DiscHierarchy": [
        "4.4.7",
        "Geosciences",
        "Environmental Research"
    ],
    "Discipline": "Environmental Research",
    "Format": [
        "URL",
        "PDF",
        "NetCDF4 CF-1.6"
    ],
    "Language": [
        "English"
    ],
    "MetaDataAccess": "https://www.envidat.ch/oai?verb=GetRecord&metadataPrefix=datacite&identifier=oai:envidat.ch:b16a0901-3abe-4da0-b61e-cdb80c59ba63",
    "MetadataAccess": [
        "oai:envidat.ch:b16a0901-3abe-4da0-b61e-cdb80c59ba63"
    ],
    "PublicationTimestamp": "2016-07-01T11:59:59Z",
    "PublicationYear": [
        "2016"
    ],
    "Publisher": [
        "ETH Zurich"
    ],
    "RelatedIdentifier": [
        "https://www.envidat.ch/dataset/10-16904-8"
    ],
    "ResourceType": [
        "Dataset"
    ],
    "Rights": [
        "Other (Non-Commercial)"
    ],
    "SpatialCoverage": "(90S-37S,180W-180E)",
    "TempCoverageBegin": 62519428799,
    "TempCoverageEnd": 62519428799,
    "TemporalCoverage": " point in time : 1982-03-01T11:59:59Z",
    "TemporalCoverage:BeginDate": "1982-03-01T11:59:59Z",
    "TemporalCoverage:EndDate": "1982-03-01T11:59:59Z",
    "author": [
        "Nicolas Gruber",
        "Ivy Frenger",
        "Stefan Kern",
        "Matthias M\u00fcnnich",
        "F. Alexander Haumann"
    ],
    "fulltext": "oai:envidat.ch:b16a0901-3abe-4da0-b61e-cdb80c59ba63;2018-07-10T07:48:38Z;10.16904/8;F. Alexander Haumann;0000-0002-8218-977X;ETHZ;Nicolas Gruber;ETHZ;Matthias M\u00fcnnich;ETHZ;Ivy Frenger;ETHZ, GEOMAR Helmholtz Centre for Ocean Research Kiel;Stefan Kern;ICDC  University of Hamburg;Antarctic sea-ice freshwater fluxes associated with freezing, transport, and melting;2016;ETH Zurich;ANTARTIC;CLIMATE CHANGE;CRYOSPHERIC SCIENCE;FORCING;FREEZING;FRESHWATER FLUX;MASS BALANCE;MELTING;PHYSICAL OCEANOGRAPHY;POLAR;SALINITY;SALT;SATELLITE;SEA ICE;SEA ICE DIVERGENCE;SEA ICE VOLUME;SOUTHERN OCEAN;TRANSPORT;F. Alexander Haumann;0000-0002-8218-977X;1982-03-01;en;Dataset;https://www.envidat.ch/dataset/10-16904-8;379128 bytes;1493303 bytes;260945 bytes;PDF;NetCDF4 CF-1.6;URL;1;Other (Non-Commercial);This data set provides estimates of annual fresh water fluxes related to sea-ice formation from ocean freezing and snow-ice formation, sea-ice melting, lateral transport of sea ice in the Southern Ocean over the period 1982 to 2008.It is derived from a mass balance calculation of local sea-ice volume change and divergence from satellite data and sea-ice reconstructions. The mass balance is calculated on a daily basis and fluxes are then integrated over the entire year, where a year is defined from March to February of the next year (i.e. from March 1982 to February 2009). This approach combines multiple products of sea-ice concentration (Cavalieri & Parkinson, 2008;Comiso, 1986; Meier et al., 2013), sea-ice thickness (Kurtz & Markus, 2012; Massonnet et al., 2013; Worby et al., 2008), and sea-ice drift (Fowler et al., 2013; Kwok 2005; Schwegmann et al., 2011). For a detailed description of the method see Haumann et al. (2016). The data set is derived to estimate large-scale (regional to basin-scale) fluxes on an annual basis. Our confidence is reduced on a grid cell basis, such as for single coastal polynyas, where the method and underlying data induce large, unknown uncertainties.\n\n_Disclaimer: This data set is free to use for any non-commercial purpose at the risk of the user and the authors do not take any liability on the use of the data set. The authors assembled the data set carefully and assessed accuracy, errors, and uncertainties. Please contact the authors if you find any issues._\n\n__Related publication__: http://www.nature.com/nature/journal/v537/n7618/full/nature19101.html (doi:10.1038/nature19101);-89.7 -180 -37 180;Southern Ocean",
    "group": "envidat",
    "groups": [
        {
            "name": "envidat"
        }
    ],
    "name": "62778fc3-5a23-514c-b5d6-7b4b094f90bc",
    "notes": [
        "This data set provides estimates of annual fresh water fluxes related to sea-ice formation from ocean freezing and snow-ice formation, sea-ice melting, lateral transport of sea ice in the Southern Ocean over the period 1982 to 2008.It is derived from a mass balance calculation of local sea-ice volume change and divergence from satellite data and sea-ice reconstructions. The mass balance is calculated on a daily basis and fluxes are then integrated over the entire year, where a year is defined from March to February of the next year (i.e. from March 1982 to February 2009). This approach combines multiple products of sea-ice concentration (Cavalieri & Parkinson, 2008;Comiso, 1986; Meier et al., 2013), sea-ice thickness (Kurtz & Markus, 2012; Massonnet et al., 2013; Worby et al., 2008), and sea-ice drift (Fowler et al., 2013; Kwok 2005; Schwegmann et al., 2011). For a detailed description of the method see Haumann et al. (2016). The data set is derived to estimate large-scale (regional to basin-scale) fluxes on an annual basis. Our confidence is reduced on a grid cell basis, such as for single coastal polynyas, where the method and underlying data induce large, unknown uncertainties.\n\n_Disclaimer: This data set is free to use for any non-commercial purpose at the risk of the user and the authors do not take any liability on the use of the data set. The authors assembled the data set carefully and assessed accuracy, errors, and uncertainties. Please contact the authors if you find any issues._\n\n__Related publication__: http://www.nature.com/nature/journal/v537/n7618/full/nature19101.html (doi:10.1038/nature19101)"
    ],
    "oai_identifier": [
        "oai:envidat.ch:b16a0901-3abe-4da0-b61e-cdb80c59ba63"
    ],
    "oai_set": "",
    "spatial": "{\"type\":\"Polygon\",\"coordinates\":[[[-180,-89.7],[-180,-37],[180,-37],[180,-89.7],[-180,-89.7]]]}",
    "state": "active",
    "tags": [
        {
            "name": "ANTARTIC"
        },
        {
            "name": "CLIMATE CHANGE"
        },
        {
            "name": "CRYOSPHERIC SCIENCE"
        },
        {
            "name": "FORCING"
        },
        {
            "name": "FREEZING"
        },
        {
            "name": "FRESHWATER FLUX"
        },
        {
            "name": "MASS BALANCE"
        },
        {
            "name": "MELTING"
        },
        {
            "name": "PHYSICAL OCEANOGRAPHY"
        },
        {
            "name": "POLAR"
        },
        {
            "name": "SALINITY"
        },
        {
            "name": "SALT"
        }
    ],
    "title": [
        "Antarctic sea-ice freshwater fluxes associated with freezing, transport, and melting"
    ],
    "url": ""
}