{
    "Contact": [
        "Nander Wever"
    ],
    "Contributor": [
        "EnviDat"
    ],
    "DOI": "http://dx.doi.org/doi:10.16904/1",
    "DiscHierarchy": [
        "4.4.7",
        "Geosciences",
        "Environmental Research"
    ],
    "Discipline": "Environmental Research",
    "Format": [
        "PDF",
        "SMET"
    ],
    "Language": [
        "English"
    ],
    "MetaDataAccess": "https://www.envidat.ch/oai?verb=GetRecord&metadataPrefix=datacite&identifier=oai:envidat.ch:38112bee-f865-4b29-ba19-47a99ba78833",
    "MetadataAccess": [
        "oai:envidat.ch:38112bee-f865-4b29-ba19-47a99ba78833"
    ],
    "PublicationTimestamp": "2015-07-01T11:59:59Z",
    "PublicationYear": [
        "2015"
    ],
    "Publisher": [
        "WSL Institute for Snow and Avalanche Research SLF"
    ],
    "RelatedIdentifier": [
        "https://www.envidat.ch/dataset/10-16904-1",
        "http://www.envidat.ch/catalogue/10.16904/1"
    ],
    "ResourceType": [
        "Measurements"
    ],
    "Rights": [
        "Open Data Commons Open Database License (ODbL)"
    ],
    "SpatialCoverage": "(47N,10E)",
    "TempCoverageBegin": 62977172399,
    "TempCoverageEnd": 62977172399,
    "TemporalCoverage": " point in time : 1996-09-01T11:59:59Z",
    "TemporalCoverage:BeginDate": "1996-09-01T11:59:59Z",
    "TemporalCoverage:EndDate": "1996-09-01T11:59:59Z",
    "author": [
        "WSL Institute for Snow and Avalanche Research SLF"
    ],
    "fulltext": "oai:envidat.ch:38112bee-f865-4b29-ba19-47a99ba78833;2018-12-09T00:24:25Z;10.16904/1;WSL Institute for Snow and Avalanche Research SLF;SLF;WFJ_MOD: Meteorological and snowpack measurements from Weissfluhjoch, Davos, Switzerland;Meteorologische und Schneedecke Messungen von Weissfluhjoch, Davos, Schweiz.;2015;WSL Institute for Snow and Avalanche Research SLF;AIR TEMPERATURE;HUMIDITY;LONGWAVE RADIATION;PRECIPITATION AMOUNT;SHORTWAVE RADIATION;SNOW DEPTH;SNOW ICE TEMPERATURE;WIND DIRECTION;WIND SPEED;Nander Wever;SLF;1996-09-01;en;Measurements;https://www.envidat.ch/dataset/10-16904-1;http://www.envidat.ch/catalogue/10.16904/1;2490 bytes;2223 bytes;1095 bytes;59121 bytes;SMET;PDF;1;Open Data Commons Open Database License (ODbL);Dataset of meteorological and snowpack measurements from the automatic weather station at Weissfluhjoch, Davos, Switzerland, suitable for driving snowpack models. The dataset contains standard meteorological measurements, and additionally snowpack runoff data from a snow lysimeter. Where possible, data is quality checked and missing data are replaced from backup sensors from the measurement site itself, or (in only a few cases) from the MeteoSwiss weather station at 470 m distance and 150 m above the measurement site. \n\n__Publication__\nWever, N., Schmid, L., Heilig, A., Eisen, O., Fierz, C., and Lehning, M. Verification of the multi-layer SNOWPACK model with different water transport schemes. 2015. The Cryosphere. Volume 9. 2271-2293. http://dx.doi.org/10.5194/tc-9-2271-2015. 10.5194/tc-9-2271-2015;46.829598 9.809568;[46.829598 9.809568]",
    "group": "envidat",
    "groups": [
        {
            "name": "envidat"
        }
    ],
    "name": "8e3afba6-a9e9-5f6a-9337-75d00b7d03db",
    "notes": [
        "Dataset of meteorological and snowpack measurements from the automatic weather station at Weissfluhjoch, Davos, Switzerland, suitable for driving snowpack models. The dataset contains standard meteorological measurements, and additionally snowpack runoff data from a snow lysimeter. Where possible, data is quality checked and missing data are replaced from backup sensors from the measurement site itself, or (in only a few cases) from the MeteoSwiss weather station at 470 m distance and 150 m above the measurement site. \n\n__Publication__\nWever, N., Schmid, L., Heilig, A., Eisen, O., Fierz, C., and Lehning, M. Verification of the multi-layer SNOWPACK model with different water transport schemes. 2015. The Cryosphere. Volume 9. 2271-2293. http://dx.doi.org/10.5194/tc-9-2271-2015. 10.5194/tc-9-2271-2015"
    ],
    "oai_identifier": [
        "oai:envidat.ch:38112bee-f865-4b29-ba19-47a99ba78833"
    ],
    "oai_set": "",
    "spatial": "{\"type\":\"Polygon\",\"coordinates\":[[[9.809568,46.829598],[9.809568,46.829598],[9.809568,46.829598],[9.809568,46.829598],[9.809568,46.829598]]]}",
    "state": "active",
    "tags": [
        {
            "name": "AIR TEMPERATURE"
        },
        {
            "name": "HUMIDITY"
        },
        {
            "name": "LONGWAVE RADIATION"
        },
        {
            "name": "PRECIPITATION AMOUNT"
        },
        {
            "name": "SHORTWAVE RADIATION"
        },
        {
            "name": "SNOW DEPTH"
        },
        {
            "name": "SNOW ICE TEMPERATURE"
        },
        {
            "name": "WIND DIRECTION"
        },
        {
            "name": "WIND SPEED"
        }
    ],
    "title": [
        "WFJ_MOD: Meteorological and snowpack measurements from Weissfluhjoch, Davos, Switzerland",
        "Meteorologische und Schneedecke Messungen von Weissfluhjoch, Davos, Schweiz."
    ],
    "url": ""
}