{
    "Contact": [
        "Mountain Hydrology and Mass Movements"
    ],
    "Contributor": [
        "EnviDat"
    ],
    "DOI": "http://dx.doi.org/doi:10.16904/envidat.33",
    "DiscHierarchy": [
        "4.4.7",
        "Geosciences",
        "Environmental Research"
    ],
    "Discipline": "Environmental Research",
    "Format": [
        "CSV"
    ],
    "Language": [
        "English"
    ],
    "MetaDataAccess": "https://www.envidat.ch/oai?verb=GetRecord&metadataPrefix=datacite&identifier=oai:envidat.ch:17732065-e90f-452d-838d-ba70bfd01a5e",
    "MetadataAccess": [
        "oai:envidat.ch:17732065-e90f-452d-838d-ba70bfd01a5e"
    ],
    "PublicationTimestamp": "2018-07-01T11:59:59Z",
    "PublicationYear": [
        "2018"
    ],
    "Publisher": [
        "Swiss Federal Institute for Forest, Snow and Landscape Research WSL"
    ],
    "RelatedIdentifier": [
        "https://www.envidat.ch/dataset/number-of-natural-hazard-fatalities-per-year-in-switzerland-since-1946"
    ],
    "ResourceType": [
        "Dataset"
    ],
    "Rights": [
        "Open Data Commons Open Database License (ODbL)"
    ],
    "SpatialCoverage": "(46N-48N,6 E-11E)",
    "TempCoverageBegin": 63679694399,
    "TempCoverageEnd": 63679694399,
    "TemporalCoverage": " point in time : 2018-12-06T11:59:59Z",
    "TemporalCoverage:BeginDate": "2018-12-06T11:59:59Z",
    "TemporalCoverage:EndDate": "2018-12-06T11:59:59Z",
    "author": [
        "WSL"
    ],
    "fulltext": "oai:envidat.ch:17732065-e90f-452d-838d-ba70bfd01a5e;2018-12-09T00:32:46Z;10.16904/envidat.33;WSL;Swiss Federal Institute for Forest, Snow and Landscape Research WSL;Number of natural hazard fatalities per year in Switzerland since 1946;2018;Swiss Federal Institute for Forest, Snow and Landscape Research WSL;DEBRIS FLOW FATALITIES;EARTHQUAKE FATALITIES;FLOOD FATALITIES;ICE AVALANCHE FATALITIES;LANDSLIDE FATALITIES;LIGHTNING FATALITIES;NATURAL HAZARD FATALITIES;ROCKFALL FATALITIES;WINDSTORM FATALITIES;Mountain Hydrology and Mass Movements;Swiss Federal Institute for Forest, Snow and Landscape Research WSL;2018-12-06;en;Dataset;https://www.envidat.ch/dataset/number-of-natural-hazard-fatalities-per-year-in-switzerland-since-1946;1576 bytes;CSV;1.0;Open Data Commons Open Database License (ODbL);This dataset contains the number of fatalities due to flood, debris flow, landslide, rockfall, windstorm, lightning, ice avalanche, earthquake and other processes like roof avalanche or lacustrine tsunami for each year since 1946.\nThe following information is contained (by column and column title):  \n\n* year\n* total number of hazard fatalities\n* number of fatalities by flood (German: Hochwasser, \u00dcberschwemmung). Flood includes people drowned in flooded or inundated areas or carried away in streams under high-water conditions.\n* number of fatalities by debris flow (German: Murgang).\n* number of fatalities by landslide (German: Erdrutsch). Landslide includes people killed by landslides and hillslope debris flows (German: Hangmure).\n* number of fatalities by rockfall (German: Steinschlag, Fels- und Bergsturz).\n* number of fatalities by windstorm (German: Sturm). Windstorm includes people killed by falling objects or trees during very strong wind conditions and people who drowned in lakes because their boat capsized during such conditions.\n* number of fatalities by lightning (German: Blitz).\n* number of fatalities by ice avalanche (German: Eislawine).\n* number of fatalities by earthquake (German: Erdbeben).\n* number of fatalities by other processes like roof avalanche, lacustrine tsunami (German: andere Prozesse wie Dachlawine, Tsunami im See).\n\nThe data was collected based on newspaper research. For more information please refer to \n\n_Badoux, A., Andres, N., Techel, F., and Hegg, C.: Natural hazard fatalities in Switzerland from 1946 to 2015, Nat. Hazards Earth Syst. Sci., 16, 2747-2768, https://doi.org/10.5194/nhess-16-2747-2016, 2016._\n\nThe data collection is financed by the FOEN (with exception of the collection of the avalanche fatalities). The data contains the official statistics of the FOEN on fatalities due to flood, debris flow, landslide, rock fall and avalanche.\n\n__Restrictions: The data set is not complete.__ Only fatalities in or around settlements and on open transportation routes are included. More precisely, fatalities were not collected, when persons exposed themselves to a great danger on purpose. Or fatalities during leisure activities which are connected to a higher risk were not included (this includes e.g. canoeing or river surfing during flood, canyoning, mountaineering, climbing, walking or driving on a closed road).\n\nFatalities by avalanches are collected at the WSL Institute for Snow and Avalanche Research SLF. You can download the avalanche fatalities per hydrological year [here](https://www.envidat.ch/dataset/avalanche-fatalities-switzerland-1936) and per calendar year [here](https://www.envidat.ch/dataset/avalanche-fatalities-per-calendar-year-since-1936). For a direct comparison with the fatalities presented here, please download the data set with the calendar years and do not consider fatalities in the backcountry (tour) or in terrain close to ski areas (offpiste).;45.7675229621 5.64697265625 47.8647739558 10.5798339844;Switzerland",
    "group": "envidat",
    "groups": [
        {
            "name": "envidat"
        }
    ],
    "name": "9846b79b-3ecd-5121-ad5a-dd438961ffc7",
    "notes": [
        "This dataset contains the number of fatalities due to flood, debris flow, landslide, rockfall, windstorm, lightning, ice avalanche, earthquake and other processes like roof avalanche or lacustrine tsunami for each year since 1946.\nThe following information is contained (by column and column title):  \n\n* year\n* total number of hazard fatalities\n* number of fatalities by flood (German: Hochwasser, \u00dcberschwemmung). Flood includes people drowned in flooded or inundated areas or carried away in streams under high-water conditions.\n* number of fatalities by debris flow (German: Murgang).\n* number of fatalities by landslide (German: Erdrutsch). Landslide includes people killed by landslides and hillslope debris flows (German: Hangmure).\n* number of fatalities by rockfall (German: Steinschlag, Fels- und Bergsturz).\n* number of fatalities by windstorm (German: Sturm). Windstorm includes people killed by falling objects or trees during very strong wind conditions and people who drowned in lakes because their boat capsized during such conditions.\n* number of fatalities by lightning (German: Blitz).\n* number of fatalities by ice avalanche (German: Eislawine).\n* number of fatalities by earthquake (German: Erdbeben).\n* number of fatalities by other processes like roof avalanche, lacustrine tsunami (German: andere Prozesse wie Dachlawine, Tsunami im See).\n\nThe data was collected based on newspaper research. For more information please refer to \n\n_Badoux, A., Andres, N., Techel, F., and Hegg, C.: Natural hazard fatalities in Switzerland from 1946 to 2015, Nat. Hazards Earth Syst. Sci., 16, 2747-2768, https://doi.org/10.5194/nhess-16-2747-2016, 2016._\n\nThe data collection is financed by the FOEN (with exception of the collection of the avalanche fatalities). The data contains the official statistics of the FOEN on fatalities due to flood, debris flow, landslide, rock fall and avalanche.\n\n__Restrictions: The data set is not complete.__ Only fatalities in or around settlements and on open transportation routes are included. More precisely, fatalities were not collected, when persons exposed themselves to a great danger on purpose. Or fatalities during leisure activities which are connected to a higher risk were not included (this includes e.g. canoeing or river surfing during flood, canyoning, mountaineering, climbing, walking or driving on a closed road).\n\nFatalities by avalanches are collected at the WSL Institute for Snow and Avalanche Research SLF. You can download the avalanche fatalities per hydrological year [here](https://www.envidat.ch/dataset/avalanche-fatalities-switzerland-1936) and per calendar year [here](https://www.envidat.ch/dataset/avalanche-fatalities-per-calendar-year-since-1936). For a direct comparison with the fatalities presented here, please download the data set with the calendar years and do not consider fatalities in the backcountry (tour) or in terrain close to ski areas (offpiste)."
    ],
    "oai_identifier": [
        "oai:envidat.ch:17732065-e90f-452d-838d-ba70bfd01a5e"
    ],
    "oai_set": "",
    "spatial": "{\"type\":\"Polygon\",\"coordinates\":[[[5.64697265625,45.7675229621],[5.64697265625,47.8647739558],[10.5798339844,47.8647739558],[10.5798339844,45.7675229621],[5.64697265625,45.7675229621]]]}",
    "state": "active",
    "tags": [
        {
            "name": "DEBRIS FLOW FATALITIES"
        },
        {
            "name": "EARTHQUAKE FATALITIES"
        },
        {
            "name": "FLOOD FATALITIES"
        },
        {
            "name": "ICE AVALANCHE FATALITIES"
        },
        {
            "name": "LANDSLIDE FATALITIES"
        },
        {
            "name": "LIGHTNING FATALITIES"
        },
        {
            "name": "NATURAL HAZARD FATALITIES"
        },
        {
            "name": "ROCKFALL FATALITIES"
        },
        {
            "name": "WINDSTORM FATALITIES"
        }
    ],
    "title": [
        "Number of natural hazard fatalities per year in Switzerland since 1946"
    ],
    "url": ""
}