{
    "Contact": [
        "Benjamin Reuter"
    ],
    "Contributor": [
        "EnviDat"
    ],
    "DOI": "http://dx.doi.org/doi:10.16904/envidat.40",
    "DiscHierarchy": [
        "4.4.7",
        "Geosciences",
        "Environmental Research"
    ],
    "Discipline": "Environmental Research",
    "Format": [
        "PDF",
        "CSV"
    ],
    "Language": [
        "English"
    ],
    "MetaDataAccess": "https://www.envidat.ch/oai?verb=GetRecord&metadataPrefix=datacite&identifier=oai:envidat.ch:3735a11a-34a5-4a83-b2db-ed22484589d8",
    "MetadataAccess": [
        "oai:envidat.ch:3735a11a-34a5-4a83-b2db-ed22484589d8"
    ],
    "PublicationTimestamp": "2018-07-01T11:59:59Z",
    "PublicationYear": [
        "2018"
    ],
    "Publisher": [
        "WSL Institute for Snow and Avalanche Research SLF"
    ],
    "RelatedIdentifier": [
        "https://www.envidat.ch/dataset/data-snow-instability"
    ],
    "ResourceType": [
        "Dataset"
    ],
    "Rights": [
        "Open Data Commons Open Database License (ODbL)"
    ],
    "SpatialCoverage": "(47N-47N,10E-10E)",
    "TempCoverageBegin": 63180820799,
    "TempCoverageEnd": 63180820799,
    "TemporalCoverage": " point in time : 2003-02-14T11:59:59Z",
    "TemporalCoverage:BeginDate": "2003-02-14T11:59:59Z",
    "TemporalCoverage:EndDate": "2003-02-14T11:59:59Z",
    "author": [
        "Benjamin Reuter",
        "Sascha Bellaire",
        "Alec van Herwijnen",
        "J\u00fcrg Schweizer"
    ],
    "fulltext": "oai:envidat.ch:3735a11a-34a5-4a83-b2db-ed22484589d8;2018-12-06T17:34:19Z;10.16904/envidat.40;Benjamin Reuter;0000-0002-7302-3858;WSL Institute for Snow and Avalanche Research SLF;Alec van Herwijnen;0000-0001-5637-6486;WSL Institute for Snow and Avalanche Research SLF;Sascha Bellaire;WSL Institute for Snow and Avalanche Research SLF;J\u00fcrg Schweizer;0000-0001-5076-2968;WSL Institute for Snow and Avalanche Research SLF;Data set on snow instability;Snow instability;2018;WSL Institute for Snow and Avalanche Research SLF;AVALANCHE FORCASTING;CRACK PROPAGATION;FAILURE INITIATION;PROPGATOIN SAW TEST;RUTSCHBLOCK;SLAB;SLAB TENSILE SUPPORT;SNOW AVALANCHE;SNOW STABILITY EVALUATION;WEAK LAYER;Benjamin Reuter;0000-0002-7302-3858;WSL Institute for Snow and Avalanche Research SLF;2003-02-14;en;Dataset;https://www.envidat.ch/dataset/data-snow-instability;10332 bytes;172308 bytes;CSV;PDF;1.0;Open Data Commons Open Database License (ODbL);These data on snow instability include three data subsets that were analyzed and the results published by Reuter and Schweizer (2018) who suggest a novel framework on how to describe snow instability by failure initiation, crack propagation and slab tensile support.\n\nPlease refer to the Read-me file for further details on the data.\n\nThese data are the basis of the following publication:\nReuter, B. and Schweizer, J., 2018. Describing snow instability by failure initiation, crack propagation and slab tensile support. Geophys. Res. Lett., 45, doi: 10.1029/2018GL078069.;46.7353429853 9.73182678223 46.8707071353 9.96528625488;Switzerland",
    "group": "envidat",
    "groups": [
        {
            "name": "envidat"
        }
    ],
    "name": "9ef2871b-20c5-59ab-924a-54a415554ada",
    "notes": [
        "These data on snow instability include three data subsets that were analyzed and the results published by Reuter and Schweizer (2018) who suggest a novel framework on how to describe snow instability by failure initiation, crack propagation and slab tensile support.\n\nPlease refer to the Read-me file for further details on the data.\n\nThese data are the basis of the following publication:\nReuter, B. and Schweizer, J., 2018. Describing snow instability by failure initiation, crack propagation and slab tensile support. Geophys. Res. Lett., 45, doi: 10.1029/2018GL078069."
    ],
    "oai_identifier": [
        "oai:envidat.ch:3735a11a-34a5-4a83-b2db-ed22484589d8"
    ],
    "oai_set": "",
    "spatial": "{\"type\":\"Polygon\",\"coordinates\":[[[9.73182678223,46.7353429853],[9.73182678223,46.8707071353],[9.96528625488,46.8707071353],[9.96528625488,46.7353429853],[9.73182678223,46.7353429853]]]}",
    "state": "active",
    "tags": [
        {
            "name": "AVALANCHE FORCASTING"
        },
        {
            "name": "CRACK PROPAGATION"
        },
        {
            "name": "FAILURE INITIATION"
        },
        {
            "name": "PROPGATOIN SAW TEST"
        },
        {
            "name": "RUTSCHBLOCK"
        },
        {
            "name": "SLAB"
        },
        {
            "name": "SLAB TENSILE SUPPORT"
        },
        {
            "name": "SNOW AVALANCHE"
        },
        {
            "name": "SNOW STABILITY EVALUATION"
        },
        {
            "name": "WEAK LAYER"
        }
    ],
    "title": [
        "Data set on snow instability",
        "Snow instability"
    ],
    "url": ""
}