{
    "Contact": [
        "Frank Techel"
    ],
    "Contributor": [
        "EnviDat"
    ],
    "DOI": "http://dx.doi.org/doi:10.16904/envidat.39",
    "DiscHierarchy": [
        "4.4.7",
        "Geosciences",
        "Environmental Research"
    ],
    "Discipline": "Environmental Research",
    "Format": [
        "ZIP"
    ],
    "Language": [
        "German"
    ],
    "MetaDataAccess": "https://www.envidat.ch/oai?verb=GetRecord&metadataPrefix=datacite&identifier=oai:envidat.ch:93e6820a-536e-4df0-b9d0-dc2550c89873",
    "MetadataAccess": [
        "oai:envidat.ch:93e6820a-536e-4df0-b9d0-dc2550c89873"
    ],
    "PublicationTimestamp": "2018-07-01T11:59:59Z",
    "PublicationYear": [
        "2018"
    ],
    "Publisher": [
        "WSL Institute for Snow and Avalanche Research SLF"
    ],
    "RelatedIdentifier": [
        "https://www.envidat.ch/dataset/selected-wet-snow-avalanche-activity-data-davos-switzerland-2011-2014"
    ],
    "ResourceType": [
        "Dataset"
    ],
    "Rights": [
        "Open Data Commons Open Database License (ODbL)"
    ],
    "SpatialCoverage": "(47N-47N,10E-10E)",
    "TempCoverageBegin": 63421527599,
    "TempCoverageEnd": 63421527599,
    "TemporalCoverage": " point in time : 2010-10-01T11:59:59Z",
    "TemporalCoverage:BeginDate": "2010-10-01T11:59:59Z",
    "TemporalCoverage:EndDate": "2010-10-01T11:59:59Z",
    "author": [
        "Swiss Avalanche Warning Service"
    ],
    "fulltext": "oai:envidat.ch:93e6820a-536e-4df0-b9d0-dc2550c89873;2018-12-09T00:24:11Z;10.16904/envidat.39;Swiss Avalanche Warning Service;WSL Institute for Snow and Avalanche Research SLF;Selected wet snow avalanche activity data Davos, Switzerland (2011-2014);2018;WSL Institute for Snow and Avalanche Research SLF;ALPS;AVALANCHES;OBSERVATIONS;SHAPEFILE;SNOW;Frank Techel;WSL/SLF;2010-10-01;de;Dataset;https://www.envidat.ch/dataset/selected-wet-snow-avalanche-activity-data-davos-switzerland-2011-2014;416928 bytes;ZIP;1.0;Open Data Commons Open Database License (ODbL);Polygons of wet snow avalanches in the Davos area, as documented by the Swiss avalanche warning service. The georeferenced outlines of the avalanches contain both the release as well as the deposit area, but without separating between both.\n\nThe dataset is a subset of the total record of 1615 avalanches classified as wet snow avalanches from October 2011 - September 2014, containing those 255 avalanches exceeding 0.0125 km^2. Every polygon comes with meta data, including the date of occurrence.\n\nThis dataset is the underlying dataset to:\nWever, N., Vera Valero, C. and Techel, F. (2018) _Coupled snow cover and avalanche dynamics simulations to evaluate wet snow avalanche activity_. Submitted to J. Geophys. Res., in review.;46.6729987746 9.70848083496 46.8658249013 9.99549865723;Switzerland",
    "group": "envidat",
    "groups": [
        {
            "name": "envidat"
        }
    ],
    "name": "ca037177-6e2d-5a88-b107-92ee725d3419",
    "notes": [
        "Polygons of wet snow avalanches in the Davos area, as documented by the Swiss avalanche warning service. The georeferenced outlines of the avalanches contain both the release as well as the deposit area, but without separating between both.\n\nThe dataset is a subset of the total record of 1615 avalanches classified as wet snow avalanches from October 2011 - September 2014, containing those 255 avalanches exceeding 0.0125 km^2. Every polygon comes with meta data, including the date of occurrence.\n\nThis dataset is the underlying dataset to:\nWever, N., Vera Valero, C. and Techel, F. (2018) _Coupled snow cover and avalanche dynamics simulations to evaluate wet snow avalanche activity_. Submitted to J. Geophys. Res., in review."
    ],
    "oai_identifier": [
        "oai:envidat.ch:93e6820a-536e-4df0-b9d0-dc2550c89873"
    ],
    "oai_set": "",
    "spatial": "{\"type\":\"Polygon\",\"coordinates\":[[[9.70848083496,46.6729987746],[9.70848083496,46.8658249013],[9.99549865723,46.8658249013],[9.99549865723,46.6729987746],[9.70848083496,46.6729987746]]]}",
    "state": "active",
    "tags": [
        {
            "name": "ALPS"
        },
        {
            "name": "AVALANCHES"
        },
        {
            "name": "OBSERVATIONS"
        },
        {
            "name": "SHAPEFILE"
        },
        {
            "name": "SNOW"
        }
    ],
    "title": [
        "Selected wet snow avalanche activity data Davos, Switzerland (2011-2014)"
    ],
    "url": ""
}