{
    "Contact": [
        "Materials Cloud"
    ],
    "DOI": "http://dx.doi.org/doi:10.24435/materialscloud:2019.0013/v1",
    "DiscHierarchy": [
        "5.3",
        "Engineering Sciences",
        "Materials Science and Engineeringy"
    ],
    "Discipline": "Materials Science And Engineering",
    "Language": [
        "English"
    ],
    "MetaDataAccess": "https://archive.materialscloud.org/xml?verb=GetRecord&metadataPrefix=oai_dc&identifier=oai:materialscloud.org:2019.0013/v1",
    "MetadataAccess": [
        "oai:materialscloud.org:2019.0013/v1"
    ],
    "OpenAccess": "true",
    "PublicationTimestamp": "2019-04-17T11:59:59Z",
    "PublicationYear": [
        "2019"
    ],
    "Publisher": [
        "Materials Cloud"
    ],
    "ResourceType": [
        "Dataset"
    ],
    "Rights": [
        "Creative Commons Attribution 4.0 International https://creativecommons.org/licenses/by/4.0/legalcode",
        "info:eu-repo/semantics/openAccess"
    ],
    "author": [
        "\u0160u\u0107ur, Zoran",
        "Spiwok, Vojtech",
        "K\u0159\u00ed\u017e, Pavel"
    ],
    "fulltext": "oai:materialscloud.org:2019.0013/v1;2019-06-12Z;DOI;Dataset;Spiwok, Vojtech;\u0160u\u0107ur, Zoran;K\u0159\u00ed\u017e, Pavel;Free-Energy Surface Prediction by Flying Gaussian Method: Numerical Proof;Materials Cloud;2019-04-17;Creative Commons Attribution 4.0 International https://creativecommons.org/licenses/by/4.0/legalcode;info:eu-repo/semantics/openAccess;metadynamics;flying Gaussian method;molecular dynamics simulation;sampling;doi:10.24435/materialscloud:2019.0013/v1;https://archive.materialscloud.org/2019.0013/v1;en;Biomolecular simulations have a great potential in protein engineering, drug discovery and many other fields. Unfortunately, this method is computationally expensive, so many interesting processes cannot be routinely studied. In order to address this problem we developed Flying Gaussian method [Journal of Chemical Theory and Computation 12, 4644-4650 (2016)]. This method simultaneously simulates multiple replicas of the studied system and disfavor replicas with similar structures by artificial bias potential. The question arises how to calculate an unbiased free energy surface from a biased simulation. This dataset demonstrates together with mathematical arguments supports application of Umbrella Sampling reweighing method, despite the fact that this method is designed for methods with a time-independent bias potential.\n<br/>\n",
    "group": "materialscloud",
    "groups": [
        {
            "name": "materialscloud"
        }
    ],
    "name": "011f4e59-80c9-5e58-9ee6-ee1523f8f837",
    "notes": [
        "Biomolecular simulations have a great potential in protein engineering, drug discovery and many other fields. Unfortunately, this method is computationally expensive, so many interesting processes cannot be routinely studied. In order to address this problem we developed Flying Gaussian method [Journal of Chemical Theory and Computation 12, 4644-4650 (2016)]. This method simultaneously simulates multiple replicas of the studied system and disfavor replicas with similar structures by artificial bias potential. The question arises how to calculate an unbiased free energy surface from a biased simulation. This dataset demonstrates together with mathematical arguments supports application of Umbrella Sampling reweighing method, despite the fact that this method is designed for methods with a time-independent bias potential.\n<br/>\n"
    ],
    "oai_identifier": [
        "oai:materialscloud.org:2019.0013/v1"
    ],
    "oai_set": [
        "DOI"
    ],
    "state": "active",
    "tags": [
        {
            "name": "metadynamics"
        },
        {
            "name": "flying Gaussian method"
        },
        {
            "name": "molecular dynamics simulation"
        },
        {
            "name": "sampling"
        }
    ],
    "title": [
        "Free-Energy Surface Prediction by Flying Gaussian Method: Numerical Proof"
    ],
    "url": "https://archive.materialscloud.org/2019.0013/v1"
}