{
    "Contact": [
        "Materials Cloud"
    ],
    "DOI": "http://dx.doi.org/doi:10.24435/materialscloud:2018.0007/v2",
    "DiscHierarchy": [
        "5.3",
        "Engineering Sciences",
        "Materials Science and Engineeringy"
    ],
    "Discipline": "Materials Science And Engineering",
    "Language": [
        "English"
    ],
    "MetaDataAccess": "https://archive.materialscloud.org/xml?verb=GetRecord&metadataPrefix=oai_dc&identifier=oai:materialscloud.org:2018.0007/v2",
    "MetadataAccess": [
        "oai:materialscloud.org:2018.0007/v2"
    ],
    "OpenAccess": "true",
    "PublicationTimestamp": "2018-11-14T11:59:59Z",
    "PublicationYear": [
        "2018"
    ],
    "Publisher": [
        "Materials Cloud"
    ],
    "ResourceType": [
        "Dataset"
    ],
    "Rights": [
        "Creative Commons Attribution 4.0 International https://creativecommons.org/licenses/by/4.0/legalcode",
        "info:eu-repo/semantics/openAccess"
    ],
    "author": [
        "Jariwala, Kuldeep",
        "Haranczyk, Maciej",
        "Lin, Li-Chiang",
        "Martin, Richard L.",
        "Smit, Berend"
    ],
    "fulltext": "oai:materialscloud.org:2018.0007/v2;2019-06-12Z;DOI;Dataset;Martin, Richard L.;Lin, Li-Chiang;Jariwala, Kuldeep;Smit, Berend;Haranczyk, Maciej;Mail-order metal-organic frameworks (MOFs): designing isoreticular MOF-5 analogues comprising commercially available organic molecules;Materials Cloud;2018-11-14;Creative Commons Attribution 4.0 International https://creativecommons.org/licenses/by/4.0/legalcode;info:eu-repo/semantics/openAccess;3D;three-dimensional;database;high-throughput;MOF-5;nanoporous;methane storage;deliverable capacities;DC;grand canonical Monte Carlo;GCMC;doi:10.24435/materialscloud:2018.0007/v2;https://archive.materialscloud.org/2018.0007/v2;en;Metal\u2013organic frameworks (MOFs), a class of porous materials, are of particular interest in gas storage and separation applications due largely to their high internal surface areas and tunable structures. MOF-5 is perhaps the archetypal MOF; in particular, many isoreticular analogues of MOF-5 have been synthesized, comprising alternative dicarboxylic acid ligands. In this contribution we introduce a new set of hypothesized MOF-5 analogues, constructed from commercially available organic molecules. We describe our automated procedure for hypothetical MOF design, comprising selection of appropriate ligands, construction of 3D structure models, and structure relaxation methods. 116 MOF-5 analogues were designed and characterized in terms of geometric properties and simulated methane uptake at conditions relevant to vehicular storage applications. A strength of the presented approach is that all of the hypothesized MOFs are designed to be synthesizable utilizing ligands purchasable online.<br/>\n<br/>\nVersion 2 includes the structures in CIF format.",
    "group": "materialscloud",
    "groups": [
        {
            "name": "materialscloud"
        }
    ],
    "name": "2756811f-15cb-58d3-8a75-2687b8c68c64",
    "notes": [
        "Metal\u2013organic frameworks (MOFs), a class of porous materials, are of particular interest in gas storage and separation applications due largely to their high internal surface areas and tunable structures. MOF-5 is perhaps the archetypal MOF; in particular, many isoreticular analogues of MOF-5 have been synthesized, comprising alternative dicarboxylic acid ligands. In this contribution we introduce a new set of hypothesized MOF-5 analogues, constructed from commercially available organic molecules. We describe our automated procedure for hypothetical MOF design, comprising selection of appropriate ligands, construction of 3D structure models, and structure relaxation methods. 116 MOF-5 analogues were designed and characterized in terms of geometric properties and simulated methane uptake at conditions relevant to vehicular storage applications. A strength of the presented approach is that all of the hypothesized MOFs are designed to be synthesizable utilizing ligands purchasable online.<br/>\n<br/>\nVersion 2 includes the structures in CIF format."
    ],
    "oai_identifier": [
        "oai:materialscloud.org:2018.0007/v2"
    ],
    "oai_set": [
        "DOI"
    ],
    "state": "active",
    "tags": [
        {
            "name": "three-dimensional"
        },
        {
            "name": "database"
        },
        {
            "name": "high-throughput"
        },
        {
            "name": "MOF-"
        },
        {
            "name": "nanoporous"
        },
        {
            "name": "methane storage"
        },
        {
            "name": "deliverable capacities"
        },
        {
            "name": "DC"
        },
        {
            "name": "grand canonical Monte Carlo"
        },
        {
            "name": "GCMC"
        }
    ],
    "title": [
        "Mail-order metal-organic frameworks (MOFs): designing isoreticular MOF-5 analogues comprising commercially available organic molecules"
    ],
    "url": "https://archive.materialscloud.org/2018.0007/v2"
}