{
    "Contact": [
        "Materials Cloud"
    ],
    "DOI": "http://dx.doi.org/doi:10.24435/materialscloud:2018.0005/v1",
    "DiscHierarchy": [
        "5.3",
        "Engineering Sciences",
        "Materials Science and Engineeringy"
    ],
    "Discipline": "Materials Science And Engineering",
    "Language": [
        "English"
    ],
    "MetaDataAccess": "https://archive.materialscloud.org/xml?verb=GetRecord&metadataPrefix=oai_dc&identifier=oai:materialscloud.org:2018.0005/v1",
    "MetadataAccess": [
        "oai:materialscloud.org:2018.0005/v1"
    ],
    "OpenAccess": "true",
    "PublicationTimestamp": "2018-05-15T11:59:59Z",
    "PublicationYear": [
        "2018"
    ],
    "Publisher": [
        "Materials Cloud"
    ],
    "ResourceType": [
        "Dataset"
    ],
    "Rights": [
        "Creative Commons Attribution 4.0 International https://creativecommons.org/licenses/by/4.0/legalcode",
        "info:eu-repo/semantics/openAccess"
    ],
    "author": [
        "Lin, Li-Chiang",
        "Braun, Efrem",
        "Schnell, Sondre",
        "Kim, Jihan",
        "Smit, Berend",
        "Thijssen, Wouter",
        "Zurhelle, Alexander F.",
        "Thompson, Joshua A."
    ],
    "fulltext": "oai:materialscloud.org:2018.0005/v1;2019-06-12Z;DOI;Dataset;Braun, Efrem;Zurhelle, Alexander F.;Thijssen, Wouter;Schnell, Sondre;Lin, Li-Chiang;Kim, Jihan;Thompson, Joshua A.;Smit, Berend;High-throughput computational screening of nanoporous adsorbents for CO 2 capture from natural gas;Materials Cloud;2018-05-15;Creative Commons Attribution 4.0 International https://creativecommons.org/licenses/by/4.0/legalcode;info:eu-repo/semantics/openAccess;3D;three-dimensional;database;high-throughput;porous polymer networks;IZA;nanoporous;methane storage;deliverable capacities;DC;zeolites;grand canonical Monte Carlo;GCMC;doi:10.24435/materialscloud:2018.0005/v1;https://archive.materialscloud.org/2018.0005/v1;en;With the growth of natural gas as an energy source, upgrading CO2-contaminated supplies has become increasingly important. Here we develop a single metric that captures how well an adsorbent performs the separation of CH4 and CO2, and we then use this metric to computationally screen tens of thousands of all-silica zeolites. We show that the most important predictors of separation performance are the CO2 heat of adsorption (Qst, CO2) and the CO2 saturation loading capacity. We find that a higher-performing material results when the absolute value of the CH4 heat of adsorption (Qst, CH4) is decreased independently of Qst, CO2, but a correlation that exists between Qst, CH4 and Qst, CO2 in all-silica zeolites leads to incongruity between the objectives of optimizing Qst, CO2 and minimizing Qst, CH4, rendering Qst, CH4 nonpredictive of separation performance. We also conduct a large-scale analysis of ideal adsorbed solution theory (IAST) by comparing results obtained using directly-generated mixture isotherms to those obtained using IAST; IAST appears adequate for the purposes of establishing performance trends and structure\u2013property relationships in a high-throughput manner, but it must be tested for validity when analyzing individual adsorbents in detail since it can produce significant errors for materials in which there is site segregation of the adsorbate species.",
    "group": "materialscloud",
    "groups": [
        {
            "name": "materialscloud"
        }
    ],
    "name": "77a4d9dd-9dd1-50fb-9d2b-303782c05b7e",
    "notes": [
        "With the growth of natural gas as an energy source, upgrading CO2-contaminated supplies has become increasingly important. Here we develop a single metric that captures how well an adsorbent performs the separation of CH4 and CO2, and we then use this metric to computationally screen tens of thousands of all-silica zeolites. We show that the most important predictors of separation performance are the CO2 heat of adsorption (Qst, CO2) and the CO2 saturation loading capacity. We find that a higher-performing material results when the absolute value of the CH4 heat of adsorption (Qst, CH4) is decreased independently of Qst, CO2, but a correlation that exists between Qst, CH4 and Qst, CO2 in all-silica zeolites leads to incongruity between the objectives of optimizing Qst, CO2 and minimizing Qst, CH4, rendering Qst, CH4 nonpredictive of separation performance. We also conduct a large-scale analysis of ideal adsorbed solution theory (IAST) by comparing results obtained using directly-generated mixture isotherms to those obtained using IAST; IAST appears adequate for the purposes of establishing performance trends and structure\u2013property relationships in a high-throughput manner, but it must be tested for validity when analyzing individual adsorbents in detail since it can produce significant errors for materials in which there is site segregation of the adsorbate species."
    ],
    "oai_identifier": [
        "oai:materialscloud.org:2018.0005/v1"
    ],
    "oai_set": [
        "DOI"
    ],
    "state": "active",
    "tags": [
        {
            "name": "three-dimensional"
        },
        {
            "name": "database"
        },
        {
            "name": "high-throughput"
        },
        {
            "name": "porous polymer networks"
        },
        {
            "name": "IZA"
        },
        {
            "name": "nanoporous"
        },
        {
            "name": "methane storage"
        },
        {
            "name": "deliverable capacities"
        },
        {
            "name": "DC"
        },
        {
            "name": "zeolites"
        },
        {
            "name": "grand canonical Monte Carlo"
        },
        {
            "name": "GCMC"
        }
    ],
    "title": [
        "High-throughput computational screening of nanoporous adsorbents for CO 2 capture from natural gas"
    ],
    "url": "https://archive.materialscloud.org/2018.0005/v1"
}