{
    "Contact": [
        "Materials Cloud"
    ],
    "DOI": "http://dx.doi.org/doi:10.24435/materialscloud:2018.0008/v1",
    "DiscHierarchy": [
        "5.3",
        "Engineering Sciences",
        "Materials Science and Engineeringy"
    ],
    "Discipline": "Materials Science And Engineering",
    "Language": [
        "English"
    ],
    "MetaDataAccess": "https://archive.materialscloud.org/xml?verb=GetRecord&metadataPrefix=oai_dc&identifier=oai:materialscloud.org:2018.0008/v1",
    "MetadataAccess": [
        "oai:materialscloud.org:2018.0008/v1"
    ],
    "OpenAccess": "true",
    "PublicationTimestamp": "2018-05-15T11:59:59Z",
    "PublicationYear": [
        "2018"
    ],
    "Publisher": [
        "Materials Cloud"
    ],
    "ResourceType": [
        "Dataset"
    ],
    "Rights": [
        "Creative Commons Attribution 4.0 International https://creativecommons.org/licenses/by/4.0/legalcode",
        "info:eu-repo/semantics/openAccess"
    ],
    "author": [
        "Haranczyk, Maciej",
        "Simon, Cory M.",
        "Martin, Richard L.",
        "Smit, Berend"
    ],
    "fulltext": "oai:materialscloud.org:2018.0008/v1;2019-06-12Z;DOI;Dataset;Martin, Richard L.;Simon, Cory M.;Smit, Berend;Haranczyk, Maciej;In Silico Design of Porous Polymer Networks: High Throughput Screening for Methane Storage Materials;Materials Cloud;2018-05-15;Creative Commons Attribution 4.0 International https://creativecommons.org/licenses/by/4.0/legalcode;info:eu-repo/semantics/openAccess;3D;three-dimensional;database;high-throughput;porous polymer networks;PPN;nanoporous;methane storage;deliverable capacities;DC;grand canonical Monte Carlo;GCMC;doi:10.24435/materialscloud:2018.0008/v1;https://archive.materialscloud.org/2018.0008/v1;en;Porous polymer networks (PPNs) are a class of advanced porous materials that combine the advantages of cheap and stable polymers with the high surface areas and tunable chemistry of metal\u2013organic frameworks. They are of particular interest for gas separation or storage applications, for instance, as methane adsorbents for a vehicular natural gas tank or other portable applications. PPNs are self-assembled from distinct building units; here, we utilize commercially available chemical fragments and two experimentally known synthetic routes to design in silico a large database of synthetically realistic PPN materials. All structures from our database of 18,000 materials have been relaxed with semiempirical electronic structure methods and characterized with Grand-canonical Monte Carlo simulations for methane uptake and deliverable (working) capacity. A number of novel structure\u2013property relationships that govern methane storage performance were identified. The relationships are translated into experimental guidelines to realize the ideal PPN structure. We found that cooperative methane\u2013methane attractions were present in all of the best-performing materials, highlighting the importance of guest interaction in the design of optimal materials for methane storage.",
    "group": "materialscloud",
    "groups": [
        {
            "name": "materialscloud"
        }
    ],
    "name": "b92f55d1-b0ea-5113-9b35-0a5a1cbb51ba",
    "notes": [
        "Porous polymer networks (PPNs) are a class of advanced porous materials that combine the advantages of cheap and stable polymers with the high surface areas and tunable chemistry of metal\u2013organic frameworks. They are of particular interest for gas separation or storage applications, for instance, as methane adsorbents for a vehicular natural gas tank or other portable applications. PPNs are self-assembled from distinct building units; here, we utilize commercially available chemical fragments and two experimentally known synthetic routes to design in silico a large database of synthetically realistic PPN materials. All structures from our database of 18,000 materials have been relaxed with semiempirical electronic structure methods and characterized with Grand-canonical Monte Carlo simulations for methane uptake and deliverable (working) capacity. A number of novel structure\u2013property relationships that govern methane storage performance were identified. The relationships are translated into experimental guidelines to realize the ideal PPN structure. We found that cooperative methane\u2013methane attractions were present in all of the best-performing materials, highlighting the importance of guest interaction in the design of optimal materials for methane storage."
    ],
    "oai_identifier": [
        "oai:materialscloud.org:2018.0008/v1"
    ],
    "oai_set": [
        "DOI"
    ],
    "state": "active",
    "tags": [
        {
            "name": "three-dimensional"
        },
        {
            "name": "database"
        },
        {
            "name": "high-throughput"
        },
        {
            "name": "porous polymer networks"
        },
        {
            "name": "PPN"
        },
        {
            "name": "nanoporous"
        },
        {
            "name": "methane storage"
        },
        {
            "name": "deliverable capacities"
        },
        {
            "name": "DC"
        },
        {
            "name": "grand canonical Monte Carlo"
        },
        {
            "name": "GCMC"
        }
    ],
    "title": [
        "In Silico Design of Porous Polymer Networks: High Throughput Screening for Methane Storage Materials"
    ],
    "url": "https://archive.materialscloud.org/2018.0008/v1"
}