{
    "Contact": [
        "Materials Cloud"
    ],
    "DOI": "http://dx.doi.org/doi:10.24435/materialscloud:2019.0017/v1",
    "DiscHierarchy": [
        "5.3",
        "Engineering Sciences",
        "Materials Science and Engineeringy"
    ],
    "Discipline": "Materials Science And Engineering",
    "Language": [
        "English"
    ],
    "MetaDataAccess": "https://archive.materialscloud.org/xml?verb=GetRecord&metadataPrefix=oai_dc&identifier=oai:materialscloud.org:2019.0017/v1",
    "MetadataAccess": [
        "oai:materialscloud.org:2019.0017/v1"
    ],
    "OpenAccess": "true",
    "PublicationTimestamp": "2019-05-09T11:59:59Z",
    "PublicationYear": [
        "2019"
    ],
    "Publisher": [
        "Materials Cloud"
    ],
    "ResourceType": [
        "Dataset"
    ],
    "Rights": [
        "Creative Commons Attribution Non Commercial 4.0 International https://creativecommons.org/licenses/by-nc/4.0/legalcode",
        "info:eu-repo/semantics/openAccess"
    ],
    "author": [
        "Grossman, Jeffrey",
        "Shao-Horn, Yang",
        "Xie, Tian",
        "France-Lanord, Arthur",
        "Wang, Yanming"
    ],
    "fulltext": "oai:materialscloud.org:2019.0017/v1;2019-06-12Z;DOI;Dataset;Xie, Tian;France-Lanord, Arthur;Wang, Yanming;Shao-Horn, Yang;Grossman, Jeffrey;Graph Dynamical Networks for Unsupervised Learning of Atomic Scale Dynamics in Materials;Materials Cloud;2019-05-09;Creative Commons Attribution Non Commercial 4.0 International https://creativecommons.org/licenses/by-nc/4.0/legalcode;info:eu-repo/semantics/openAccess;machine learning;molecular dynamics;polymer;deep learning;graph;neural networks;amorphous;interface;trajectory;doi:10.24435/materialscloud:2019.0017/v1;https://archive.materialscloud.org/2019.0017/v1;en;Understanding the dynamical processes that govern the performance of functional materials is essential for the design of next generation materials to tackle global energy and environmental challenges. Many of these processes involve the dynamics of individual atoms or small molecules in condensed phases, e.g. lithium ions in electrolytes, water molecules in membranes, molten atoms at interfaces, etc., which are difficult to understand due to the complexity of local environments. We develop graph dynamical networks, an unsupervised learning approach for understanding atomic scale dynamics in arbitrary phases and environments from molecular dynamics simulations. We show that important dynamical information can be learned for various multi-component amorphous material systems, which is difficult to obtain otherwise. We develop a software package &#34;gdynet&#34; at https://github.com/txie-93/gdynet which implements the graph dynamical networks algorithm. This record contains the MD trajectories of a Li-S toy system, a Si-Au binary system, and a polymer battery electrolyte system in a format designed for the &#34;gdynet&#34; package.",
    "group": "materialscloud",
    "groups": [
        {
            "name": "materialscloud"
        }
    ],
    "name": "c1acd268-0cba-5b7d-bb23-2f41bc04c893",
    "notes": [
        "Understanding the dynamical processes that govern the performance of functional materials is essential for the design of next generation materials to tackle global energy and environmental challenges. Many of these processes involve the dynamics of individual atoms or small molecules in condensed phases, e.g. lithium ions in electrolytes, water molecules in membranes, molten atoms at interfaces, etc., which are difficult to understand due to the complexity of local environments. We develop graph dynamical networks, an unsupervised learning approach for understanding atomic scale dynamics in arbitrary phases and environments from molecular dynamics simulations. We show that important dynamical information can be learned for various multi-component amorphous material systems, which is difficult to obtain otherwise. We develop a software package &#34;gdynet&#34; at https://github.com/txie-93/gdynet which implements the graph dynamical networks algorithm. This record contains the MD trajectories of a Li-S toy system, a Si-Au binary system, and a polymer battery electrolyte system in a format designed for the &#34;gdynet&#34; package."
    ],
    "oai_identifier": [
        "oai:materialscloud.org:2019.0017/v1"
    ],
    "oai_set": [
        "DOI"
    ],
    "state": "active",
    "tags": [
        {
            "name": "machine learning"
        },
        {
            "name": "molecular dynamics"
        },
        {
            "name": "polymer"
        },
        {
            "name": "deep learning"
        },
        {
            "name": "graph"
        },
        {
            "name": "neural networks"
        },
        {
            "name": "amorphous"
        },
        {
            "name": "interface"
        },
        {
            "name": "trajectory"
        }
    ],
    "title": [
        "Graph Dynamical Networks for Unsupervised Learning of Atomic Scale Dynamics in Materials"
    ],
    "url": "https://archive.materialscloud.org/2019.0017/v1"
}