{
    "Contact": [
        "Materials Cloud"
    ],
    "DOI": "http://dx.doi.org/doi:10.24435/materialscloud:2017.0006/v1",
    "DiscHierarchy": [
        "5.3",
        "Engineering Sciences",
        "Materials Science and Engineeringy"
    ],
    "Discipline": "Materials Science And Engineering",
    "Language": [
        "English"
    ],
    "MetaDataAccess": "https://archive.materialscloud.org/xml?verb=GetRecord&metadataPrefix=oai_dc&identifier=oai:materialscloud.org:2017.0006/v1",
    "MetadataAccess": [
        "oai:materialscloud.org:2017.0006/v1"
    ],
    "OpenAccess": "true",
    "PublicationTimestamp": "2017-06-21T11:59:59Z",
    "PublicationYear": [
        "2017"
    ],
    "Publisher": [
        "Materials Cloud"
    ],
    "ResourceType": [
        "Dataset"
    ],
    "Rights": [
        "Creative Commons Attribution 4.0 International https://creativecommons.org/licenses/by/4.0/legalcode",
        "info:eu-repo/semantics/openAccess"
    ],
    "author": [
        "Dragoni, Daniele",
        "Daff, Tom",
        "Csanyi, Gabor",
        "Marzari, Nicola"
    ],
    "fulltext": "oai:materialscloud.org:2017.0006/v1;2019-06-12Z;DOI;Dataset;Dragoni, Daniele;Daff, Tom;Csanyi, Gabor;Marzari, Nicola;Gaussian Approximation Potentials for iron from extended first-principles database (Data Download);Materials Cloud;2017-06-21;Creative Commons Attribution 4.0 International https://creativecommons.org/licenses/by/4.0/legalcode;info:eu-repo/semantics/openAccess;Machine-learning;\u03b1-iron;Gaussian approximation potentials;artificial neural networks;interatomic potentials;MARVEL;doi:10.24435/materialscloud:2017.0006/v1;https://archive.materialscloud.org/2017.0006/v1;en;Interatomic potentials are often necessary to describe complex realistic systems that would be too costly to study from first-principles. Commonly, interatomic potentials are designed using functional forms driven by physical intuition and fitted to experimental or computational data. The moderate flexibility of these functional forms limits their ability to be systematically improved by increasing the fitting datasets; on the other hand, their qualitative description of the essential physical interactions ensures a modicum degree of transferability. Recently, a novel trend has emerged where potential-energy surfaces are represented by neural networks fitted on large numbers of first-principles calculations, thus maximizing flexibility but requiring extensive datasets to ensure transferability. Gaussian Approximation Potentials in particular are a novel class of potentials based on non-linear, non-parametric Gaussian-process regression. Here we generate a Gaussian Approximation model for the \u03b1-phase of iron training on energies, stresses and forces taken from first-principles molecular dynamics simulations of pristine and defected bulk systems, of surfaces and \u03b3-surfaces with different crystallographic orientations.",
    "group": "materialscloud",
    "groups": [
        {
            "name": "materialscloud"
        }
    ],
    "name": "e073b9a8-6d35-5a93-897d-ca7327bfb51d",
    "notes": [
        "Interatomic potentials are often necessary to describe complex realistic systems that would be too costly to study from first-principles. Commonly, interatomic potentials are designed using functional forms driven by physical intuition and fitted to experimental or computational data. The moderate flexibility of these functional forms limits their ability to be systematically improved by increasing the fitting datasets; on the other hand, their qualitative description of the essential physical interactions ensures a modicum degree of transferability. Recently, a novel trend has emerged where potential-energy surfaces are represented by neural networks fitted on large numbers of first-principles calculations, thus maximizing flexibility but requiring extensive datasets to ensure transferability. Gaussian Approximation Potentials in particular are a novel class of potentials based on non-linear, non-parametric Gaussian-process regression. Here we generate a Gaussian Approximation model for the \u03b1-phase of iron training on energies, stresses and forces taken from first-principles molecular dynamics simulations of pristine and defected bulk systems, of surfaces and \u03b3-surfaces with different crystallographic orientations."
    ],
    "oai_identifier": [
        "oai:materialscloud.org:2017.0006/v1"
    ],
    "oai_set": [
        "DOI"
    ],
    "state": "active",
    "tags": [
        {
            "name": "Machine-learning"
        },
        {
            "name": "Machine-learning"
        },
        {
            "name": "Gaussian approximation potentials"
        },
        {
            "name": "artificial neural networks"
        },
        {
            "name": "interatomic potentials"
        },
        {
            "name": "MARVEL"
        }
    ],
    "title": [
        "Gaussian Approximation Potentials for iron from extended first-principles database (Data Download)"
    ],
    "url": "https://archive.materialscloud.org/2017.0006/v1"
}