{
    "Contact": [
        "Drs. Monique Brinks, interviewster"
    ],
    "Contributor": [
        "Drs. Monique Brinks, interviewster"
    ],
    "DOI": "http://dx.doi.org/doi:10.17026/dans-xaz-5fnp",
    "DiscHierarchy": [
        "4.4",
        "Natural Sciences",
        "Geosciences"
    ],
    "Discipline": "History",
    "Format": [
        "video/quicktime",
        "transcriptie: word",
        "verklaring: jpg"
    ],
    "Language": [
        "Dutch"
    ],
    "MetaDataAccess": "https://easy.dans.knaw.nl/oai?verb=GetRecord&metadataPrefix=oai_datacite&identifier=oai:easy.dans.knaw.nl:easy-dataset:41843",
    "MetadataAccess": [
        "oai:easy.dans.knaw.nl:easy-dataset:41843"
    ],
    "PublicationTimestamp": "2010-07-01T11:59:59Z",
    "PublicationYear": [
        "2010"
    ],
    "Publisher": [
        "Data Archiving and Networked Services (DANS)"
    ],
    "ResourceType": [
        "Dataset"
    ],
    "Rights": [
        "info:eu-repo/semantics/openAccess",
        "License: http://creativecommons.org/publicdomain/zero/1.0"
    ],
    "TemporalCoverage": [
        "2010-06-23",
        "2009-11-24",
        "2010-05-31"
    ],
    "author": [
        "Stichting Oorlogs- en Verzetscentrum Groningen (OVCG)"
    ],
    "fulltext": "oai:easy.dans.knaw.nl:easy-dataset:41843;2018-09-18T16:57:09Z;D30000:D34000:D34300;driver;easy-collection:2;easy-collection:1;10.17026/dans-xaz-5fnp;Stichting Oorlogs- en Verzetscentrum Groningen (OVCG);Stichting Oorlogs- en Verzetscentrum Groningen (OVCG);Groningen in Oorlogstijd, interview 06;Data Archiving and Networked Services (DANS);2010;Modern and contemporary\n                        history;Groningen;rooms-katholiek;eigen zaak;stoffenhandel;Seyss-Inquart;Rotterdam;Naber;Scholtenhuis;deken Buve;Veringa;inzamelingen van radio's;metaal en fietsen;HBS;vorderingen;tekorten;bevrijding;brand;Waagstraat;Guldenstraat;Martinuskerk;ondernemers in centrum Groningen;fotograaf Kramer;Rein Veld;Bertie Bossina;Tweede Wereldoorlog;oral history;Temporal coverage: Groningen;Drs. Monique Brinks, interviewster;2010-06-23;2009-11-24;2010-05-31;nl;Dataset;urn:nbn:nl:ui:13-uzi-4aq;easy-dataset:41843;twips.dans.knaw.nl-2635184198456718120-1275304932416;video/quicktime;transcriptie: word;verklaring: jpg;info:eu-repo/semantics/openAccess;License: http://creativecommons.org/publicdomain/zero/1.0;Mevrouw Regina Veeger Janssen groeide op in een katholiek gezin en woonde tijdens de oorlog als tiener aan de Grote Markt. Zij vertelt van het dagelijks leven in de oorlog en van de bevrijdingsstrijd, waarbij hun huis, samen met grote delen van de Grote Markt, verwoest werd.  \n  \n00:04:15 Begin van de oorlog; inzamelen radio's en metaal.  \n  \n00:06:49 Joodse kinderen op de katholieke school  \n  \n00:09:56 Kinderen uit Rotterdam in huis, en anderen.  \n  \n00:12:25 Moeder kookt extra eten voor onbekenden  \n  \n00:14:05 Naber en arrestatie van deken Buve  \n  \n00:16:00 Naar de HBS; door Duitse vorderingen twee scholen in \u00e9\u00e9n gebouw.  \n  \n00:22:18 Stelen witte kool van Duitsers; de handtastelijke Duitse soldaat.  \n  \n00:24:50 Het kanonnetje op het Scholtenhuis; Seyss-Inquart; de bevrijding  \n  \n00:27:38 Brand Waagstraat verspreidt zich; familie onder de bureau's.  \n  \n00:33:38 Familie vlucht tijdens mini-wapenstilstand naar Poststraat en de Martinuskerk.  \n  \n00:38:02 Vader en RV bekijken de schade aan de Grote Markt  \n  \n00:40:47 Foto van gestorven vriendin terug naar ouders.  \n  \n00:42:40 Gezin krijgt huis toegewezen; een nieuwe start van ondernemersactiviteiten: foto's van de verwoesting en stoffen.  \n  \n00:46:40 Een Duitse soldaat in de gang; na de oorlog;1940-1945",
    "group": "danseasy",
    "groups": [
        {
            "name": "danseasy"
        }
    ],
    "name": "0a2cb465-2bca-51ad-965f-b2dbc43ca1e1",
    "notes": [
        "Mevrouw Regina Veeger Janssen groeide op in een katholiek gezin en woonde tijdens de oorlog als tiener aan de Grote Markt. Zij vertelt van het dagelijks leven in de oorlog en van de bevrijdingsstrijd, waarbij hun huis, samen met grote delen van de Grote Markt, verwoest werd.  \n  \n00:04:15 Begin van de oorlog; inzamelen radio's en metaal.  \n  \n00:06:49 Joodse kinderen op de katholieke school  \n  \n00:09:56 Kinderen uit Rotterdam in huis, en anderen.  \n  \n00:12:25 Moeder kookt extra eten voor onbekenden  \n  \n00:14:05 Naber en arrestatie van deken Buve  \n  \n00:16:00 Naar de HBS; door Duitse vorderingen twee scholen in \u00e9\u00e9n gebouw.  \n  \n00:22:18 Stelen witte kool van Duitsers; de handtastelijke Duitse soldaat.  \n  \n00:24:50 Het kanonnetje op het Scholtenhuis; Seyss-Inquart; de bevrijding  \n  \n00:27:38 Brand Waagstraat verspreidt zich; familie onder de bureau's.  \n  \n00:33:38 Familie vlucht tijdens mini-wapenstilstand naar Poststraat en de Martinuskerk.  \n  \n00:38:02 Vader en RV bekijken de schade aan de Grote Markt  \n  \n00:40:47 Foto van gestorven vriendin terug naar ouders.  \n  \n00:42:40 Gezin krijgt huis toegewezen; een nieuwe start van ondernemersactiviteiten: foto's van de verwoesting en stoffen.  \n  \n00:46:40 Een Duitse soldaat in de gang; na de oorlog"
    ],
    "oai_identifier": [
        "oai:easy.dans.knaw.nl:easy-dataset:41843"
    ],
    "oai_set": [
        "D30000:D34000:D34300",
        "driver",
        "easy-collection:2",
        "easy-collection:1"
    ],
    "state": "active",
    "tags": [
        {
            "name": "Modern contemporary"
        },
        {
            "name": "history"
        },
        {
            "name": "Groningen"
        },
        {
            "name": "rooms-katholiek"
        },
        {
            "name": "eigen zaak"
        },
        {
            "name": "stoffenhandel"
        },
        {
            "name": "Seyss-Inquart"
        },
        {
            "name": "Rotterdam"
        },
        {
            "name": "Naber"
        },
        {
            "name": "Scholtenhuis"
        },
        {
            "name": "deken Buve"
        },
        {
            "name": "Veringa"
        }
    ],
    "title": [
        "Groningen in Oorlogstijd, interview 06"
    ],
    "url": ""
}