{
    "DOI": "http://dx.doi.org/doi:10.17026/dans-zaj-v79s",
    "DiscHierarchy": [
        "1.5.9",
        "Literary Studies",
        "Poetry"
    ],
    "Discipline": "History;Humanities;Psychology;Geography",
    "Format": [
        "WAV",
        "application/x-cmdi+xml"
    ],
    "Language": [
        "Dutch"
    ],
    "MetaDataAccess": "https://easy.dans.knaw.nl/oai?verb=GetRecord&metadataPrefix=oai_datacite&identifier=oai:easy.dans.knaw.nl:easy-dataset:35855",
    "MetadataAccess": [
        "oai:easy.dans.knaw.nl:easy-dataset:35855"
    ],
    "PublicationTimestamp": "2010-07-01T11:59:59Z",
    "PublicationYear": [
        "2010"
    ],
    "Publisher": [
        "Data Archiving and Networked Services (DANS)"
    ],
    "ResourceType": [
        "Dataset", 
        "Data Collection"
    ],
    "Rights": [
        "info:eu-repo/semantics/restrictedAccess"
    ],
    "TemporalCoverage": [
        "2010-04-07",
        "2008-02-01",
        "2010-04-06"
    ],
    "author": [
        "Veteranen Instituut"
    ],
    "fulltext": "oai:easy.dans.knaw.nl:easy-dataset:35855;2018-09-18T16:53:27Z;D30000:D34000:D34300;D50000:D51000;D60000:D61000;D60000:D62000;D40000:D42000;easy-collection:1;10.17026/dans-zaj-v79s;Veteranen Instituut;Veteranen Instituut, IPNV, interview 374;Data Archiving and Networked Services (DANS);2010;Social sciences;Modern and contemporary\n                        history;Humanities;Political and administrative\n                        sciences;Psychology;Social geography;Sociology;Nederlands-Indi\u00eb;KNIL;Java 1945-1950;Oorlogsvrijwilligers;Koninklijke Marine;Soevereiniteitsoverdracht;Onafhankelijkheid Indonesi\u00eb;Inlichtingen;Militaire Inlichtingen Dienst;Officieren Koninklijke Landmacht;Koninklijke Landmacht ;Militaire opleiding in Engeland;NAVO;Carri\u00e8re bij defensie;Temporal coverage: 1945-1950;2010-04-07;2008-02-01;2010-04-06;nl;Dataset;urn:nbn:nl:ui:13-u0b-igf;easy-dataset:35855;twips.dans.knaw.nl-3693036603916007988-1270639755549;WAV;application/x-cmdi+xml;info:eu-repo/semantics/restrictedAccess;Deze oorlogsvrijwilliger ging in februari 1945 al naar Engeland voor zijn militaire opleiding. Na de Infanterie-opleiding werd hij geselecteerd bij de War Office Selection Board voor 164 OCTU in Wales. De opleiding van de expeditionele macht was eerst nog gericht op de strijd tegen Japan. Leiderschap maakte een belangrijk onderdeel uit van de officiersselectie en -opleiding. Met 4-9 RI ging hij naar Nederlands-Indi\u00eb in de zomer van 1947, waar hij langs de demarcatielijn op Java werd gelegerd. Hij was Inlichtingenofficier en werkte als zodanig nauw samen met het hoofdkwartier in Batavia en een KNIL-sergeant. Later maakte deze officier verder carri\u00e8re bij de Koninklijke Landmacht. Hij ging naar het Nato Defence College in Rome en had verschillende functies in Den Haag.;Java;Batavia;Solo;Semarang ;Djokja;Tangerang",
    "group": "danseasy",
    "groups": [
        {
            "name": "danseasy"
        }
    ],
    "name": "0dcce5f1-eca6-538d-aabc-4e0b0cb77cbe",
    "notes": [
        "Deze oorlogsvrijwilliger ging in februari 1945 al naar Engeland voor zijn militaire opleiding. Na de Infanterie-opleiding werd hij geselecteerd bij de War Office Selection Board voor 164 OCTU in Wales. De opleiding van de expeditionele macht was eerst nog gericht op de strijd tegen Japan. Leiderschap maakte een belangrijk onderdeel uit van de officiersselectie en -opleiding. Met 4-9 RI ging hij naar Nederlands-Indi\u00eb in de zomer van 1947, waar hij langs de demarcatielijn op Java werd gelegerd. Hij was Inlichtingenofficier en werkte als zodanig nauw samen met het hoofdkwartier in Batavia en een KNIL-sergeant. Later maakte deze officier verder carri\u00e8re bij de Koninklijke Landmacht. Hij ging naar het Nato Defence College in Rome en had verschillende functies in Den Haag."
    ],
    "oai_identifier": [
        "oai:easy.dans.knaw.nl:easy-dataset:35855"
    ],
    "oai_set": [
        "D30000:D34000:D34300",
        "D50000:D51000",
        "D60000:D61000",
        "D60000:D62000",
        "D40000:D42000",
        "easy-collection:1"
    ],
    "state": "active",
    "tags": [
        {
            "name": "Social sciences"
        },
        {
            "name": "Modern contemporary"
        },
        {
            "name": "history"
        },
        {
            "name": "Humanities"
        },
        {
            "name": "Political administrative"
        },
        {
            "name": "sciences"
        },
        {
            "name": "Psychology"
        },
        {
            "name": "Social geography"
        },
        {
            "name": "Sociology"
        },
        {
            "name": "Sociology"
        },
        {
            "name": "KNIL"
        },
        {
            "name": "Java -"
        }
    ],
    "title": [
        "Veteranen Instituut, IPNV, interview 374"
    ],
    "url": ""
}