{
    "Contact": [
        "cbmp_terrestrial@caff.is"
    ],
    "Contributor": [
        "Circumpolar Biodiversity Monitoring Program - CAFF"
    ],
    "DiscHierarchy": [
        "4.4.7",
        "Geosciences",
        "Environmental Research"
    ],
    "Discipline": "Environmental Research",
    "Language": [
        "English"
    ],
    "MapperVersion": [
        "1) Characterize changes in ungulate habitat quality and quantity over time, particularly reindeer and caribou winter range condition (e.g., sensitive lichen communities measured both by plots and with exclosures, biomass of forage species or groups of interest); 2) Determine changes to lichen and bryophyte communities associated with increasing inputs of sulfur, nitrogen or metals in active mining areas; 3) Determine the effects of fire and burn severity on the species composition (species diversity and % cover), vegetation structure (tree diameters and heights), and ground cover (% cover and depth) of varying vegetation types; 4) Determine vegetation change over time associated with contaminants (e.g., changes to lichen and bryophyte communities associated with increasing inputs of sulfur, nitrogen or metals in active mining areas); 5) Monitor long-term changes in lichen abundance and diversity; 6) Monitor long-term changes in plant structure - the height and density of plants - using ground plots that can be tied to remotely sensed imagery, such as aerial photographs and satellite images, for extrapolation over large areas."
    ],
    "MetaDataAccess": "http://www.polardata.ca/oai/provider?verb=GetRecord&metadataPrefix=fgdc&identifier=12391_fgdc",
    "PublicationTimestamp": "2015-04-30T11:59:59Z",
    "PublicationYear": [
        "2015"
    ],
    "Publisher": [
        "Canadian Cryospheric Information Network"
    ],
    "Rights": [
        "Limited"
    ],
    "SpatialCoverage": "(53N-71N,169W-141W)",
    "TempCoverageBegin": 63334785599,
    "TempCoverageEnd": 315537854399,
    "TemporalCoverage": " period : ( 2008-01-01T11:59:59Z - 9999-12-31T11:59:59Z ) ",
    "TemporalCoverage:BeginDate": "2008-01-01T11:59:59Z",
    "TemporalCoverage:EndDate": "9999-12-31T11:59:59Z",
    "author": [
        "Swanson, David",
        "Wesser, Sara"
    ],
    "fulltext": "12391_fgdc;2017-04-09T22:02:42Z;PDCMetadata;Swanson, David;Wesser, Sara;20150430;Terrestrial Vegetation and Soils: National Park Service Alaska Region Inventory &amp; Monitoring Program;Computer file;unknown;Swanson, David; Unpublished data;unavailable;https://www.polardata.ca/pdcsearch/PDCSearchDOI.jsp?doi_id=12391;All monitoring occurs within the ARCN (Arctic Inventory and Monitoring Network) using a \"vegetation node\" framework of clustered sampling plots.  As of 2013, the project had sampled 23 \"nodes.\"  Each vegetation node consists of a set of approximately 20 plots accessed from a central campsite. The node locations are chosen to be readily accessible and representative of major ARCN ecosystems. All nodes to date are accessible by fixed-wing aircraft landing on lakes or undeveloped gravel airstrips. The vicinity of each node is stratified into landform-based physiographic units, and proposed transect locations are placed within the strata. Transect starting points and azimuths are randomized, and plots are located systematically thereafter. A few plots locations were deliberately chosen to target features of special interest. Plots locations are recorded with a sub-meter resolution GPS and marked with a buried magnet for future re-sampling. At each plot, plant cover and height by species (or species group for many non-vascular plants) are measured by point intercept using a laser at 100 points spaced 25 cm apart (Fig. 3). Tree and sapling diameters, and seedling counts by species are made on an 8-m radius fixed-area plot (no trees were recorded in 2013). Comprehensive site and soil descriptions are made at each plot, and the intensity of herbivore effects on vegetation are assessed.;1) Characterize changes in ungulate habitat quality and quantity over time, particularly reindeer and caribou winter range condition (e.g., sensitive lichen communities measured both by plots and with exclosures, biomass of forage species or groups of interest); 2) Determine changes to lichen and bryophyte communities associated with increasing inputs of sulfur, nitrogen or metals in active mining areas; 3) Determine the effects of fire and burn severity on the species composition (species diversity and % cover), vegetation structure (tree diameters and heights), and ground cover (% cover and depth) of varying vegetation types; 4) Determine vegetation change over time associated with contaminants (e.g., changes to lichen and bryophyte communities associated with increasing inputs of sulfur, nitrogen or metals in active mining areas); 5) Monitor long-term changes in lichen abundance and diversity; 6) Monitor long-term changes in plant structure - the height and density of plants - using ground plots that can be tied to remotely sensed imagery, such as aerial photographs and satellite images, for extrapolation over large areas.;Summary: Not Applicable Research Program(s): CBMP/CAFF - Terrestrial. For further information: http://catalog.northslope.org/catalogs/646;20080101;99991231;NULL;In work;As needed;-169;-141;71.25;53;NULL;Alaska;Climate;Landscape;Soils;Species composition;Vegetation;Wetland;Alaska, USA;NULL;Limited;NULL;Circumpolar Biodiversity Monitoring Program - CAFF;CBMP Terrestrial - CAFF;NULL;mailing;Borgir, Nordurslod;Akureyri;N/A;600;Iceland;+ 354 462 3350;cbmp_terrestrial@caff.is;NULL;Polar Data Catalogue;Canadian Cryospheric Information Network;Director;mailing;200 University Avenue West, University of Waterloo;Waterloo;Ontario;N2L 3G1;Canada;(519) 888-4567 x32689;(519) 888-6768;pdc@uwaterloo.ca;12391;Research programs, CCIN, or ArcticNet take no liability for the use or transmission of this data;20150430;20150430;CBMP Terrestrial - CAFF;Circumpolar Biodiversity Monitoring Program - CAFF;mailing;Borgir, Nordurslod;Akureyri;N/A;600;Iceland;+ 354 462 3350;cbmp_terrestrial@caff.is;FGDC Content Standards for Digital Geospatial Metadata;FGDC-STD-001-1998",
    "group": "pdc",
    "groups": [
        {
            "name": "pdc"
        }
    ],
    "name": "0c3e9cb4-c96a-5bce-a8b2-8183b5cf5a1a",
    "notes": [
        "All monitoring occurs within the ARCN (Arctic Inventory and Monitoring Network) using a \"vegetation node\" framework of clustered sampling plots.  As of 2013, the project had sampled 23 \"nodes.\"  Each vegetation node consists of a set of approximately 20 plots accessed from a central campsite. The node locations are chosen to be readily accessible and representative of major ARCN ecosystems. All nodes to date are accessible by fixed-wing aircraft landing on lakes or undeveloped gravel airstrips. The vicinity of each node is stratified into landform-based physiographic units, and proposed transect locations are placed within the strata. Transect starting points and azimuths are randomized, and plots are located systematically thereafter. A few plots locations were deliberately chosen to target features of special interest. Plots locations are recorded with a sub-meter resolution GPS and marked with a buried magnet for future re-sampling. At each plot, plant cover and height by species (or species group for many non-vascular plants) are measured by point intercept using a laser at 100 points spaced 25 cm apart (Fig. 3). Tree and sapling diameters, and seedling counts by species are made on an 8-m radius fixed-area plot (no trees were recorded in 2013). Comprehensive site and soil descriptions are made at each plot, and the intensity of herbivore effects on vegetation are assessed."
    ],
    "oai_identifier": [
        "12391_fgdc"
    ],
    "oai_set": [
        "PDCMetadata"
    ],
    "spatial": "{\"type\":\"Polygon\",\"coordinates\":[[[-169,53],[-169,71.25],[-141,71.25],[-141,53],[-169,53]]]}",
    "state": "active",
    "tags": [
        {
            "name": "Alaska"
        },
        {
            "name": "Climate"
        },
        {
            "name": "Landscape"
        },
        {
            "name": "Soils"
        },
        {
            "name": "Species composition"
        },
        {
            "name": "Vegetation"
        },
        {
            "name": "Wetland"
        }
    ],
    "title": [
        "Terrestrial Vegetation and Soils: National Park Service Alaska Region Inventory &amp; Monitoring Program"
    ],
    "url": "https://www.polardata.ca/pdcsearch/PDCSearchDOI.jsp?doi_id=12391"
}