{
    "Contact": [
        "accidents@slf.ch"
    ],
    "Contributor": [
        "EnviDat"
    ],
    "DiscHierarchy": [],
    "Discipline": "Not stated",
    "Format": [
        "CSV"
    ],
    "MetaDataAccess": "https://www.envidat.ch/oai?verb=GetRecord&metadataPrefix=iso19139&identifier=doi:10.16904/13",
    "PublicationTimestamp": "2018-12-31T11:59:59Z",
    "PublicationYear": [
        "2018"
    ],
    "Publisher": [
        "WSL Institute for Snow and Avalanche Research SLF"
    ],
    "Rights": [
        "Open Data Commons Open Database License (ODbL)"
    ],
    "SpatialCoverage": "(46N-48N,6 E-10E)",
    "author": [
        "Avalanche Warning Service SLF"
    ],
    "fulltext": "oai:envidat.ch:10.16904/13;2018-11-12T08:50:36Z;doi:10.16904/13;Eng;MD_CharacterSetCode_utf8;Avalanche Warning Service SLF;WSL Institute for Snow and Avalanche Research SLF;accidents@slf.ch;2017-03-01T12:20:55;ISO 19115:2003/19139;1.0;EPSG:4326;Fatal avalanche accidents in Switzerland since 1995-1996;2018-12-31;This data collection contains information concerning all accidents by snow avalanches causing at least one fatality in Switzerland. The data set commences on 01/10/1995. After the completion of a hydrological year, the new data is added.      The following information is provided:         * avalanche identifier      * date of the accident     * accuracy of the date in range of days before and after     * canton     * name of the locality     * start zone of the avalanche       * coordinates (Swiss coordinate system, approximately in middle of start zone)       * accuracy of the coordinates in meters    * elevation (in meteres above sea level, app. in middle of start zone)      * slope aspect (main orientation of start zone)       * slope inclination (in degree, steepest point within start zone)       * number of dead persons      * number of caught persons     * number of fully buried persons       * forecasted avalanche danger level      * activity/location of the accident party at the time of the incident;Avalanche Warning Service SLF;WSL Institute for Snow and Avalanche Research SLF;accidents@slf.ch;AVALANCHE ACCIDENT STATISTICS;AVALANCHE ACCIDENTS;AVALANCHE FATALITIES;Open Data Commons Open Database License (ODbL);Eng;MD_CharacterSetCode_utf8;5.95587;10.49203;45.81802;47.80838;CSV;https://www.envidat.ch/dataset/fatal-avalanche-accidents-switzerland-1995;HTTPS;DATASET METADATA;information;https://www.envidat.ch/dataset/f7160261-c98d-4d49-8966-10c1b0a32831/resource/6dd040cb-e505-4373-8f7f-e932e7d73c17/download/avalanche_accidents_switzerland_since_1995.csv;HTTPS;FATAL AVALANCHE ACCIDENTS IN SWITZERLAND SINCE 1995-1996;download",
    "group": "envidat",
    "groups": [
        {
            "name": "envidat"
        }
    ],
    "name": "c7798a7d-2a26-5255-a779-a7df7a337707",
    "notes": [
        "This data collection contains information concerning all accidents by snow avalanches causing at least one fatality in Switzerland. The data set commences on 01/10/1995. After the completion of a hydrological year, the new data is added.      The following information is provided:         * avalanche identifier      * date of the accident     * accuracy of the date in range of days before and after     * canton     * name of the locality     * start zone of the avalanche       * coordinates (Swiss coordinate system, approximately in middle of start zone)       * accuracy of the coordinates in meters    * elevation (in meteres above sea level, app. in middle of start zone)      * slope aspect (main orientation of start zone)       * slope inclination (in degree, steepest point within start zone)       * number of dead persons      * number of caught persons     * number of fully buried persons       * forecasted avalanche danger level      * activity/location of the accident party at the time of the incident"
    ],
    "oai_identifier": [
        "doi:10.16904/13",
        "oai:envidat.ch:10.16904/13"
    ],
    "oai_set": "",
    "spatial": "{\"type\":\"Polygon\",\"coordinates\":[[[5.95587,45.81802],[5.95587,47.80838],[10.49203,47.80838],[10.49203,45.81802],[5.95587,45.81802]]]}",
    "state": "active",
    "tags": [
        {
            "name": "AVALANCHE ACCIDENT STATISTICS"
        },
        {
            "name": "AVALANCHE ACCIDENTS"
        },
        {
            "name": "AVALANCHE FATALITIES"
        }
    ],
    "title": [
        "Fatal avalanche accidents in Switzerland since 1995-1996"
    ],
    "url": "https://www.envidat.ch/dataset/f7160261-c98d-4d49-8966-10c1b0a32831/resource/6dd040cb-e505-4373-8f7f-e932e7d73c17/download/avalanche_accidents_switzerland_since_1995.csv"
}