{
    "Contact": [
        "lehning@slf.ch"
    ],
    "Contributor": [
        "EnviDat"
    ],
    "DiscHierarchy": [],
    "Discipline": "Not stated",
    "Format": [
        "ZIP"
    ],
    "MetaDataAccess": "https://www.envidat.ch/oai?verb=GetRecord&metadataPrefix=iso19139&identifier=doi:10.16904/23",
    "PublicationTimestamp": "2016-12-31T11:59:59Z",
    "PublicationYear": [
        "2016"
    ],
    "Publisher": [
        "WSL"
    ],
    "Rights": [
        "Open Data Commons Open Database License (ODbL)"
    ],
    "SpatialCoverage": "(47N-47N,10E-10E)",
    "author": [
        "Michael Lehning"
    ],
    "fulltext": "oai:envidat.ch:10.16904/23;2018-10-24T13:31:41Z;doi:10.16904/23;Eng;MD_CharacterSetCode_utf8;Michael Lehning;WSL;lehning@slf.ch;2017-08-15T15:23:58;ISO 19115:2003/19139;1.0;EPSG:4326;Precipitation Scaling Data Set (V\u00f6geli et al., Frontiers);2016-12-31;Dataset (Model input, snow distribution and validation) for the precipitation scaling paper, which should be cited along with the data set citation.    This data is useful for distributed hydrological modelling or other tasks that involve the study of snow distribution and precipitation in the high Alpine.     The format of the data is for Alpine3D (models.slf.ch) model runs but other models could be used, too.    Please cite:    _V\u00f6geli, C., Lehning, M., Wever, N., Bavay M., 2016: Scaling Precipitation Input to Spatially Distributed Hydrological Models by Measured Snow Distribution., Front. Earth Sci. 4: 108. doi: 10.3389/feart.2016.00108._    Dataset is provided as a single zip file.   The archive contains two directories, the valuable distributed snow depth maps for the landscape Davos and the simulation input.   The archive also contains the file: \"ReadMeMetadataDataSetPrecipitationScaling\" which explains the data structure.;Michael Lehning;WSL;lehning@slf.ch;ALPINE PRECIPITATION;ALPINE3D;ALPINE3D SIMULATIONS;SNOW;SNOW COVER;SNOW DISTRIBUTION;SNOW HYDROLOGY;Open Data Commons Open Database License (ODbL);Eng;MD_CharacterSetCode_utf8;9.70985412598;10.0037384033;46.6866603841;46.8606605287;ZIP;https://www.envidat.ch/dataset/10-16904-23;HTTPS;DATASET METADATA;information;https://www.envidat.ch/dataset/e3176e82-1561-4df0-8830-76eb4f66166b/resource/34945680-7cb0-47a1-96cb-ee6832a2b17c/download/archivevogeliforenvidat.zip;HTTPS;ADS DATASETS AND SIMULATION INPUTS;download",
    "group": "envidat",
    "groups": [
        {
            "name": "envidat"
        }
    ],
    "name": "eea9a427-a09c-5204-8dc3-e1908db794cc",
    "notes": [
        "Dataset (Model input, snow distribution and validation) for the precipitation scaling paper, which should be cited along with the data set citation.    This data is useful for distributed hydrological modelling or other tasks that involve the study of snow distribution and precipitation in the high Alpine.     The format of the data is for Alpine3D (models.slf.ch) model runs but other models could be used, too.    Please cite:    _V\u00f6geli, C., Lehning, M., Wever, N., Bavay M., 2016: Scaling Precipitation Input to Spatially Distributed Hydrological Models by Measured Snow Distribution., Front. Earth Sci. 4: 108. doi: 10.3389/feart.2016.00108._    Dataset is provided as a single zip file.   The archive contains two directories, the valuable distributed snow depth maps for the landscape Davos and the simulation input.   The archive also contains the file: \"ReadMeMetadataDataSetPrecipitationScaling\" which explains the data structure."
    ],
    "oai_identifier": [
        "doi:10.16904/23",
        "oai:envidat.ch:10.16904/23"
    ],
    "oai_set": "",
    "spatial": "{\"type\":\"Polygon\",\"coordinates\":[[[9.70985412598,46.6866603841],[9.70985412598,46.8606605287],[10.0037384033,46.8606605287],[10.0037384033,46.6866603841],[9.70985412598,46.6866603841]]]}",
    "state": "active",
    "tags": [
        {
            "name": "ALPINE PRECIPITATION"
        },
        {
            "name": "ALPINED"
        },
        {
            "name": "ALPINED SIMULATIONS"
        },
        {
            "name": "SNOW"
        },
        {
            "name": "SNOW COVER"
        },
        {
            "name": "SNOW DISTRIBUTION"
        },
        {
            "name": "SNOW HYDROLOGY"
        }
    ],
    "title": [
        "Precipitation Scaling Data Set (V\u00f6geli et al., Frontiers)"
    ],
    "url": "https://www.envidat.ch/dataset/e3176e82-1561-4df0-8830-76eb4f66166b/resource/34945680-7cb0-47a1-96cb-ee6832a2b17c/download/archivevogeliforenvidat.zip"
}