{
    "Contact": [
        "gerberf@slf.ch"
    ],
    "Contributor": [
        "EnviDat"
    ],
    "DiscHierarchy": [],
    "Discipline": "Not stated",
    "Format": [
        "ZIP"
    ],
    "MetaDataAccess": "https://www.envidat.ch/oai?verb=GetRecord&metadataPrefix=iso19139&identifier=doi:10.16904/19",
    "PublicationTimestamp": "2017-12-31T11:59:59Z",
    "PublicationYear": [
        "2017"
    ],
    "Publisher": [
        "Laboratory of Cryospheric Sciences, School of Architecture and Civil Engineering, \u00c9cole Polytechnique F\u00e9d\u00e9rale de Lausanne, Lausanne, Switzerland and WSL Institute for Snow and Avalanche Research SLF, Davos, Switzerland"
    ],
    "Rights": [
        "Open Data Commons Open Database License (ODbL)"
    ],
    "author": [
        "Franziska Gerber"
    ],
    "fulltext": "oai:envidat.ch:10.16904/19;2018-06-16T11:07:20Z;doi:10.16904/19;Eng;MD_CharacterSetCode_utf8;Franziska Gerber;Laboratory of Cryospheric Sciences, School of Architecture and Civil Engineering, \u00c9cole Polytechnique F\u00e9d\u00e9rale de Lausanne, Lausanne, Switzerland and WSL Institute for Snow and Avalanche Research SLF, Davos, Switzerland;gerberf@slf.ch;2017-06-01T12:46:02;ISO 19115:2003/19139;1.0;EPSG:4326;DISCHMEX - Observations and simulations of the close-ridge small-scale atmospheric flow field and snow accumulation at Sattelhorn, Dischma valley, Davos, Switzerland.;2017-12-31;The data presented here corresponds to the publication \"A Close-Ridge Small-Scale Atmospheric Flow Field and its Influence on Snow Accumulation\" (Gerber et al., 2017), which investigates an eddy-like structure in the vicinity of the Sattelhorn in the Dischma valley (Davos Switzerland)  and its influence on snow accumulation. The dataset contains:    * Alpine3D: Alpine3D snow depth grids (25 m resolution) for two simulations with and without snow redistribution.  * ARPS: 10 ARPS simulations (25 m horizontal resolution) with different model setups (wind direction, wind speed, stability).  * LiDAR: Processed LiDAR PPI (D2_PPI_1h) and RHI (D2_cross_1h) across the valley with a hourly resolution for the period 27 October 2015 01:00 - 29 October 2015c 21:00 (spatial resolution: 25 m).  * meteostations-dischma: Meteorological station data of two meteorological stations in the Dischma valley with 10 minute resolution for the period 28 October 2015 - 30 October 2015.  * TLS: Snow depth change data (m) between 28 October 2015 and 30 October 2015 based on terrestrial laser scans.    For more details about the simulation and observation data, see Gerber et al., 2017.    __Publication__: Gerber et al., 2017: A Close-Ridge Small-Scale Atmospheric Flow Field and its Influence on Snow Accumulation, submitted to JGR - Atmospheres.;Franziska Gerber;Laboratory of Cryospheric Sciences, School of Architecture and Civil Engineering, \u00c9cole Polytechnique F\u00e9d\u00e9rale de Lausanne, Lausanne, Switzerland and WSL Institute for Snow and Avalanche Research SLF, Davos, Switzerland;gerberf@slf.ch;LEE-SIDE FLOW FIELD;LIDAR;PREFERENTIAL DEPOSITION;TLS;Open Data Commons Open Database License (ODbL);Eng;MD_CharacterSetCode_utf8;9.852357673 46.700152853;9.935928682 46.700152853;9.935928682 46.739303111;9.852357673 46.739303111;9.852357673 46.700152853;ZIP;https://www.envidat.ch/dataset/10-16904-19;HTTPS;DATASET METADATA;information;http://montblanc.slf.ch/owncloud/index.php/s/9COZ0CRW8r255OL;HTTP;DATASET;download",
    "group": "envidat",
    "groups": [
        {
            "name": "envidat"
        }
    ],
    "name": "fa681dd6-0f3e-5cb1-8595-16e5d7b5150f",
    "notes": [
        "The data presented here corresponds to the publication \"A Close-Ridge Small-Scale Atmospheric Flow Field and its Influence on Snow Accumulation\" (Gerber et al., 2017), which investigates an eddy-like structure in the vicinity of the Sattelhorn in the Dischma valley (Davos Switzerland)  and its influence on snow accumulation. The dataset contains:    * Alpine3D: Alpine3D snow depth grids (25 m resolution) for two simulations with and without snow redistribution.  * ARPS: 10 ARPS simulations (25 m horizontal resolution) with different model setups (wind direction, wind speed, stability).  * LiDAR: Processed LiDAR PPI (D2_PPI_1h) and RHI (D2_cross_1h) across the valley with a hourly resolution for the period 27 October 2015 01:00 - 29 October 2015c 21:00 (spatial resolution: 25 m).  * meteostations-dischma: Meteorological station data of two meteorological stations in the Dischma valley with 10 minute resolution for the period 28 October 2015 - 30 October 2015.  * TLS: Snow depth change data (m) between 28 October 2015 and 30 October 2015 based on terrestrial laser scans.    For more details about the simulation and observation data, see Gerber et al., 2017.    __Publication__: Gerber et al., 2017: A Close-Ridge Small-Scale Atmospheric Flow Field and its Influence on Snow Accumulation, submitted to JGR - Atmospheres."
    ],
    "oai_identifier": [
        "doi:10.16904/19",
        "oai:envidat.ch:10.16904/19"
    ],
    "oai_set": "",
    "state": "active",
    "tags": [
        {
            "name": "LEE-SIDE FLOW FIELD"
        },
        {
            "name": "LIDAR"
        },
        {
            "name": "PREFERENTIAL DEPOSITION"
        },
        {
            "name": "TLS"
        }
    ],
    "title": [
        "DISCHMEX - Observations and simulations of the close-ridge small-scale atmospheric flow field and snow accumulation at Sattelhorn, Dischma valley, Davos, Switzerland."
    ],
    "url": "http://montblanc.slf.ch/owncloud/index.php/s/9COZ0CRW8r255OL"
}