{
    "Contact": [
        "SEANOE"
    ],
    "DOI": "http://dx.doi.org/10.17882/59867",
    "DiscHierarchy": [
        "4.4.4",
        "Geosciences",
        "Oceanography/Marine Science"
    ],
    "Discipline": "Oceanography/Marine Science",
    "MetaDataAccess": "http://www.seanoe.org/oai/OAIHandler?verb=GetRecord&metadataPrefix=oai_dc&identifier=1cc66e50-1d82-54f8-9c55-5844ca0236a7",
    "PublicationTimestamp": "2019-04-03T11:59:59Z",
    "PublicationYear": [
        "2019"
    ],
    "Publisher": [
        "SEANOE"
    ],
    "ResourceType": [
        "dataset"
    ],
    "Rights": [
        "CC-BY-NC-SA"
    ],
    "SpatialCoverage": "(37N-42N,7 E-10E)",
    "TemporalCoverage": " point in time : None",
    "author": [
        "Ribotti, Alberto",
        "Borghini, Mireno",
        "Di Bitetto, Massimiliano",
        "Sorgente, Roberto"
    ],
    "fulltext": "oai:seanoe.org:59867;2019-04-25;CTD profiles in western Sardinia (2000 - 2004), western Mediterranean;Ribotti, Alberto;Di Bitetto, Massimiliano;Borghini, Mireno;Sorgente, Roberto;Sardinia;water masses;mesoscale activity;hydrological data;western Mediterranean;CTD profiles;Hydrological data have been collected during 7 oceanographic cruises, named medgoos, organized in the Sardinia Sea and in the Sardinia Channel between May 2000 and January 2004 (table 1) by the Italian Consiglio Nazionale delle Ricerche (CNR).\nTab.1\n\nThe 61,30 meters long R/V Urania of CNR was used during all cruises. Data of conductivity, temperature, dissolved oxygen (DO) and Chlorophyll-a fluorescence (Chl-a) were acquired by a SBE911 plus CTD probe (Sea-Bird Inc.) equipped with a 24 Niskin bottle rosette for water column samples collection. The CTD data were quality checked and processed by Seasoft software. Then salinity was checked against the on-board analyses of water samples by a Guildline-Autosal salinometer. The same for DO data checked against Winkler titration analyses. Chl-a data were not calibrated, so they are reported as Relative Fluorescence Units. During cruises from medgoos4 to medgoos7 acquired temperature data were checked at defined depths against inverted thermometers installed in correspondence of the Niskin bottles number 1, 3, 5, 7 of the rosette sampler. Pre-cruise and post-cruise calibrations of the sensors were performed at the SACLANT Center (now NATO-CMRE) of La Spezia (Italy). Redundant sensors were often used for both temperature and salinity measurements, apart during the medgoos1 and medgoos2 cruises.\nThe vessel was positioned using an integrated navigation system consisting of two DGPS antennas managed by Andrews Hydrographics software installed on HP 386, 33 MHz PCs.\nThe data set is provided per cruise as ODV Spreadsheet files in TXT format:\n\t- Cruise name\n\t- Station number\n\t- Type of acquisition (here C)\n\t- Date in mon/day/yr and Time in hh:mm\n\t- Coordinates in Longitude [degrees_east] and Latitude [degrees_north]\n\t- Bot. Depth [m]\n\t- Ship name\n\t- Pressure, Digiquartz [db]\n\t- Conductivity [mS/cm]\n\t- Fluorescence, Seatech\n\t- Temperature [deg C]; IPTS-68 in medgoos1; ITS-68 in medgoos2, 6; ITS-90 in medgoos3, 4, 5, 7\n\t- Oxygen, Beckman/YSI , WS = 3 [ml/l]\n\t- Depth [salt water, m]\n\t- Practical Salinity from Conductivity [PSS-78]\n;SEANOE;2019-04-03;dataset;DOI:10.17882/59867;http://dx.doi.org/10.17882/59867;North 41.5, South 37.0, East 9.5, West 7.0;http://www.seanoe.org/data/00487/59867/illustration.gif;37.0 7.0 41.5 9.5;CC-BY-NC-SA",
    "group": "seanoe",
    "groups": [
        {
            "name": "seanoe"
        }
    ],
    "name": "1cc66e50-1d82-54f8-9c55-5844ca0236a7",
    "notes": [
        "Hydrological data have been collected during 7 oceanographic cruises, named medgoos, organized in the Sardinia Sea and in the Sardinia Channel between May 2000 and January 2004 (table 1) by the Italian Consiglio Nazionale delle Ricerche (CNR).\nTab.1\n\nThe 61,30 meters long R/V Urania of CNR was used during all cruises. Data of conductivity, temperature, dissolved oxygen (DO) and Chlorophyll-a fluorescence (Chl-a) were acquired by a SBE911 plus CTD probe (Sea-Bird Inc.) equipped with a 24 Niskin bottle rosette for water column samples collection. The CTD data were quality checked and processed by Seasoft software. Then salinity was checked against the on-board analyses of water samples by a Guildline-Autosal salinometer. The same for DO data checked against Winkler titration analyses. Chl-a data were not calibrated, so they are reported as Relative Fluorescence Units. During cruises from medgoos4 to medgoos7 acquired temperature data were checked at defined depths against inverted thermometers installed in correspondence of the Niskin bottles number 1, 3, 5, 7 of the rosette sampler. Pre-cruise and post-cruise calibrations of the sensors were performed at the SACLANT Center (now NATO-CMRE) of La Spezia (Italy). Redundant sensors were often used for both temperature and salinity measurements, apart during the medgoos1 and medgoos2 cruises.\nThe vessel was positioned using an integrated navigation system consisting of two DGPS antennas managed by Andrews Hydrographics software installed on HP 386, 33 MHz PCs.\nThe data set is provided per cruise as ODV Spreadsheet files in TXT format:\n\t- Cruise name\n\t- Station number\n\t- Type of acquisition (here C)\n\t- Date in mon/day/yr and Time in hh:mm\n\t- Coordinates in Longitude [degrees_east] and Latitude [degrees_north]\n\t- Bot. Depth [m]\n\t- Ship name\n\t- Pressure, Digiquartz [db]\n\t- Conductivity [mS/cm]\n\t- Fluorescence, Seatech\n\t- Temperature [deg C]; IPTS-68 in medgoos1; ITS-68 in medgoos2, 6; ITS-90 in medgoos3, 4, 5, 7\n\t- Oxygen, Beckman/YSI , WS = 3 [ml/l]\n\t- Depth [salt water, m]\n\t- Practical Salinity from Conductivity [PSS-78]\n"
    ],
    "oai_identifier": [
        "1cc66e50-1d82-54f8-9c55-5844ca0236a7"
    ],
    "oai_set": "",
    "spatial": "{\"type\":\"Polygon\",\"coordinates\":[[[7.0,37.0],[7.0,41.5],[9.5,41.5],[9.5,37.0],[7.0,37.0]]]}",
    "state": "active",
    "tags": [
        {
            "name": "Sardinia"
        },
        {
            "name": "water masses"
        },
        {
            "name": "mesoscale activity"
        },
        {
            "name": "hydrological data"
        },
        {
            "name": "western Mediterranean"
        },
        {
            "name": "CTD profiles"
        }
    ],
    "title": [
        "CTD profiles in western Sardinia (2000 - 2004), western Mediterranean"
    ],
    "url": ""
}