{
    "Contact": [
        "SEANOE"
    ],
    "DOI": "http://dx.doi.org/10.17882/46446",
    "DiscHierarchy": [
        "4.4.4",
        "Geosciences",
        "Oceanography/Marine Science"
    ],
    "Discipline": "Oceanography/Marine Science",
    "MetaDataAccess": "http://www.seanoe.org/oai/OAIHandler?verb=GetRecord&metadataPrefix=oai_dc&identifier=1e449dcc-2026-5d86-9501-3013d1cc40f4",
    "PublicationTimestamp": "2016-07-01T11:59:59Z",
    "PublicationYear": [
        "2016"
    ],
    "Publisher": [
        "SEANOE"
    ],
    "ResourceType": [
        "dataset"
    ],
    "Rights": [
        "CC-BY-NC"
    ],
    "SpatialCoverage": "(40N-60N,45W-5 E)",
    "TemporalCoverage": " point in time : None",
    "author": [
        "Daniault, Nathalie",
        "Lherminier, Pascale",
        "Mercier, Herle"
    ],
    "fulltext": "oai:seanoe.org:46446;2016-10-12;Gridded property and transport data of the biennial Greenland-Portugal A25 OVIDE line;Daniault, Nathalie;Mercier, Herle;Lherminier, Pascale;North Atlantic Ocean;circulation;water mass;transport;OVIDE;This data set contains the gridded hydrographic and transport data for the biennial Go-Ship A25 Greenland\u2013Portugal OVIDE section from 2002 to 2012. The properties and transports are mapped on a 7km x 1m grid. Using a common grid facilitates the comparison between the different occupations of the line and the averaging. This data set was used in Daniault et al. (2016, Progress in Oceanography) to which the reader is referred for a description of the gridding method.\n;SEANOE;2016-10;dataset;DOI:10.17882/46446;http://dx.doi.org/10.17882/46446;North 60.0, South 40.0, East 5.0, West -45.0;https://www.seanoe.org/data/00353/46446/illustration.gif;40.0 -45.0 60.0 5.0;CC-BY-NC",
    "group": "seanoe",
    "groups": [
        {
            "name": "seanoe"
        }
    ],
    "name": "1e449dcc-2026-5d86-9501-3013d1cc40f4",
    "notes": [
        "This data set contains the gridded hydrographic and transport data for the biennial Go-Ship A25 Greenland\u2013Portugal OVIDE section from 2002 to 2012. The properties and transports are mapped on a 7km x 1m grid. Using a common grid facilitates the comparison between the different occupations of the line and the averaging. This data set was used in Daniault et al. (2016, Progress in Oceanography) to which the reader is referred for a description of the gridding method.\n"
    ],
    "oai_identifier": [
        "1e449dcc-2026-5d86-9501-3013d1cc40f4"
    ],
    "oai_set": "",
    "spatial": "{\"type\":\"Polygon\",\"coordinates\":[[[-45.0,40.0],[-45.0,60.0],[5.0,60.0],[5.0,40.0],[-45.0,40.0]]]}",
    "state": "active",
    "tags": [
        {
            "name": "North Atlantic Ocean"
        },
        {
            "name": "circulation"
        },
        {
            "name": "water mass"
        },
        {
            "name": "transport"
        },
        {
            "name": "OVIDE"
        }
    ],
    "title": [
        "Gridded property and transport data of the biennial Greenland-Portugal A25 OVIDE line"
    ],
    "url": ""
}