{
    "Contact": [
        "SEANOE"
    ],
    "DOI": "http://dx.doi.org/10.17882/59777",
    "DiscHierarchy": [
        "4.4.4",
        "Geosciences",
        "Oceanography/Marine Science"
    ],
    "Discipline": "Oceanography/Marine Science",
    "MetaDataAccess": "http://www.seanoe.org/oai/OAIHandler?verb=GetRecord&metadataPrefix=oai_dc&identifier=0dfb1443-3871-5820-9633-bb5588cce052",
    "PublicationTimestamp": "2019-04-11T11:59:59Z",
    "PublicationYear": [
        "2019"
    ],
    "Publisher": [
        "SEANOE"
    ],
    "ResourceType": [
        "dataset"
    ],
    "Rights": [
        "CC-BY-NC-ND"
    ],
    "SpatialCoverage": "(37N-43N,9 E-16E)",
    "TempCoverageBegin": 142021943999,
    "TempCoverageEnd": 142021943999,
    "TemporalCoverage": " point in time : 4501-07-01T11:59:59Z",
    "TemporalCoverage:BeginDate": "4501-07-01T11:59:59Z",
    "TemporalCoverage:EndDate": "4501-07-01T11:59:59Z",
    "author": [
        "Vetrano, Anna",
        "Ribotti, Alberto",
        "Magni, Paolo",
        "Borghini, Mireno",
        "Chiappini, Catia"
    ],
    "fulltext": "oai:seanoe.org:59777;2019-04-11;GROUP:EMSO;ICHNUSSA 2015;Ribotti, Alberto;Magni, Paolo;Vetrano, Anna;Chiappini, Catia;Borghini, Mireno;Mediterranean;Temperature;Salinity;Dissolved Oxygen;Fluorescence;hydrological data;CTD profiles;The sampling plan of the ICHNUSSA2015 proposes the route already covered in previous cruises since 2000 to acquire data for the activities of Cal/Val of oceanographic ecosystem or for the validation of forecasting numerical models at different spatial scales. Then the aim is also to study the inter-annual variability of biogeochemical and physical properties of the water masses in crucial areas for understanding the circulation and exchange between basins, in particular the transport of heat and salt in the western Mediterranean. In particular, we want to study the exchange between western and eastern Mediterranean and the waters recirculating or formed in the Algerian-Proven\u00e7al basin (like the new deep water in the Gulf of Lions) and along the transect Sardinia-Balearic islands. Then we want to monitor characteristics and distribution of the new western Mediterranean deep water and its possible effects on the general circulation of the Mediterranean. The ICHNUSSA2015 is designed to approximately replicate the stations of previous cruises like those named medgoos, MedCO or MedOc and the most recent ICHNUSSA2012 and 2013.\nCTD Casts\nAt every station, pressure (P), salinity (S), potential temperature (\u03b8) dissolved oxygen concentration (DO) and Fluorescence were measured with a CTD-rosette system consisting of a CTD SBE 911 plus, and a General Oceanics rosette with 24 Niskin Bottles (12 liters each). Temperature measurements were performed with a SBE-3/F thermometer, with a resolution of 0.00015 \u00b0C/bit at -1 \u00b0C or 0.00018\u00b0C/bit at 31 \u00b0C, and conductivity measurements were performed with a SBE-4C sensor, with a resolution of 3 x 10-4 S/m. Dissolved oxygen was measured with a SBE-43 sensor (resolution 4.3\u03bcM). The vertical profiles of all parameters were obtained by sampling the signals at 24 Hz, with the CTD/rosette going down at a speed of 1 m/s. The data were processed on board, and the coarse errors were corrected thanks to the sampling and analyzing on board o f oxygen and salinity of the deepest station. The rosette is equipped with a sonar altimeter which intercept the bottom 70-50 meters before getting to it. The altimeter is used just for safety, to avoid the rosette to touch the bottom, and for more precision in measuring depth.\nOxygen and Salinity Determination\nSalinity samples were collected, stored and analyzed with a Guildline Portasal Salinometer, standardized with IPSO standard 34.999 PSu Water and at controlled temperature. Also dissolved oxygen samples were collected and analyzed with the Winkler method,using a computer controlled potentiometric end-point titration procedure. Samples were taken from the Niskins bottle with the recommendedprecautions and following the Winkler procedure.\nThe dataset is provided as an ODV txt file and has been processed in accordance to the SeaDataNet's Data QC rules; for each station (66 station) the file contains the following parameters: DEPTH, PRESS, TEMP, PSAL, DOXY and FLUOZZ.\n;SEANOE;2019-04-11;dataset;DOI:10.17882/59777;http://dx.doi.org/10.17882/59777;North 43.450166, South 37.226833, East 15.5, West 8.8;http://www.seanoe.org/data/00486/59777/illustration.gif;37.226833 8.8 43.450166 15.5;CC-BY-NC-ND",
    "group": "seanoe",
    "groups": [
        {
            "name": "seanoe"
        }
    ],
    "name": "0dfb1443-3871-5820-9633-bb5588cce052",
    "notes": [
        "The sampling plan of the ICHNUSSA2015 proposes the route already covered in previous cruises since 2000 to acquire data for the activities of Cal/Val of oceanographic ecosystem or for the validation of forecasting numerical models at different spatial scales. Then the aim is also to study the inter-annual variability of biogeochemical and physical properties of the water masses in crucial areas for understanding the circulation and exchange between basins, in particular the transport of heat and salt in the western Mediterranean. In particular, we want to study the exchange between western and eastern Mediterranean and the waters recirculating or formed in the Algerian-Proven\u00e7al basin (like the new deep water in the Gulf of Lions) and along the transect Sardinia-Balearic islands. Then we want to monitor characteristics and distribution of the new western Mediterranean deep water and its possible effects on the general circulation of the Mediterranean. The ICHNUSSA2015 is designed to approximately replicate the stations of previous cruises like those named medgoos, MedCO or MedOc and the most recent ICHNUSSA2012 and 2013.\nCTD Casts\nAt every station, pressure (P), salinity (S), potential temperature (\u03b8) dissolved oxygen concentration (DO) and Fluorescence were measured with a CTD-rosette system consisting of a CTD SBE 911 plus, and a General Oceanics rosette with 24 Niskin Bottles (12 liters each). Temperature measurements were performed with a SBE-3/F thermometer, with a resolution of 0.00015 \u00b0C/bit at -1 \u00b0C or 0.00018\u00b0C/bit at 31 \u00b0C, and conductivity measurements were performed with a SBE-4C sensor, with a resolution of 3 x 10-4 S/m. Dissolved oxygen was measured with a SBE-43 sensor (resolution 4.3\u03bcM). The vertical profiles of all parameters were obtained by sampling the signals at 24 Hz, with the CTD/rosette going down at a speed of 1 m/s. The data were processed on board, and the coarse errors were corrected thanks to the sampling and analyzing on board o f oxygen and salinity of the deepest station. The rosette is equipped with a sonar altimeter which intercept the bottom 70-50 meters before getting to it. The altimeter is used just for safety, to avoid the rosette to touch the bottom, and for more precision in measuring depth.\nOxygen and Salinity Determination\nSalinity samples were collected, stored and analyzed with a Guildline Portasal Salinometer, standardized with IPSO standard 34.999 PSu Water and at controlled temperature. Also dissolved oxygen samples were collected and analyzed with the Winkler method,using a computer controlled potentiometric end-point titration procedure. Samples were taken from the Niskins bottle with the recommendedprecautions and following the Winkler procedure.\nThe dataset is provided as an ODV txt file and has been processed in accordance to the SeaDataNet's Data QC rules; for each station (66 station) the file contains the following parameters: DEPTH, PRESS, TEMP, PSAL, DOXY and FLUOZZ.\n"
    ],
    "oai_identifier": [
        "0dfb1443-3871-5820-9633-bb5588cce052"
    ],
    "oai_set": "",
    "spatial": "{\"type\":\"Polygon\",\"coordinates\":[[[8.8,37.226833],[8.8,43.450166],[15.5,43.450166],[15.5,37.226833],[8.8,37.226833]]]}",
    "state": "active",
    "tags": [
        {
            "name": "Mediterranean"
        },
        {
            "name": "Temperature"
        },
        {
            "name": "Salinity"
        },
        {
            "name": "Dissolved Oxygen"
        },
        {
            "name": "Fluorescence"
        },
        {
            "name": "hydrological data"
        },
        {
            "name": "CTD profiles"
        }
    ],
    "title": [
        "ICHNUSSA 2015"
    ],
    "url": ""
}