{
    "DOI": "http://dx.doi.org/doi:10.15479/AT:ISTA:57",
    "DiscHierarchy": [],
    "Discipline": "Not stated",
    "Format": [
        "archive"
    ],
    "MetaDataAccess": "http://datarep.app.ist.ac.at/cgi/oai2?verb=GetRecord&metadataPrefix=oai_dc&identifier=oai:datarep.app.ist.ac.at:57",
    "RelatedIdentifier": [
        "https://datarep.app.ist.ac.at/57/"
    ],
    "ResourceType": [
        "Data Collection"
    ],
    "author": [
        "Jug, Florian",
        "Kainmueller, Dagmar",
        "Rother, Carsten",
        "Meyers, Gene"
    ],
    "fulltext": "oai:datarep.app.ist.ac.at:57;2017-02-24T11:56:57Z;Graph matching problems for annotating C. Elegans;Kainmueller, Dagmar;Jug, Florian;Rother, Carsten;Meyers, Gene;000 Computer science, knowledge & systems;Graph matching problems as described in \"Active Graph Matching for Automatic Joint Segmentation and Annotation of C. Elegans.\" by Kainmueller, Dagmar and Jug, Florian and Rother, Carsten and Myers, Gene, MICCAI 2014. Problems are in OpenGM2 hdf5 format (see http://hciweb2.iwr.uni-heidelberg.de/opengm/) and a custom text format used by the feature matching solver described in \"Feature Correspondence via Graph Matching: Models and Global Optimization.\" by Lorenzo Torresani, Vladimir Kolmogorov and Carsten Rother, ECCV 2008, code at http://pub.ist.ac.at/~vnk/software/GraphMatching-v1.02.src.zip. ;Data Collection;NonPeerReviewed;archive;https://datarep.app.ist.ac.at/57/;https://datarep.app.ist.ac.at/57/1/wormMatchingProblems.zip;  Kainmueller, Dagmar and Jug, Florian and Rother, Carsten and Meyers, Gene   Graph matching problems for annotating C. Elegans.  [Data Collection]     ;10.15479/AT:ISTA:57",
    "group": "ist",
    "groups": [
        {
            "name": "ist"
        }
    ],
    "name": "00afc6ee-df51-5f89-b3d7-ad07745aad90",
    "notes": [
        "Graph matching problems as described in \"Active Graph Matching for Automatic Joint Segmentation and Annotation of C. Elegans.\" by Kainmueller, Dagmar and Jug, Florian and Rother, Carsten and Myers, Gene, MICCAI 2014. Problems are in OpenGM2 hdf5 format (see http://hciweb2.iwr.uni-heidelberg.de/opengm/) and a custom text format used by the feature matching solver described in \"Feature Correspondence via Graph Matching: Models and Global Optimization.\" by Lorenzo Torresani, Vladimir Kolmogorov and Carsten Rother, ECCV 2008, code at http://pub.ist.ac.at/~vnk/software/GraphMatching-v1.02.src.zip. "
    ],
    "oai_identifier": [
        "oai:datarep.app.ist.ac.at:57"
    ],
    "oai_set": "",
    "state": "active",
    "tags": [
        {
            "name": "Computer science"
        },
        {
            "name": "knowledge"
        },
        {
            "name": "systems"
        }
    ],
    "title": [
        "Graph matching problems for annotating C. Elegans"
    ],
    "url": "https://datarep.app.ist.ac.at/57/1/wormMatchingProblems.zip"
}