{
    "DOI": "http://dx.doi.org/doi:10.15479/AT:ISTA:28",
    "DiscHierarchy": [],
    "Discipline": "Not stated",
    "Format": [
        "archive"
    ],
    "MetaDataAccess": "http://datarep.app.ist.ac.at/cgi/oai2?verb=GetRecord&metadataPrefix=oai_dc&identifier=oai:datarep.app.ist.ac.at:28",
    "RelatedIdentifier": [
        "https://datarep.app.ist.ac.at/28/"
    ],
    "ResourceType": [
        "Data Collection"
    ],
    "author": [
        "Fellner, Andreas"
    ],
    "fulltext": "oai:datarep.app.ist.ac.at:28;2016-02-19T08:57:23Z;Experimental part of CAV 2015 publication: Counterexample Explanation by Learning Small Strategies in Markov Decision Processes;Fellner, Andreas;004 Data processing & computer science;005 Computer programming, programs & data;This repository contains the experimental part of the CAV 2015 publication Counterexample Explanation by Learning Small Strategies in Markov Decision Processes.\r\nWe extended the probabilistic model checker PRISM to represent strategies of Markov Decision Processes as Decision Trees.\r\nThe archive contains a java executable version of the extended tool (prism_dectree.jar) together with a few examples of the PRISM benchmark library.\r\nTo execute the program, please have a look at the README.txt, which provides instructions and further information on the archive.\r\nThe archive contains scripts that (if run often enough) reproduces the data presented in the publication.;Data Collection;NonPeerReviewed;archive;https://datarep.app.ist.ac.at/28/;https://datarep.app.ist.ac.at/28/2/Fellner_DataRep.zip;  Fellner, Andreas   Experimental part of CAV 2015 publication: Counterexample Explanation by Learning Small Strategies in Markov Decision Processes.  [Data Collection]     ;10.15479/AT:ISTA:28",
    "group": "ist",
    "groups": [
        {
            "name": "ist"
        }
    ],
    "name": "1d6cc71b-82e0-57b4-adf3-8be1fd26bb37",
    "notes": [
        "This repository contains the experimental part of the CAV 2015 publication Counterexample Explanation by Learning Small Strategies in Markov Decision Processes.\r\nWe extended the probabilistic model checker PRISM to represent strategies of Markov Decision Processes as Decision Trees.\r\nThe archive contains a java executable version of the extended tool (prism_dectree.jar) together with a few examples of the PRISM benchmark library.\r\nTo execute the program, please have a look at the README.txt, which provides instructions and further information on the archive.\r\nThe archive contains scripts that (if run often enough) reproduces the data presented in the publication."
    ],
    "oai_identifier": [
        "oai:datarep.app.ist.ac.at:28"
    ],
    "oai_set": "",
    "state": "active",
    "tags": [
        {
            "name": "Data processing"
        },
        {
            "name": "computer science"
        },
        {
            "name": "Computer programming"
        },
        {
            "name": "programs"
        },
        {
            "name": "data"
        }
    ],
    "title": [
        "Experimental part of CAV 2015 publication: Counterexample Explanation by Learning Small Strategies in Markov Decision Processes"
    ],
    "url": "https://datarep.app.ist.ac.at/28/2/Fellner_DataRep.zip"
}