{
    "DOI": "http://dx.doi.org/doi:10.15479/AT:ISTA:36 ",
    "DiscHierarchy": [],
    "Discipline": "Not stated",
    "Format": [
        "archive"
    ],
    "MetaDataAccess": "http://datarep.app.ist.ac.at/cgi/oai2?verb=GetRecord&metadataPrefix=oai_dc&identifier=oai:datarep.app.ist.ac.at:36",
    "RelatedIdentifier": [
        "https://datarep.app.ist.ac.at/36/"
    ],
    "ResourceType": [
        "Data Collection"
    ],
    "author": [
        "Ellis, Thomas"
    ],
    "fulltext": "oai:datarep.app.ist.ac.at:36;2017-03-30T14:27:36Z;Pollinator visitation data for wild Antirrhinum majus plants, with phenotypic and frequency data.;Ellis, Thomas;576 Genetics and evolution;577 Ecology;Data on pollinator visitation to wild snapdragons in a natural hybrid zone, collected as part of Tom Ellis' PhD thesis (submitted February 2016).\r\n\r\nSnapdragon flowers have a mouth-like structure which pollinators must open to access nectar. We placed 5mm cellophane tags in these mouths, which are held in place by the pressure of the flower until a pollinator visits. When she opens the flower, the tag drops out, and one can infer a visit. We surveyed plants over multiple days in 2010, 2011 and 2012.\r\n\r\nAlso included are data on phenotypic and demographic variables which may be explanatory variables for pollinator visitation.;Data Collection;NonPeerReviewed;archive;https://datarep.app.ist.ac.at/36/;https://datarep.app.ist.ac.at/36/1/tag_assay_archive.zip;  Ellis, Thomas   Pollinator visitation data for wild Antirrhinum majus plants, with phenotypic and frequency data.  [Data Collection]     ;10.15479/AT:ISTA:36 ",
    "group": "ist",
    "groups": [
        {
            "name": "ist"
        }
    ],
    "name": "2b61e7c6-0a83-567b-b8ac-880bfe7ef013",
    "notes": [
        "Data on pollinator visitation to wild snapdragons in a natural hybrid zone, collected as part of Tom Ellis' PhD thesis (submitted February 2016).\r\n\r\nSnapdragon flowers have a mouth-like structure which pollinators must open to access nectar. We placed 5mm cellophane tags in these mouths, which are held in place by the pressure of the flower until a pollinator visits. When she opens the flower, the tag drops out, and one can infer a visit. We surveyed plants over multiple days in 2010, 2011 and 2012.\r\n\r\nAlso included are data on phenotypic and demographic variables which may be explanatory variables for pollinator visitation."
    ],
    "oai_identifier": [
        "oai:datarep.app.ist.ac.at:36"
    ],
    "oai_set": "",
    "state": "active",
    "tags": [
        {
            "name": "Genetics evolution"
        },
        {
            "name": "Ecology"
        }
    ],
    "title": [
        "Pollinator visitation data for wild Antirrhinum majus plants, with phenotypic and frequency data."
    ],
    "url": "https://datarep.app.ist.ac.at/36/1/tag_assay_archive.zip"
}