{
    "DOI": "http://dx.doi.org/doi:10.15479/AT:ISTA:37 ",
    "DiscHierarchy": [],
    "Discipline": "Not stated",
    "Format": [
        "archive"
    ],
    "MetaDataAccess": "http://datarep.app.ist.ac.at/cgi/oai2?verb=GetRecord&metadataPrefix=oai_dc&identifier=oai:datarep.app.ist.ac.at:37",
    "RelatedIdentifier": [
        "https://datarep.app.ist.ac.at/37/"
    ],
    "ResourceType": [
        "Data Collection"
    ],
    "author": [
        "Ellis, Thomas",
        "Field, David"
    ],
    "fulltext": "oai:datarep.app.ist.ac.at:37;2017-03-30T14:27:55Z;\tInference of mating patterns among wild snapdragons in a natural hybrid zone in 2012.;Field, David;Ellis, Thomas;576 Genetics and evolution;577 Ecology;Genotypic, phenotypic and demographic data for 2128 wild snapdragons and 1127 open-pollinated progeny from a natural hybrid zone, collected as part of Tom Ellis' PhD thesis (submitted) February 2016).\r\n\r\nTissue samples were sent to LGC Genomics in Berlin for DNA extraction, and genotyping at 70 SNP markers by KASPR genotyping. 29 of these SNPs failed to amplify reliably, and have been removed from this dataset.\r\n\r\nOther data were retreived from an online database of this population at www.antspec.org.;Data Collection;NonPeerReviewed;archive;https://datarep.app.ist.ac.at/37/;https://datarep.app.ist.ac.at/37/1/paternity_archive.zip;  Field, David and Ellis, Thomas    Inference of mating patterns among wild snapdragons in a natural hybrid zone in 2012.  [Data Collection]     ;10.15479/AT:ISTA:37 ",
    "group": "ist",
    "groups": [
        {
            "name": "ist"
        }
    ],
    "name": "6cac1636-dc33-5b7d-a4ba-e28edb7ab8fb",
    "notes": [
        "Genotypic, phenotypic and demographic data for 2128 wild snapdragons and 1127 open-pollinated progeny from a natural hybrid zone, collected as part of Tom Ellis' PhD thesis (submitted) February 2016).\r\n\r\nTissue samples were sent to LGC Genomics in Berlin for DNA extraction, and genotyping at 70 SNP markers by KASPR genotyping. 29 of these SNPs failed to amplify reliably, and have been removed from this dataset.\r\n\r\nOther data were retreived from an online database of this population at www.antspec.org."
    ],
    "oai_identifier": [
        "oai:datarep.app.ist.ac.at:37"
    ],
    "oai_set": "",
    "state": "active",
    "tags": [
        {
            "name": "Genetics evolution"
        },
        {
            "name": "Ecology"
        }
    ],
    "title": [
        "\tInference of mating patterns among wild snapdragons in a natural hybrid zone in 2012."
    ],
    "url": "https://datarep.app.ist.ac.at/37/1/paternity_archive.zip"
}