{
    "DOI": "http://dx.doi.org/doi:10.15479/AT:ISTA:64",
    "DiscHierarchy": [],
    "Discipline": "Not stated",
    "Format": [
        "archive"
    ],
    "MetaDataAccess": "http://datarep.app.ist.ac.at/cgi/oai2?verb=GetRecord&metadataPrefix=oai_dc&identifier=oai:datarep.app.ist.ac.at:64",
    "RelatedIdentifier": [
        "https://datarep.app.ist.ac.at/64/"
    ],
    "ResourceType": [
        "Data Collection"
    ],
    "author": [
        "Lukacisin, Martin"
    ],
    "fulltext": "oai:datarep.app.ist.ac.at:64;2017-03-20T08:07:13Z;MATLAB analysis code for 'Sequence-Specific Thermodynamic Properties of Nucleic Acids Influence Both Transcriptional Pausing and Backtracking in Yeast';Lukacisin, Martin;571 Physiology;579 Microorganisms, fungi, algae;MATLAB code and processed datasets available for reproducing the results in: \r\nLuka\u010di\u0161in, M.*, Landon, M.*, Jajoo, R*. (2016) Sequence-Specific Thermodynamic Properties of Nucleic Acids Influence Both Transcriptional Pausing and Backtracking in Yeast.\r\n*equal contributions;Data Collection;NonPeerReviewed;archive;https://datarep.app.ist.ac.at/64/;https://datarep.app.ist.ac.at/64/1/PaperCode.zip;  Lukacisin, Martin   MATLAB analysis code for 'Sequence-Specific Thermodynamic Properties of Nucleic Acids Influence Both Transcriptional Pausing and Backtracking in Yeast'.  [Data Collection]     ;10.15479/AT:ISTA:64",
    "group": "ist",
    "groups": [
        {
            "name": "ist"
        }
    ],
    "name": "90168a14-9bde-5002-9a16-9b88681bd82a",
    "notes": [
        "MATLAB code and processed datasets available for reproducing the results in: \r\nLuka\u010di\u0161in, M.*, Landon, M.*, Jajoo, R*. (2016) Sequence-Specific Thermodynamic Properties of Nucleic Acids Influence Both Transcriptional Pausing and Backtracking in Yeast.\r\n*equal contributions"
    ],
    "oai_identifier": [
        "oai:datarep.app.ist.ac.at:64"
    ],
    "oai_set": "",
    "state": "active",
    "tags": [
        {
            "name": "Physiology"
        },
        {
            "name": "Microorganisms"
        },
        {
            "name": "fungi"
        },
        {
            "name": "algae"
        }
    ],
    "title": [
        "MATLAB analysis code for 'Sequence-Specific Thermodynamic Properties of Nucleic Acids Influence Both Transcriptional Pausing and Backtracking in Yeast'"
    ],
    "url": "https://datarep.app.ist.ac.at/64/1/PaperCode.zip"
}