{
    "DOI": "http://dx.doi.org/doi:10.15479/AT:ISTA:62",
    "DiscHierarchy": [],
    "Discipline": "Not stated",
    "Format": [
        "archive"
    ],
    "MetaDataAccess": "http://datarep.app.ist.ac.at/cgi/oai2?verb=GetRecord&metadataPrefix=oai_dc&identifier=oai:datarep.app.ist.ac.at:111",
    "RelatedIdentifier": [
        "https://datarep.app.ist.ac.at/111/"
    ],
    "ResourceType": [
        "Data Collection"
    ],
    "author": [
        "Tkacik, Gasper",
        "De Martino, Daniele"
    ],
    "fulltext": "oai:datarep.app.ist.ac.at:111;2018-09-21T14:11:04Z;Supporting materials \"STATISTICAL MECHANICS FOR METABOLIC NETWORKS IN STEADY-STATE GROWTH\";De Martino, Daniele;Tkacik, Gasper;530 Physics;570 Life sciences; biology;Supporting material to the article \r\nSTATISTICAL MECHANICS FOR METABOLIC NETWORKS IN STEADY-STATE GROWTH\r\n\r\n\r\nboundscoli.dat\r\nFlux Bounds of the E. coli catabolic core model iAF1260 in a glucose limited minimal medium. \r\n\r\n\r\npolcoli.dat\r\nMatrix enconding the polytope of the E. coli catabolic core model iAF1260 in a glucose limited minimal medium, \r\nobtained from the soichiometric matrix by standard linear algebra  (reduced row echelon form).\r\n\r\nellis.dat\r\nApproximate Lowner-John ellipsoid rounding the polytope of the E. coli catabolic core model iAF1260 in a glucose limited minimal medium\r\nobtained with the Lovasz method.\r\n\r\npoint0.dat\r\nCenter of the approximate Lowner-John ellipsoid rounding the polytope of the E. coli catabolic core model iAF1260 in a glucose limited minimal medium\r\nobtained with the Lovasz method.\r\n\r\n\r\n\r\nlovasz.cpp  \r\nThis c++ code file receives in input the polytope of the feasible steady states of a metabolic network, \r\n(matrix and bounds), and it gives in output an approximate Lowner-John ellipsoid rounding the polytope\r\nwith the Lovasz method \r\nNB inputs are referred by defaults to the catabolic core of the E.Coli network iAF1260. \r\nFor further details we refer to  PLoS ONE 10.4 e0122670 (2015).\r\n\r\nsampleHRnew.cpp  \r\nThis c++ code file receives in input the polytope of the feasible steady states of a metabolic network, \r\n(matrix and bounds), the ellipsoid rounding the polytope, a point inside and  \r\nit gives in output a max entropy sampling at fixed average growth rate \r\nof the steady states by performing an Hit-and-Run Monte Carlo Markov chain.\r\nNB inputs are referred by defaults to the catabolic core of the E.Coli network iAF1260. \r\nFor further details we refer to  PLoS ONE 10.4 e0122670 (2015).;Data Collection;NonPeerReviewed;archive;https://datarep.app.ist.ac.at/111/;https://datarep.app.ist.ac.at/111/1/CODES.zip;  De Martino, Daniele and Tkacik, Gasper   Supporting materials \"STATISTICAL MECHANICS FOR METABOLIC NETWORKS IN STEADY-STATE GROWTH\".  [Data Collection]     ;10.15479/AT:ISTA:62",
    "group": "ist",
    "groups": [
        {
            "name": "ist"
        }
    ],
    "name": "9083b50e-6fea-528a-9931-54ad36d88a4d",
    "notes": [
        "Supporting material to the article \r\nSTATISTICAL MECHANICS FOR METABOLIC NETWORKS IN STEADY-STATE GROWTH\r\n\r\n\r\nboundscoli.dat\r\nFlux Bounds of the E. coli catabolic core model iAF1260 in a glucose limited minimal medium. \r\n\r\n\r\npolcoli.dat\r\nMatrix enconding the polytope of the E. coli catabolic core model iAF1260 in a glucose limited minimal medium, \r\nobtained from the soichiometric matrix by standard linear algebra  (reduced row echelon form).\r\n\r\nellis.dat\r\nApproximate Lowner-John ellipsoid rounding the polytope of the E. coli catabolic core model iAF1260 in a glucose limited minimal medium\r\nobtained with the Lovasz method.\r\n\r\npoint0.dat\r\nCenter of the approximate Lowner-John ellipsoid rounding the polytope of the E. coli catabolic core model iAF1260 in a glucose limited minimal medium\r\nobtained with the Lovasz method.\r\n\r\n\r\n\r\nlovasz.cpp  \r\nThis c++ code file receives in input the polytope of the feasible steady states of a metabolic network, \r\n(matrix and bounds), and it gives in output an approximate Lowner-John ellipsoid rounding the polytope\r\nwith the Lovasz method \r\nNB inputs are referred by defaults to the catabolic core of the E.Coli network iAF1260. \r\nFor further details we refer to  PLoS ONE 10.4 e0122670 (2015).\r\n\r\nsampleHRnew.cpp  \r\nThis c++ code file receives in input the polytope of the feasible steady states of a metabolic network, \r\n(matrix and bounds), the ellipsoid rounding the polytope, a point inside and  \r\nit gives in output a max entropy sampling at fixed average growth rate \r\nof the steady states by performing an Hit-and-Run Monte Carlo Markov chain.\r\nNB inputs are referred by defaults to the catabolic core of the E.Coli network iAF1260. \r\nFor further details we refer to  PLoS ONE 10.4 e0122670 (2015)."
    ],
    "oai_identifier": [
        "oai:datarep.app.ist.ac.at:111"
    ],
    "oai_set": "",
    "state": "active",
    "tags": [
        {
            "name": "Physics"
        },
        {
            "name": "Life sciences"
        },
        {
            "name": "biology"
        }
    ],
    "title": [
        "Supporting materials \"STATISTICAL MECHANICS FOR METABOLIC NETWORKS IN STEADY-STATE GROWTH\""
    ],
    "url": "https://datarep.app.ist.ac.at/111/1/CODES.zip"
}