{
    "DOI": "http://dx.doi.org/doi:10.15479/AT:ISTA:109",
    "DiscHierarchy": [],
    "Discipline": "Not stated",
    "Format": [
        "archive"
    ],
    "MetaDataAccess": "http://datarep.app.ist.ac.at/cgi/oai2?verb=GetRecord&metadataPrefix=oai_dc&identifier=oai:datarep.app.ist.ac.at:109",
    "RelatedIdentifier": [
        "https://datarep.app.ist.ac.at/109/"
    ],
    "ResourceType": [
        "Data Collection"
    ],
    "author": [
        "Vicoso, Beatriz"
    ],
    "fulltext": "oai:datarep.app.ist.ac.at:109;2018-07-24T11:51:46Z;Input files and scripts from \"Evolution of gene dosage on the Z-chromosome of schistosome parasites\" by Picard M.A.L., et al (2018);Vicoso, Beatriz;570 Life sciences; biology;576 Genetics and evolution;Input files and scripts from \"Evolution of gene dosage on the Z-chromosome of schistosome parasites\" by Picard M.A.L., et al (2018).;Data Collection;NonPeerReviewed;archive;https://datarep.app.ist.ac.at/109/;https://datarep.app.ist.ac.at/109/1/SupplementaryMethods.zip;  Vicoso, Beatriz   Input files and scripts from \"Evolution of gene dosage on the Z-chromosome of schistosome parasites\" by Picard M.A.L., et al (2018).  [Data Collection]    (In Press)  ;10.15479/AT:ISTA:109",
    "group": "ist",
    "groups": [
        {
            "name": "ist"
        }
    ],
    "name": "e29fe838-ea0a-534c-b9a7-7dd2972ba57e",
    "notes": [
        "Input files and scripts from \"Evolution of gene dosage on the Z-chromosome of schistosome parasites\" by Picard M.A.L., et al (2018)."
    ],
    "oai_identifier": [
        "oai:datarep.app.ist.ac.at:109"
    ],
    "oai_set": "",
    "state": "active",
    "tags": [
        {
            "name": "Life sciences"
        },
        {
            "name": "biology"
        },
        {
            "name": "Genetics evolution"
        }
    ],
    "title": [
        "Input files and scripts from \"Evolution of gene dosage on the Z-chromosome of schistosome parasites\" by Picard M.A.L., et al (2018)"
    ],
    "url": "https://datarep.app.ist.ac.at/109/1/SupplementaryMethods.zip"
}