{
    "DOI": "http://dx.doi.org/doi:10.15479/AT:ISTA:35 ",
    "DiscHierarchy": [],
    "Discipline": "Not stated",
    "Format": [
        "archive"
    ],
    "MetaDataAccess": "http://datarep.app.ist.ac.at/cgi/oai2?verb=GetRecord&metadataPrefix=oai_dc&identifier=oai:datarep.app.ist.ac.at:35",
    "RelatedIdentifier": [
        "https://datarep.app.ist.ac.at/35/"
    ],
    "ResourceType": [
        "Data Collection"
    ],
    "author": [
        "Ellis, Thomas"
    ],
    "fulltext": "oai:datarep.app.ist.ac.at:35;2017-03-30T14:27:13Z;Data on pollinator observations and offpsring phenotypes;Ellis, Thomas;576 Genetics and evolution;577 Ecology;Data from array experiments investigating pollinator behaviour on snapdragons in controlled conditions, and their effect on plant mating. Data were collected as part of Tom Ellis' PhD thesis , submitted February 2016.\r\n\r\nWe placed a total of 36 plants in a grid inside a closed organza tent, with a single hive of commercially bred bumblebees (Bombus hortorum). We used only the yellow-flowered Antirrhinum majus striatum and the magenta-flowered Antirrhinum majus pseudomajus, at ratios of 6:36, 12:24, 18:18, 24:12 and 30:6.\r\n\r\nAfter 24 hours to learn how to deal with snapdragons, I observed pollinators foraging on plants, and recorded the transitions between plants. Thereafter seeds on plants were allowed to develops. A sample of these were grown to maturity when their flower colour could be determined, and they were scored as yellow, magenta, or hybrid.;Data Collection;NonPeerReviewed;archive;https://datarep.app.ist.ac.at/35/;https://datarep.app.ist.ac.at/35/1/array_data.zip;  Ellis, Thomas   Data on pollinator observations and offpsring phenotypes.  [Data Collection]     ;10.15479/AT:ISTA:35 ",
    "group": "ist",
    "groups": [
        {
            "name": "ist"
        }
    ],
    "name": "fa1bb827-bd71-569c-8db8-070bc8b64ddd",
    "notes": [
        "Data from array experiments investigating pollinator behaviour on snapdragons in controlled conditions, and their effect on plant mating. Data were collected as part of Tom Ellis' PhD thesis , submitted February 2016.\r\n\r\nWe placed a total of 36 plants in a grid inside a closed organza tent, with a single hive of commercially bred bumblebees (Bombus hortorum). We used only the yellow-flowered Antirrhinum majus striatum and the magenta-flowered Antirrhinum majus pseudomajus, at ratios of 6:36, 12:24, 18:18, 24:12 and 30:6.\r\n\r\nAfter 24 hours to learn how to deal with snapdragons, I observed pollinators foraging on plants, and recorded the transitions between plants. Thereafter seeds on plants were allowed to develops. A sample of these were grown to maturity when their flower colour could be determined, and they were scored as yellow, magenta, or hybrid."
    ],
    "oai_identifier": [
        "oai:datarep.app.ist.ac.at:35"
    ],
    "oai_set": "",
    "state": "active",
    "tags": [
        {
            "name": "Genetics evolution"
        },
        {
            "name": "Ecology"
        }
    ],
    "title": [
        "Data on pollinator observations and offpsring phenotypes"
    ],
    "url": "https://datarep.app.ist.ac.at/35/1/array_data.zip"
}