{
    "Contact": [
        "University of Bergen"
    ],
    "DiscHierarchy": [
        "1.4",
        "Humanities",
        "Linguistics"
    ],
    "Discipline": "Linguistics",
    "Format": [
        "application/zip",
        "downloadable_files_count: 1",
        "text/plain; charset=utf-8"
    ],
    "Language": [
        "Wolof"
    ],
    "MetaDataAccess": "https://clarin-pl.eu/oai/request?verb=GetRecord&metadataPrefix=oai_dc&identifier=oai:repo.clarino.uib.no:11509/112",
    "MetadataAccess": [
        "oai:repo.clarino.uib.no:11509/112"
    ],
    "PID": "http://hdl.handle.net/11509/112",
    "PublicationTimestamp": "2014-09-20T11:59:59Z",
    "PublicationYear": [
        "2014"
    ],
    "Publisher": [
        "University of Bergen"
    ],
    "ResourceType": [
        "LanguageDescription"
    ],
    "Rights": [
        "Creative Commons - Attribution 3.0 Unported (CC BY 3.0)",
        "http://creativecommons.org/licenses/by/3.0/",
        "CC"
    ],
    "author": [
        "Dione, Cheikh M. Bamba"
    ],
    "fulltext": "oai:repo.clarino.uib.no:11509/112;2016-04-15T05:59:21Z;hdl_11509_1;hdl_11509_2;Wolof Morphological Analyzer;Dione, Cheikh M. Bamba;Wolof;Morphology;Analyzer;Finite-State;Fst;Tool;Finite-State Fst Tool;This README describes a finite-state based morphological analyzer of Wolof.\r\nThe analyzer was developed and tested on natural language data extracted from Wolof text books. \r\nThese include Ciss\u00e9, M. (1994). Contes wolof modernes. L\u2019harmattan;\r\nand Ba, M. (2007). Bataaxal bu gudde nii. Nouvelles Editions Africaines du S\u00e9n\u00e9gal (NEAS). \r\nAs of September 2014, the tool shows a high coverage (more than 90%) on unseen data.\r\n\r\nSee: Cheikh M. Bamba Dione: A Morphological Analyzer For Wolof Using Finite-State Techniques. In: Proceedings of the Eighth International Conference on Language Resources and Evaluation. Eds. Nicoletta Calzolari et al. European Language Resources Association 2012. ISBN 978-2-9517408-7-7.\r\n\r\nPlease make reference to the above mentioned paper when publishing research based on this analyzer.;2014-09-20;LanguageDescription;http://hdl.handle.net/11509/112;wol;Creative Commons - Attribution 3.0 Unported (CC BY 3.0);http://creativecommons.org/licenses/by/3.0/;CC;application/zip;text/plain; charset=utf-8;downloadable_files_count: 1;University of Bergen",
    "group": "clarin",
    "groups": [
        {
            "name": "clarin"
        }
    ],
    "name": "076ac53d-1074-5707-bd2c-62e7a641a527",
    "notes": [
        "This README describes a finite-state based morphological analyzer of Wolof.\r\nThe analyzer was developed and tested on natural language data extracted from Wolof text books. \r\nThese include Ciss\u00e9, M. (1994). Contes wolof modernes. L\u2019harmattan;\r\nand Ba, M. (2007). Bataaxal bu gudde nii. Nouvelles Editions Africaines du S\u00e9n\u00e9gal (NEAS). \r\nAs of September 2014, the tool shows a high coverage (more than 90%) on unseen data.\r\n\r\nSee: Cheikh M. Bamba Dione: A Morphological Analyzer For Wolof Using Finite-State Techniques. In: Proceedings of the Eighth International Conference on Language Resources and Evaluation. Eds. Nicoletta Calzolari et al. European Language Resources Association 2012. ISBN 978-2-9517408-7-7.\r\n\r\nPlease make reference to the above mentioned paper when publishing research based on this analyzer."
    ],
    "oai_identifier": [
        "oai:repo.clarino.uib.no:11509/112"
    ],
    "oai_set": [
        "hdl_11509_1",
        "hdl_11509_2"
    ],
    "state": "active",
    "tags": [
        {
            "name": "Wolof"
        },
        {
            "name": "Morphology"
        },
        {
            "name": "Analyzer"
        },
        {
            "name": "Finite-State"
        },
        {
            "name": "Fst"
        },
        {
            "name": "Tool"
        },
        {
            "name": "Finite-State Fst Tool"
        }
    ],
    "title": [
        "Wolof Morphological Analyzer"
    ],
    "url": ""
}