{
    "Contact": [
        "Istituto di Linguistica Computazionale \u201cA. Zampolli\u201d - Consiglio Nazionale delle Ricerche (ILC-CNR)"
    ],
    "DiscHierarchy": [
        "1.4",
        "Humanities",
        "Linguistics"
    ],
    "Discipline": "Linguistics",
    "Format": [
        "downloadable_files_count: 0"
    ],
    "Language": [
        "Italian"
    ],
    "MetaDataAccess": "https://clarin-pl.eu/oai/request?verb=GetRecord&metadataPrefix=oai_dc&identifier=oai:dspace-clarin-it.ilc.cnr.it:20.500.11752/ILC-87",
    "MetadataAccess": [
        "oai:dspace-clarin-it.ilc.cnr.it:20.500.11752/ILC-87"
    ],
    "PID": "http://hdl.handle.net/20.500.11752/ILC-87",
    "PublicationTimestamp": "2017-11-30T11:59:59Z",
    "PublicationYear": [
        "2017"
    ],
    "Publisher": [
        "Istituto di Linguistica Computazionale \u201cA. Zampolli\u201d - Consiglio Nazionale delle Ricerche (ILC-CNR)"
    ],
    "ResourceType": [
        "corpus"
    ],
    "author": [
        "AA. VV., AA. VV."
    ],
    "fulltext": "oai:dspace-clarin-it.ilc.cnr.it:20.500.11752/ILC-87;2018-07-23T09:13:44Z;hdl_000-c0-111_38;hdl_000-c0-111_49;Primo Levi Selected Works;AA. VV., AA. VV.;Nazi extermination camps;Imprisonment;Lager;Drama;This is a collection of some of Primo Levi's works:\r\n  Terza pagina (La stampa) (EINAUDI 1986) \r\n  Storie naturali (EINAUDI 1966) \r\n  Se questo \u00e8 un uomo (EINAUDI 1958) \r\n  Se non ora quando (Vol. II Einaudi 1988 --- da Ediz. EINAUDI 1981) \r\n  Lilit (EINUADI 1981) \r\n  L'altrui mestiere (EINAUDI 1985) \r\n  La tregua (EINAUDI 1981) \r\n  La ricerca delle radici La chiave a stella (Vol. II Einaudi 1988) \r\n  Il sistema periodico (EINAUDI 1975)\r\n  I sommersi e i salvati (Vol. I Einaudi 1987 --- da Ediz. Giulio Einaudi editore S.p.a. Torino Gli struzzi 1986) \r\n  Vizio di forma (Einaudi 1971)\r\n\r\nThis corpus was created in the 1990s.;2017-11-30;corpus;http://hdl.handle.net/20.500.11752/ILC-87;ita;downloadable_files_count: 0;Istituto di Linguistica Computazionale \u201cA. Zampolli\u201d - Consiglio Nazionale delle Ricerche (ILC-CNR)",
    "group": "clarin",
    "groups": [
        {
            "name": "clarin"
        }
    ],
    "name": "1ce053c2-577a-5eb3-91e4-91faa15ac9b8",
    "notes": [
        "This is a collection of some of Primo Levi's works:\r\n  Terza pagina (La stampa) (EINAUDI 1986) \r\n  Storie naturali (EINAUDI 1966) \r\n  Se questo \u00e8 un uomo (EINAUDI 1958) \r\n  Se non ora quando (Vol. II Einaudi 1988 --- da Ediz. EINAUDI 1981) \r\n  Lilit (EINUADI 1981) \r\n  L'altrui mestiere (EINAUDI 1985) \r\n  La tregua (EINAUDI 1981) \r\n  La ricerca delle radici La chiave a stella (Vol. II Einaudi 1988) \r\n  Il sistema periodico (EINAUDI 1975)\r\n  I sommersi e i salvati (Vol. I Einaudi 1987 --- da Ediz. Giulio Einaudi editore S.p.a. Torino Gli struzzi 1986) \r\n  Vizio di forma (Einaudi 1971)\r\n\r\nThis corpus was created in the 1990s."
    ],
    "oai_identifier": [
        "oai:dspace-clarin-it.ilc.cnr.it:20.500.11752/ILC-87"
    ],
    "oai_set": [
        "hdl_000-c0-111_38",
        "hdl_000-c0-111_49"
    ],
    "state": "active",
    "tags": [
        {
            "name": "Nazi extermination camps"
        },
        {
            "name": "Imprisonment"
        },
        {
            "name": "Lager"
        },
        {
            "name": "Drama"
        }
    ],
    "title": [
        "Primo Levi Selected Works"
    ],
    "url": ""
}