{
    "Contact": [
        "Istituto di Linguistica Computazionale \u201cA. Zampolli\u201d - Consiglio Nazionale delle Ricerche (ILC-CNR)"
    ],
    "DiscHierarchy": [
        "1.4",
        "Humanities",
        "Linguistics"
    ],
    "Discipline": "Linguistics",
    "Format": [
        "downloadable_files_count: 0"
    ],
    "Language": [
        "Spanish"
    ],
    "MetaDataAccess": "https://clarin-pl.eu/oai/request?verb=GetRecord&metadataPrefix=oai_dc&identifier=oai:dspace-clarin-it.ilc.cnr.it:20.500.11752/ILC-58",
    "MetadataAccess": [
        "oai:dspace-clarin-it.ilc.cnr.it:20.500.11752/ILC-58"
    ],
    "PID": "http://hdl.handle.net/20.500.11752/ILC-58",
    "PublicationTimestamp": "2016-09-26T11:59:59Z",
    "PublicationYear": [
        "2016"
    ],
    "Publisher": [
        "Istituto di Linguistica Computazionale \u201cA. Zampolli\u201d - Consiglio Nazionale delle Ricerche (ILC-CNR)"
    ],
    "ResourceType": [
        "corpus"
    ],
    "author": [
        "D'\u00c1vila, Teresa di Ges\u00f9"
    ],
    "fulltext": "oai:dspace-clarin-it.ilc.cnr.it:20.500.11752/ILC-58;2018-07-23T09:13:43Z;hdl_000-c0-111_38;hdl_000-c0-111_49;Corpus delle Opere di S.Teresa de \u00c1vila;D'\u00c1vila, Teresa di Ges\u00f9;Fede;Teologia;Religione;Il corpus \u00e8 costituito dalla raccolta delle seguenti opere, fra parentesi la sigla del testo usata nel riferimento: \r\nLIBRO DE LA VIDA (VIDA), \r\nCAMINO DE PERFECCION (CAM), \r\nLAS FUNDACIONES (FUN), \r\nCARTAS (CAR), \r\nEL CASTILLO INTERIOR (MOR), \r\nCONCEPTOS (CONC), \r\nRELACIONES (RELA), \r\nEXCLAMACIONES (EXCL), \r\nCONSTITUCIONES (CONS), \r\nMODO DE VISITAR LOS CONVENTOS (MODO), \r\nPOESIAS (POES), \r\nAPUNTES (APUN).\r\n\r\nL\u2019archivio testuale (con le relative annotazioni linguistiche) \u00e8 stato prodotto negli anni \u201980-'90. Questo progetto di ricerca, promosso dal prof. Guido Mancini con i fondi del 40%-60%, \u00e8 frutto della collaborazione tra l'Universit\u00e0 di Pisa, di Torino con il prof. Ruffinatto e l'ILC-CNR di Pisa. \r\nPer quanto riguarda le fonti, si precisa che nel caso delle Cartas, l'edizione di riferimento si basa sul testo curato da Tom\u00e1s Alvarez e Simeon de la S. Familia, ed. Monte Carmelo, Burgos, 1981; il riferimento al testo viene indicato con il numero della lettera, seguito dal paragrafo e dalla riga. Per le altre opere \u00e8 stato utilizzato il testo curato da Tom\u00e1s de la Cruz, Teresa de Jes\u00fas, Obras Completas, ed. Monte Carmelo, Burgos, 1977. Nel riferimento viene posta la sigla del titolo dell'opera, seguita dall'eventuale numero del capitolo, del paragrafo e della riga all'interno del paragrafo.;2016-09-26;corpus;http://hdl.handle.net/20.500.11752/ILC-58;spa;downloadable_files_count: 0;Istituto di Linguistica Computazionale \u201cA. Zampolli\u201d - Consiglio Nazionale delle Ricerche (ILC-CNR)",
    "group": "clarin",
    "groups": [
        {
            "name": "clarin"
        }
    ],
    "name": "21b94c4b-c542-5707-8198-a316295b75de",
    "notes": [
        "Il corpus \u00e8 costituito dalla raccolta delle seguenti opere, fra parentesi la sigla del testo usata nel riferimento: \r\nLIBRO DE LA VIDA (VIDA), \r\nCAMINO DE PERFECCION (CAM), \r\nLAS FUNDACIONES (FUN), \r\nCARTAS (CAR), \r\nEL CASTILLO INTERIOR (MOR), \r\nCONCEPTOS (CONC), \r\nRELACIONES (RELA), \r\nEXCLAMACIONES (EXCL), \r\nCONSTITUCIONES (CONS), \r\nMODO DE VISITAR LOS CONVENTOS (MODO), \r\nPOESIAS (POES), \r\nAPUNTES (APUN).\r\n\r\nL\u2019archivio testuale (con le relative annotazioni linguistiche) \u00e8 stato prodotto negli anni \u201980-'90. Questo progetto di ricerca, promosso dal prof. Guido Mancini con i fondi del 40%-60%, \u00e8 frutto della collaborazione tra l'Universit\u00e0 di Pisa, di Torino con il prof. Ruffinatto e l'ILC-CNR di Pisa. \r\nPer quanto riguarda le fonti, si precisa che nel caso delle Cartas, l'edizione di riferimento si basa sul testo curato da Tom\u00e1s Alvarez e Simeon de la S. Familia, ed. Monte Carmelo, Burgos, 1981; il riferimento al testo viene indicato con il numero della lettera, seguito dal paragrafo e dalla riga. Per le altre opere \u00e8 stato utilizzato il testo curato da Tom\u00e1s de la Cruz, Teresa de Jes\u00fas, Obras Completas, ed. Monte Carmelo, Burgos, 1977. Nel riferimento viene posta la sigla del titolo dell'opera, seguita dall'eventuale numero del capitolo, del paragrafo e della riga all'interno del paragrafo."
    ],
    "oai_identifier": [
        "oai:dspace-clarin-it.ilc.cnr.it:20.500.11752/ILC-58"
    ],
    "oai_set": [
        "hdl_000-c0-111_38",
        "hdl_000-c0-111_49"
    ],
    "state": "active",
    "tags": [
        {
            "name": "Fede"
        },
        {
            "name": "Teologia"
        },
        {
            "name": "Religione"
        }
    ],
    "title": [
        "Corpus delle Opere di S.Teresa de \u00c1vila"
    ],
    "url": ""
}