{
    "Contact": [
        "CNR Edizioni",
        "Istituto di Linguistica Computazionale \u201cA. Zampolli\u201d - Consiglio Nazionale delle Ricerche (ILC-CNR)"
    ],
    "DiscHierarchy": [
        "1.4",
        "Humanities",
        "Linguistics"
    ],
    "Discipline": "Linguistics",
    "Format": [
        "text/plain; charset=utf-8",
        "downloadable_files_count: 1",
        "application/pdf"
    ],
    "Language": [
        "Italian"
    ],
    "MetaDataAccess": "https://clarin-pl.eu/oai/request?verb=GetRecord&metadataPrefix=oai_dc&identifier=oai:dspace-clarin-it.ilc.cnr.it:20.500.11752/OPEN-89",
    "MetadataAccess": [
        "oai:dspace-clarin-it.ilc.cnr.it:20.500.11752/OPEN-89"
    ],
    "PID": "http://hdl.handle.net/20.500.11752/OPEN-89",
    "PublicationTimestamp": "2018-04-05T11:59:59Z",
    "PublicationYear": [
        "2018"
    ],
    "Publisher": [
        "CNR Edizioni",
        "Istituto di Linguistica Computazionale \u201cA. Zampolli\u201d - Consiglio Nazionale delle Ricerche (ILC-CNR)"
    ],
    "ResourceType": [
        "corpus"
    ],
    "Rights": [
        "Creative Commons - Attribution-NonCommercial 4.0 International (CC BY-NC 4.0)",
        "http://creativecommons.org/licenses/by-nc/4.0/",
        "PUB"
    ],
    "author": [
        "Boschetti, Federico"
    ],
    "fulltext": "oai:dspace-clarin-it.ilc.cnr.it:20.500.11752/OPEN-89;2018-07-23T09:13:44Z;hdl_000-c0-111_39;hdl_000-c0-111_43;Copisti Digitali e Filologi Computazionali;Boschetti, Federico;Filologia collaborativa e cooperativa;Filologia computazionale;Filologia digitale;Filologia classica;Classical philology;Digital philology;Collaborative and cooperative philology;Computational philology;Digital scholarly editing;Il volume \u00e8 formato da dieci capitoli e mette insieme, elaborandoli ed aggiornandoli, materiali\r\ndelle due tesi di dottorato dell\u2019autore, una in Filologia Classica (2005) e l\u2019altra in Linguistica\r\nComputazionale (2010), entrambe discusse presso l\u2019Universit\u00e0 di Trento.\r\nDopo una breve introduzione sul concetto di filologia collaborativa e cooperativa, i primi\r\ncapitoli sono dedicati all\u2019ecdotica digitale, quindi all\u2019acquisizione del testo di edizioni critiche\r\ntramite OCR e al trattamento computazionale di apparati critici e repertori di congetture.\r\nI capitoli seguenti sono dedicati ad aspetti salienti dell\u2019ermeneutica digitale, come l\u2019analisi\r\nsintattica tramite la creazione di treebanks e l\u2019analisi lessico-semantica tramite la creazione di\r\nwordnets e l\u2019esplorazione di word spaces con metodi statistici.\r\nChiudono il volume un capitolo di discussione relativa a punti critici del testo usato come\r\ncaso di studio (I Persiani di Eschilo) e un capitolo di conclusioni e prospettive di ricerca.;2018-04-05;corpus;http://hdl.handle.net/20.500.11752/OPEN-89;ita;Creative Commons - Attribution-NonCommercial 4.0 International (CC BY-NC 4.0);http://creativecommons.org/licenses/by-nc/4.0/;PUB;application/pdf;text/plain; charset=utf-8;downloadable_files_count: 1;CNR Edizioni;Istituto di Linguistica Computazionale \u201cA. Zampolli\u201d - Consiglio Nazionale delle Ricerche (ILC-CNR)",
    "group": "clarin",
    "groups": [
        {
            "name": "clarin"
        }
    ],
    "name": "ae78d630-eab4-54b0-8475-e66f6f212a65",
    "notes": [
        "Il volume \u00e8 formato da dieci capitoli e mette insieme, elaborandoli ed aggiornandoli, materiali\r\ndelle due tesi di dottorato dell\u2019autore, una in Filologia Classica (2005) e l\u2019altra in Linguistica\r\nComputazionale (2010), entrambe discusse presso l\u2019Universit\u00e0 di Trento.\r\nDopo una breve introduzione sul concetto di filologia collaborativa e cooperativa, i primi\r\ncapitoli sono dedicati all\u2019ecdotica digitale, quindi all\u2019acquisizione del testo di edizioni critiche\r\ntramite OCR e al trattamento computazionale di apparati critici e repertori di congetture.\r\nI capitoli seguenti sono dedicati ad aspetti salienti dell\u2019ermeneutica digitale, come l\u2019analisi\r\nsintattica tramite la creazione di treebanks e l\u2019analisi lessico-semantica tramite la creazione di\r\nwordnets e l\u2019esplorazione di word spaces con metodi statistici.\r\nChiudono il volume un capitolo di discussione relativa a punti critici del testo usato come\r\ncaso di studio (I Persiani di Eschilo) e un capitolo di conclusioni e prospettive di ricerca."
    ],
    "oai_identifier": [
        "oai:dspace-clarin-it.ilc.cnr.it:20.500.11752/OPEN-89"
    ],
    "oai_set": [
        "hdl_000-c0-111_39",
        "hdl_000-c0-111_43"
    ],
    "state": "active",
    "tags": [
        {
            "name": "Filologia collaborativa e cooperativa"
        },
        {
            "name": "Filologia computazionale"
        },
        {
            "name": "Filologia digitale"
        },
        {
            "name": "Filologia classica"
        },
        {
            "name": "Classical philology"
        },
        {
            "name": "Digital philology"
        },
        {
            "name": "Collaborative cooperative philology"
        },
        {
            "name": "Computational philology"
        },
        {
            "name": "Digital scholarly editing"
        }
    ],
    "title": [
        "Copisti Digitali e Filologi Computazionali"
    ],
    "url": ""
}