{
    "Contact": [
        "Wolbramczyk Krzysztof"
    ],
    "DiscHierarchy": [
        "1.4",
        "Humanities",
        "Linguistics"
    ],
    "Discipline": "Linguistics",
    "Format": [
        "application/xml"
    ],
    "Language": [
        "Polish"
    ],
    "MetaDataAccess": "https://clarin-pl.eu/oai/request?verb=GetRecord&metadataPrefix=oai_dc&identifier=oai:fedora.clarin-d.uni-saarland.de:clarind-uds:poldilemma-5971",
    "MetadataAccess": [
        "oai:fedora.clarin-d.uni-saarland.de:clarind-uds:poldilemma-5971"
    ],
    "PID": "http://hdl.handle.net/11858/00-246C-0000-0023-8D2B-E",
    "PublicationTimestamp": "1617-07-01T11:59:59Z",
    "PublicationYear": [
        "1617"
    ],
    "Publisher": [
        "Wolbramczyk Krzysztof"
    ],
    "RelatedIdentifier": [
        "http://dlibra.bibliotekaelblaska.pl/Content/5971",
        "oai:dlibra.bibliotekaelblaska.pl:publication:6186"
    ],
    "ResourceType": [
        "starodruk",
        "alter Druck"
    ],
    "Rights": [
        "https://creativecommons.org/licenses/by-nc-sa/4.0/",
        "CC-BY-NC-SA-4.0"
    ],
    "author": [
        "Sixtus Erazm"
    ],
    "fulltext": "oai:fedora.clarin-d.uni-saarland.de:clarind-uds:poldilemma-5971;2019-03-01T15:58:03Z;O cieplicach we Skle Ksi\u0105g Troie. Przez Erazma Syxta Philozophiey y Medicyny Doktora Napisanych...;O cieplicach we Skle Ksi\u0105g Troie. Przez Erazma Syxta Philozophiey y Medicyny Doktora Napisanych...;Sixtus Erazm;Sixtus Erazm;Szk\u0142o, wie\u015b;wody siarczane;Sixtus, Erazm (w\u0142a\u015bc. Mrzyg\u0142\u00f3d) (1570-1635);kurort;wodolecznictwo;Oczko W.;Kurort;Wasserheilkunde;Szk\u0142o, Dorf;Oczko, W.;Schwefelquellen;Sixtus, Erazm (eig. Mrzyg\u0142\u00f3d) (1570-1635);Sixtus Erazm (w\u0142a\u015bc. Mrzyg\u0142\u00f3d) (1570-1635) \u2013 doktor medycyny i filozofii. W swoim dziele opisuje \u017ar\u00f3d\u0142a wody siarczanej we wsi Szk\u0142o niedaleko Lwowa. Autor powo\u0142uje si\u0119 na inne \u017ar\u00f3d\u0142o o tych wodach, a mianowicie na Cieplice W. Oczki. Sixtus E. traktuje zatem swoje dzie\u0142o jako uzupe\u0142nienie do w/w pozycji. Druk wydany w Zamo\u015bciu przez Krzysztofa Wolbramczyka, w formacie 4\u00b0, zawiera piecz\u0119ci Biblioteki Gimnazjum Elbl\u0105skiego i Stadtbibliothek.Oprawa pergaminowa z jappem. W 2010 r. drukpoddano konserwacji zachowawczej w ramach projektu \u201eKonserwacjazachowawcza druk\u00f3w XV-XVII w. Biblioteki Elbl\u0105skiej\u201d.;Sixtus Erasm war Doktor der Medizin und Philosophie. Sein Werk handelt von den Schwefelquellen im Dorf Szk\u0142o bei Lemberg . Der Autor bezieht sich auch auf andere Quellen und n\u00e4mlich auf die Abhandlung von W. Oczko, der auch f\u00fcr die Erforschung der Thermalquellen war. Der Beitrag von Sixtus soll als die Erg\u00e4nzung der Abhandlung von Oczko \u00fcber hei\u00dfe Quellen angesehen werden. Das Druckerzeugnis wurde in Zamo\u015b\u0107 (Zamosch) von Krzysztof Wolbramczyk herausgegeben. Format - 4\u00ba, Siegel der Gymnasialbibliotek und Elbinger Stadtbibliothek. Der Pergamenteinband wurde an den R\u00e4ndern geknickt, um die Blattr\u00e4nder zu sch\u00fctzen.;Wolbramczyk Krzysztof;Wolbramczyk Krzysztof;1617;1617;starodruk;alter Druck;application/xml;clarind-uds:poldilemma-5971;hdl:11858/00-246C-0000-0023-8D2B-E;Pol.7.II.303;Pol. 7. II. 303;pol;http://dlibra.bibliotekaelblaska.pl/Content/5971;oai:dlibra.bibliotekaelblaska.pl:publication:6186;https://creativecommons.org/licenses/by-nc-sa/4.0/;CC-BY-NC-SA-4.0",
    "group": "clarin",
    "groups": [
        {
            "name": "clarin"
        }
    ],
    "name": "d6db95f2-9fe9-592b-9791-754501feb82a",
    "notes": [
        "Sixtus Erazm (w\u0142a\u015bc. Mrzyg\u0142\u00f3d) (1570-1635) \u2013 doktor medycyny i filozofii. W swoim dziele opisuje \u017ar\u00f3d\u0142a wody siarczanej we wsi Szk\u0142o niedaleko Lwowa. Autor powo\u0142uje si\u0119 na inne \u017ar\u00f3d\u0142o o tych wodach, a mianowicie na Cieplice W. Oczki. Sixtus E. traktuje zatem swoje dzie\u0142o jako uzupe\u0142nienie do w/w pozycji. Druk wydany w Zamo\u015bciu przez Krzysztofa Wolbramczyka, w formacie 4\u00b0, zawiera piecz\u0119ci Biblioteki Gimnazjum Elbl\u0105skiego i Stadtbibliothek.Oprawa pergaminowa z jappem. W 2010 r. drukpoddano konserwacji zachowawczej w ramach projektu \u201eKonserwacjazachowawcza druk\u00f3w XV-XVII w. Biblioteki Elbl\u0105skiej\u201d.",
        "Sixtus Erasm war Doktor der Medizin und Philosophie. Sein Werk handelt von den Schwefelquellen im Dorf Szk\u0142o bei Lemberg . Der Autor bezieht sich auch auf andere Quellen und n\u00e4mlich auf die Abhandlung von W. Oczko, der auch f\u00fcr die Erforschung der Thermalquellen war. Der Beitrag von Sixtus soll als die Erg\u00e4nzung der Abhandlung von Oczko \u00fcber hei\u00dfe Quellen angesehen werden. Das Druckerzeugnis wurde in Zamo\u015b\u0107 (Zamosch) von Krzysztof Wolbramczyk herausgegeben. Format - 4\u00ba, Siegel der Gymnasialbibliotek und Elbinger Stadtbibliothek. Der Pergamenteinband wurde an den R\u00e4ndern geknickt, um die Blattr\u00e4nder zu sch\u00fctzen."
    ],
    "oai_identifier": [
        "oai:fedora.clarin-d.uni-saarland.de:clarind-uds:poldilemma-5971"
    ],
    "oai_set": "",
    "state": "active",
    "tags": [
        {
            "name": "Szk\u0142o"
        },
        {
            "name": "wie\u015b"
        },
        {
            "name": "wody siarczane"
        },
        {
            "name": "Sixtus"
        },
        {
            "name": "Erazm w\u0142a\u015bc. Mrzyg\u0142\u00f3d -"
        },
        {
            "name": "kurort"
        },
        {
            "name": "wodolecznictwo"
        },
        {
            "name": "Oczko W."
        },
        {
            "name": "Kurort"
        },
        {
            "name": "Wasserheilkunde"
        },
        {
            "name": "Szk\u0142o"
        },
        {
            "name": "Dorf"
        }
    ],
    "title": [
        "O cieplicach we Skle Ksi\u0105g Troie. Przez Erazma Syxta Philozophiey y Medicyny Doktora Napisanych...",
        "O cieplicach we Skle Ksi\u0105g Troie. Przez Erazma Syxta Philozophiey y Medicyny Doktora Napisanych..."
    ],
    "url": ""
}