{
    "Contact": [
        "Istituto di Linguistica Computazionale \u201cA. Zampolli\u201d - Consiglio Nazionale delle Ricerche (ILC-CNR)"
    ],
    "DiscHierarchy": [
        "1.4",
        "Humanities",
        "Linguistics"
    ],
    "Discipline": "Linguistics",
    "Format": [
        "downloadable_files_count: 0"
    ],
    "Language": [
        "Italian"
    ],
    "MetaDataAccess": "https://clarin-pl.eu/oai/request?verb=GetRecord&metadataPrefix=oai_dc&identifier=oai:dspace-clarin-it.ilc.cnr.it:20.500.11752/ILC-63",
    "MetadataAccess": [
        "oai:dspace-clarin-it.ilc.cnr.it:20.500.11752/ILC-63"
    ],
    "PID": "http://hdl.handle.net/20.500.11752/ILC-63",
    "PublicationTimestamp": "2016-09-21T11:59:59Z",
    "PublicationYear": [
        "2016"
    ],
    "Publisher": [
        "Istituto di Linguistica Computazionale \u201cA. Zampolli\u201d - Consiglio Nazionale delle Ricerche (ILC-CNR)"
    ],
    "ResourceType": [
        "toolService"
    ],
    "author": [
        "Maria Maddalena, Lombardi"
    ],
    "fulltext": "oai:dspace-clarin-it.ilc.cnr.it:20.500.11752/ILC-63;2018-07-23T09:13:44Z;hdl_000-c0-111_38;hdl_000-c0-111_49;Vittorio Alfieri's tragedies;Maria Maddalena, Lombardi;Alfieri Lexicon;Drama;Philosophy;Mythology;Texts of Vittorio Alfieri  were provided partly by the Accademia della Crusca and partly of the University of Pavia, Department of Science and Literature of Medieval and Modern Art. The tragedies listed below refer to the edition edited by Giovanna Zuradelli, Torino, UTET, 1978:\r\nAgamennone\r\nAntigone\r\nLa Congiura de' pazzi\r\nMerope\r\nMaria Stuarda\r\nOreste\r\nPolinice\r\nVirginia\r\nFilippo\r\nAgide \r\nBruto I\r\nBruto II\r\nDon Garzia\r\nMirra\r\nOttavia\r\nRosmunda\r\nSaul\r\nSofonisba\r\nTimoleone;2016-09-21;toolService;http://hdl.handle.net/20.500.11752/ILC-63;ita;downloadable_files_count: 0;Istituto di Linguistica Computazionale \u201cA. Zampolli\u201d - Consiglio Nazionale delle Ricerche (ILC-CNR)",
    "group": "clarin",
    "groups": [
        {
            "name": "clarin"
        }
    ],
    "name": "f12dfb52-3ada-5857-9462-b96f62d171da",
    "notes": [
        "Texts of Vittorio Alfieri  were provided partly by the Accademia della Crusca and partly of the University of Pavia, Department of Science and Literature of Medieval and Modern Art. The tragedies listed below refer to the edition edited by Giovanna Zuradelli, Torino, UTET, 1978:\r\nAgamennone\r\nAntigone\r\nLa Congiura de' pazzi\r\nMerope\r\nMaria Stuarda\r\nOreste\r\nPolinice\r\nVirginia\r\nFilippo\r\nAgide \r\nBruto I\r\nBruto II\r\nDon Garzia\r\nMirra\r\nOttavia\r\nRosmunda\r\nSaul\r\nSofonisba\r\nTimoleone"
    ],
    "oai_identifier": [
        "oai:dspace-clarin-it.ilc.cnr.it:20.500.11752/ILC-63"
    ],
    "oai_set": [
        "hdl_000-c0-111_38",
        "hdl_000-c0-111_49"
    ],
    "state": "active",
    "tags": [
        {
            "name": "Alfieri Lexicon"
        },
        {
            "name": "Drama"
        },
        {
            "name": "Philosophy"
        },
        {
            "name": "Mythology"
        }
    ],
    "title": [
        "Vittorio Alfieri's tragedies"
    ],
    "url": ""
}