{
    "Contact": [
        "researchdatarepository@ucl.ac.uk"
    ],
    "DOI": "http://dx.doi.org/doi:10.5522/04/8851658.v2",
    "DiscHierarchy": [],
    "Discipline": "Not stated",
    "Language": [
        "English"
    ],
    "MetaDataAccess": "https://api.figshare.com/v2/oai?verb=GetRecord&metadataPrefix=oai_dc&identifier=oai:figshare.com:article/8851658",
    "MetadataAccess": [
        "oai:figshare.com:article/8851658"
    ],
    "OpenAccess": "true",
    "PublicationTimestamp": "2019-07-10T14:43:03Z",
    "PublicationYear": [
        "2019"
    ],
    "Publisher": [
        "UCL"
    ],
    "RelatedIdentifier": [
        "https://figshare.com/articles/SynthCity_Dataset_-_Complete/8851658"
    ],
    "ResourceType": [
        "Dataset",
        "Dataset"
    ],
    "Rights": [
        "CC BY 4.0"
    ],
    "author": [
        "David Griffiths (6925508)",
        "Jan Boehm (6782060)"
    ],
    "fulltext": "oai:figshare.com:article/8851658;2019-07-10T14:43:03Z;category_179;portal_549;item_type_3;month_year_07_2019;SynthCity Dataset - Complete;David Griffiths (6925508);Jan Boehm (6782060);Artificial Intelligence and Image Processing;lidar;point cloud;dataset;synthetic;With deep learning becoming a more prominent approach for automatic classification of three-dimensional point cloud data, a key bottleneck is the amount of high quality training data, especially when compared to that available for two-dimensional images. One potential solution is the use of synthetic data for pre-training networks, however the ability for models to generalise from synthetic data to real world data has been poorly studied for point clouds. Despite this, a huge wealth of 3D virtual environments exist, which if proved effective can be exploited. We therefore argue that research in this domain would be hugely useful. In this paper we present SynthCity an open dataset to help aid research. SynthCity is a 367.9M point synthetic full colour Mobile Laser Scanning point cloud. Every point is labelled from one of nine categories. We generate our point cloud in a typical Urban/Suburban environment using the Blensor plugin for Blender. See our project website http://www.synthcity.xyz or paper https://arxiv.org/abs/1907.04758 for more information.;2019-07-10T14:43:03Z;Dataset;Dataset;10.5522/04/8851658.v2;https://figshare.com/articles/SynthCity_Dataset_-_Complete/8851658;CC BY 4.0",
    "group": "ucl",
    "groups": [
        {
            "name": "ucl"
        }
    ],
    "name": "9df55baf-92e3-5237-a629-05b867f4cb9b",
    "notes": [
        "With deep learning becoming a more prominent approach for automatic classification of three-dimensional point cloud data, a key bottleneck is the amount of high quality training data, especially when compared to that available for two-dimensional images. One potential solution is the use of synthetic data for pre-training networks, however the ability for models to generalise from synthetic data to real world data has been poorly studied for point clouds. Despite this, a huge wealth of 3D virtual environments exist, which if proved effective can be exploited. We therefore argue that research in this domain would be hugely useful. In this paper we present SynthCity an open dataset to help aid research. SynthCity is a 367.9M point synthetic full colour Mobile Laser Scanning point cloud. Every point is labelled from one of nine categories. We generate our point cloud in a typical Urban/Suburban environment using the Blensor plugin for Blender. See our project website http://www.synthcity.xyz or paper https://arxiv.org/abs/1907.04758 for more information."
    ],
    "oai_identifier": [
        "oai:figshare.com:article/8851658"
    ],
    "oai_set": [
        "category_179",
        "portal_549",
        "item_type_3",
        "month_year_07_2019"
    ],
    "state": "active",
    "tags": [
        {
            "name": "Artificial Intelligence Image Processing"
        },
        {
            "name": "lidar"
        },
        {
            "name": "point cloud"
        },
        {
            "name": "dataset"
        },
        {
            "name": "synthetic"
        }
    ],
    "title": [
        "SynthCity Dataset - Complete"
    ],
    "url": ""
}